Workbook

Sheet Data
A1: ID | B1: Start time | C1: Completion time | D1: Email | E1: Name | F1: BHR Name | G1: BHR Employee ID | H1: Date of Connect | I1: Engagement Type | J1: IBU/Practice/Location | K1: Mention your location {Ex. Noida} | L1: PRACTICE CODE (As per head count report) {Ex. DEA-D-2007} | M1: Band | N1: Engagement Mode | O1: Service Line | P1: EMPLOYEE IBU CODE (As per head count report) {Ex. DEA-D-4031} | Q1: PROJECT DESCRIPTION (As per head count report) {If Mixed then list down all the Project name/Practice/ SL} | R1: LSA Connect (In detail) | S1: Exclusive Award Ceremony (Not part of Townhall) (In detail) | T1: Cadence Connect | U1: CARES Framework | V1: Career | W1: Alignment | X1: Recognition | Y1: Empowerment | Z1: Strive | AA1: Townhall - Coverage | AB1: Townhall - Key Insight | AC1: Townhall - Action Plan | AD1: SL Induction - Coverage | AE1: SL Induction - Key Insight | AF1: SL Induction - Action Plan | AG1: Business Wait Connect - Coverage | AH1: Business Wait Connect - Key Insight | AI1: Business Wait Connect - Action Plan | AJ1: ELTP Connect (Practice Level) - Coverage | AK1: ELTP Connect (Practice Level) - Key Insight | AL1: ELTP Connect (Practice Level) - Action Plan | AM1: ELTP Connect (<6m) - Coverage | AN1: ELTP Connect (<6m) - Key Insight | AO1: ELTP Connect (<6m) - Action Plan | AP1: ELTP Connect (6-12m) - Coverage | AQ1: ELTP Connect (6-12m) - Key Insight | AR1: ELTP Connect (6-12m) - Action Plan | AS1: ELTP Connect (12-24m) - Coverage | AT1: ELTP Connect (12-24m) - Key Insight | AU1: ELTP Connect (12-24m) - Action Plan | AV1: HR Connect (Project Wise) - Coverage | AW1: HR Connect (Project Wise) - Key Insights | AX1: HR Connect (Project Wise) - Action Plan | AY1: HR Connect (General) - Coverage | AZ1: HR Connect (General) - Key Insights | BA1: HR Connect (General) - Action Plan | BB1: Top Talent Connect - Coverage | BC1: Top Talent Connect - Key Insights | BD1: Top Talent Connect - Action Plan | BE1: Top Talent FGD Connect - Coverage | BF1: Top Talent FGD Connect - Key Insights | BG1: Top Talent FGD Connect - Action Plan | BH1: New Joiner Connect (7 Days) - Coverage | BI1: New Joiner Connect (7 Days) - Key Insights | BJ1: New Joiner Connect (7 Days) - Action Plan | BK1: New Joiner Connect (30 Days) - Coverage | BL1: New Joiner Connect (30 Days) - Key Insights | BM1: New Joiner Connect (30 Days) - Action Plan | BN1: New Joiner Connect (60 Days) - Coverage | BO1: New Joiner Connect (60 Days) - Key Insights | BP1: New Joiner Connect (60 Days) - Action Plan | BQ1: New Joiner Connect (90 Days) - Coverage | BR1: New Joiner Connect (90 Days) - Key Insights | BS1: New Joiner Connect (90 Days) - Action Plan | BT1: ML Returnee Connect - Coverage | BU1: ML Returnee Connect - Key Insights | BV1: ML Returnee Connect - Action Plan | BW1: Skip Meeting - Coverage | BX1: Skip Meeting - Key Insights | BY1: Skip Meeting - Action Plan | BZ1: Women Associate Connect - Coverage | CA1: Women Associate Connect - Key Insights | CB1: Women Associate Connect - Action Plan | CC1: Band Specific FGD Connect - Coverage | CD1: Band Specific FGD Connect - Key Insights | CE1: Band Specific FGD Connect - Action Plan | CF1: Leadership Connect - Coverage | CG1: Leadership Connect - Key Insights | CH1: Leadership Connect - Action Plan | CI1: Josh (Fun Engagements) - Coverage | CJ1: Josh (Fun Engagements) - Key Insights | CK1: Josh (Fun Engagements) - Action Plan | CL1: Wellness Session - Coverage | CM1: Wellness Session - Key Insights | CN1: Wellness Session - Action Plan | CO1: ISR Activity - Coverage | CP1: ISR Activity - Key Insights | CQ1: ISR Activity - Action Plan | CR1: Overall Sentiment | CS1: Action Owner | CT1: Engagement related Queries | CU1: Severity | CV1: Status | CW1: IBU Level Connect (Points discussed if any) | CX1: SL Level Connect (Points discussed if any) | CY1: Practice Level Connect ( (Points discussed if any)
A2: 1 | B2: 46150.506 | C2: 46150.523 | D2: AK216739@techmahindra.com | E2: Anvi Konda | F2: Liam Chaudry | G2: 216739 | H2: 46142 | I2: Large Connect | J2: IBU Specific Connect | K2: Gudivada | L2: DEA-D-2003 | M2: MIX | N2: Virtual | O2: DEA Service Line | P2: DEA-D-2004 | Q2: Practice | U2: Alignment | W2: ML Returnee Connect | BT2: Review of ongoing concerns; | BU2: No major concerns raised;Minor process related queries; | BV2: NA;Continue regular check-ins; | CR2: Neutral | CS2: No specific Action, Issue addressed in meeting; | CT2: NA | CU2: Moderate | CV2: Closed
A3: 2 | B3: 46110.807 | C3: 46110.828 | D3: GK145561@techmahindra.com | E3: Girik Kamdar | F3: Girik Kamdar | G3: 145561 | H3: 46093 | I3: Large Connect | J3: Location Specific Connect | K3: Dibrugarh | L3: DEA-D-4021 | M3: U | N3: Virtual | O3: CIS Service Line | P3: DEA-D-4031 | Q3: EY Project | U3: Alignment | W3: Townhall | AA3: Business & Strategy Clarity;Career Visibility & Skill Roadmap;AI/future Readiness Messaging Is High-level; | AB3: Associates are unsure how unit goals translate into day-to-day delivery expectations; | AC3: Capture workload hotspots and review with delivery leads for rebalancing;NA; | CR3: Neutral | CS3: No specific Action, Issue addressed in meeting; | CU3: Moderate | CV3: Open
A4: 3 | B4: 46143.679 | C4: 46143.697 | D4: OK356702@techmahindra.com | E4: Oni Kannan | F4: Oni Kannan | G4: 356702 | H4: 46131 | I4: Large Connect | J4: Location Specific Connect | K4: Hyderabad | L4: DEA-D-4026 | M4: U | N4: In-person-Tech M | O4: DEA Service Line | P4: CIS D 2001 | Q4: Kimberly Clark | U4: Alignment | W4: SL Induction | AD4: Visibility on Allocation & Demand; | AE4: Associates lack clarity on practice goals and IBU priorities;HR/WFM/Training updates not actionable; | AF4: TLS SPOC had cleared all the queries w.r.t learning;Provide FAQs, guides, refresher sessions; | CR4: Positive | CS4: No specific Action, Issue addressed in meeting; | CT4: Team was contented with the fun connect as it was a nice short break from work and the whole account was able to connect virtually | CU4: Moderate | CV4: Closed
A5: 4 | B5: 46115.788 | C5: 46115.793 | D5: AD634277@techmahindra.com | E5: Abeer Dutta | F5: Abeer Dutta | G5: 634277 | H5: 46114 | I5: Location-Offshore | J5: IBU Specific Connect | K5: Mau | L5: NGS-D-2004 | M5: MIX | N5: Virtual | O5: DEA Service Line | P5: DEA-D-4022 | Q5: Rating Calibration call with IBU Head | U5: Alignment | W5: ML Returnee Connect | BT5: General wellbeing check-in; | BU5: Associates are settling in well;NA; | BV5: Share update with relevant stakeholder;Continue regular check-ins; | CR5: Positive | CS5: WFM;Delivery; | CT5: No response on IJP applied on Rapid | CU5: High | CV5: In-progress
A6: 5 | B6: 46084.515 | C6: 46084.532 | D6: GC632323@techmahindra.com | E6: Gayathri Chaudry | F6: Gayathri Chaudry | G6: 632323 | H6: 46080 | I6: FGD | J6: IBU Specific Connect | K6: Bengaluru | L6: DEA-D-4026 | M6: MIX | N6: Virtual | O6: DEA Service Line | P6: NGS-D-4037 | Q6: Keysight | U6: Alignment | W6: HR Connect (General) | AY6: Connect for recognition;Clarity On Role-based Learning Expectations;On Hybrid/WFO Rules And Monthly Compliance Expectations; | AZ6: Discussed on how to simply WFH exception requests and about various projects;NA; | BA6: Share role-based learning pathways and recommended certifications; | CR6: Positive | CS6: Delivery; | CT6: NA | CU6: Moderate | CV6: Closed
A7: 6 | B7: 46050.726 | C7: 46050.735 | D7: JP518373@techmahindra.com | E7: Jagrati Padmanabhan | F7: Jagrati Padmanabhan | G7: 518373 | H7: 46030 | I7: FGD | J7: Location Specific Connect | K7: Hyderabad | L7: DEA-D-2026 | M7: MIX | N7: Virtual | O7: DEA Service Line | P7: DEA-D-4032 | Q7: GE | U7: Career | V7: ELTP Connect (6-12m) | AP7: Business Context & Org Awareness; | AQ7: Feedback is irregular or not tied to a rubric; | AR7: Run fortnightly utilization reviews with WFM + delivery owners to rebalance work; | CR7: Positive | CS7: No specific Action, Issue addressed in meeting; | CT7: Need budget clarity | CU7: Low | CV7: Closed
A8: 7 | B8: 46143.99 | C8: 46144.003 | D8: TY946721@techmahindra.com | E8: Tripti Yadav | F8: Tripti Yadav | G8: 946721 | H8: 46140 | I8: Large Connect | J8: IBU Specific Connect | K8: Pune | L8: DEA- D-4023, DEA-D-4024, DEA-D-4025 | M8: MIX | N8: In-person-Client Location | O8: DEA Service Line | P8: DEA-D-4018 | Q8: TMC-D-1001- TMC ALL | U8: Alignment | W8: SL Induction | AD8: Business & Practice Awareness; | AE8: Low interaction and hesitation in raising questions; | AF8: Create consistent onboarding framework across practice;Provide FAQs, guides, refresher sessions; | CR8: Positive | CS8: No specific Action, Issue addressed in meeting; | CT8: Allocation related queries and opportunities | CU8: Moderate | CV8: In-progress | CY8: Practice level priorities and bench status reviewed.
A9: 8 | B9: 46056.582 | C9: 46056.583 | D9: FM197793@techmahindra.com | E9: Farhan Memon | F9: Farhan Memon | G9: 197793 | H9: 46049 | I9: Large Connect | J9: IBU Specific Connect | K9: Gangtok | L9: IIGA | M9: E | N9: Virtual | O9: DEA Service Line | P9: DEA-D-4016 | Q9: IBU Head of SNOW Europe | U9: Empowerment | Y9: Band Specific FGD Connect | CC9: Clarity on expectations;Review of ongoing concerns; | CD9: No major concerns raised; | CE9: Continue regular check-ins;NA; | CR9: Positive | CS9: No specific Action, Issue addressed in meeting; | CT9: All was resolved | CU9: Moderate | CV9: Closed | CW9: SALESFORCE PRACTICE
A10: 9 | B10: 46068.895 | C10: 46068.898 | D10: CK992697@techmahindra.com | E10: Chakradev Kari | F10: Chakradev Kari | G10: 992697 | H10: 46049 | I10: Large Connect | J10: Location Specific Connect | K10: Hyderabad | L10: DEA- D-4023, DEA-D-4024, DEA-D-4025 | M10: MIX | N10: Virtual | O10: DEA Service Line | P10: DEA-D-4026 | Q10: Kimberly Clark | U10: Empowerment | Y10: Women Associate Connect | BZ10: Recognition & Visibility;Grievance/speak-up Clarity;Empathy And Communication; | CA10: Need empathy and communication;Grievance/speak-up clarity; | CB10: There werenot much queries;Promote DEI initiatives; | CR10: Mixed | CS10: HRBP;Delivery; | CT10: NA | CU10: Low | CV10: Closed
A11: 10 | B11: 46174.899 | C11: 46174.908 | D11: VC172132@techmahindra.com | E11: Viraj Chaudhuri | F11: Viraj Chaudhuri | G11: 172132 | H11: 46163 | I11: FGD | J11: IBU Specific Connect | K11: Hyderbad | L11: all | M11: MIX | N11: In-person-Tech M | O11: DEA Service Line | P11: DIG-D-4001, DIG-D-4005, DIG-D-4007 | Q11: DEA BLR (Women Associates) | U11: Empowerment | Y11: Women Associate Connect | BZ11: Career Support & Sponsorship;Work-Life Balance & Flexibility; | CA11: Inclusive team practices; | CB11: Promote DEI initiatives;Reinforce speak-up channels; | CR11: Positive | CS11: Delivery; | CT11: RTO management and Bench | CU11: Low | CV11: In-progress
A12: 11 | B12: 46103.179 | C12: 46103.187 | D12: JG146228@techmahindra.com | E12: Janya Gaba | F12: Isha Kadakia | G12: 146228 | H12: 46099 | I12: 1:1 | J12: IBU Specific Connect | K12: PUNE | L12: DAI-D-2005 | M12: MIX | N12: Mix (Virtual & In-person) | O12: DEA Service Line | P12: COM D 4018 | Q12: SAP | U12: Career | V12: Top Talent FGD Connect | BE12: Review of ongoing concerns;Feedback on recent processes;Clarity on expectations; | BF12: NA; | BG12: Monitor and follow up in next cycle;NA; | CR12: Neutral | CS12: No specific Action, Issue addressed in meeting; | CU12: Low | CV12: In-progress
A13: 12 | B13: 46156.119 | C13: 46156.126 | D13: OW270395@techmahindra.com | E13: Onveer Walla | F13: Onveer Walla | G13: 270395 | H13: 46151 | I13: Location-Offshore | J13: IBU Specific Connect | K13: Kolkata | L13: NGS-D-2004 | M13: U | N13: In-person-Tech M | O13: CIS Service Line | P13: DEA-D-4001 | Q13: DIG-D-4005, DIG-D-4008, DIG-D-4009 | U13: Empowerment | Y13: Leadership Connect | CF13: AI Session;Review Cadence; | CG13: Need AI/skill readiness; | CH13: Publish budget guidelines;Identify hotspots; | CR13: Neutral | CS13: Delivery;HRBP; | CT13: NA | CU13: Moderate | CV13: Closed
A14: 13 | B14: 46166.878 | C14: 46166.892 | D14: TR519093@techmahindra.com | E14: Turvi Raghavan | F14: Turvi Raghavan | G14: 519093 | H14: 46149 | I14: FGD | J14: IBU Specific Connect | K14: Hyderbad | L14: DEA-D-2006 | M14: MIX | N14: In-person-Client Location | O14: DEA Service Line | P14: DEA-D-4040 | Q14: New Joiner Connect - 60 days | U14: Alignment | W14: New Joiner Connect (30 Days) | BK14: Role Expectation Clarity;Initial Engagement Level; | BL14: Most of the associates are undergoing trainings as there are FCTP's;Delay or lack of clarity in project onboarding; | BM14: Define timeline for project allocation (max 0 days);Ensure weekly : connect with manager; | CR14: Positive | CS14: HRBP;Delivery; | CT14: NA | CU14: Low | CV14: Closed
A15: 14 | B15: 46083.069 | C15: 46083.078 | D15: EB753425@techmahindra.com | E15: Ekta Bhalla | F15: Ekta Bhalla | G15: 753425 | H15: 46080 | I15: Floor Connect | J15: IBU Specific Connect | K15: PUNE | L15: DEA-D-4026 | M15: MIX | N15: Virtual | O15: DEA Service Line | P15: DEA-D-4019 | Q15: Scotia | U15: Empowerment | Y15: Women Associate Connect | BZ15: Learning & Skill Building;Grievance/speak-up Clarity;Inclusive Team Practices; | CA15: Inclusive team practices; | CB15: Promote DEI initiatives;There werenot much queries; | CR15: Neutral | CS15: Delivery; | CU15: Low | CV15: Closed
A16: 15 | B16: 46075.604 | C16: 46075.621 | D16: DR188914@techmahindra.com | E16: Diya Rattan | F16: Diya Rattan | G16: 188914 | H16: 46055 | I16: 1:1 | J16: IBU Specific Connect | K16: Hyderabad | L16: DEA-D-4021 | M16: MIX | N16: Virtual | O16: DEA Service Line | P16: DEA-D-2007 | Q16: Oracle HCM – UKG & Workday | U16: Alignment | W16: SL Induction | AD16: HR / WFM / Training Communication Effectiveness;Business & Practice Awareness; | AE16: HR/WFM/Training updates not actionable;NA; | AF16: Create consistent onboarding framework across practice; | CR16: Neutral | CS16: No specific Action, Issue addressed in meeting; | CT16: Bench guidelines are explained | CU16: Low | CV16: Closed
A17: 16 | B17: 46082.666 | C17: 46082.681 | D17: DK361303@techmahindra.com | E17: Divya Kala | F17: Divya Kala | G17: 361303 | H17: 46079 | I17: FGD | J17: Practice Specific Connect (Across IBU) | K17: Kolkata | L17: NWS-D-1001 | M17: MIX | N17: In-person-Tech M | O17: DEA Service Line | P17: NGS-D-4037 | Q17: SAP HLS | U17: Alignment | W17: HR Connect (Project Wise) | AV17: Timesheet Submission/approval Process Inconsistencies Create;Workload & Work-Life Balance;Manager Support & Local Leadership Effectiveness; | AW17: Timesheet submission/approval process inconsistencies create compliance risk; | AX17: Share project-specific policy FAQ (WFO, exceptions, leave, timesheet);Implement monthly recognition cadence (kudos, spotlight, customer praise); | CR17: Positive | CS17: No specific Action, Issue addressed in meeting; | CT17: NA | CU17: Moderate | CV17: Closed
A18: 17 | B18: 46153.429 | C18: 46153.439 | D18: TD827659@techmahindra.com | E18: Tara Dhar | F18: Tara Dhar | G18: 827659 | H18: 46147 | I18: Large Connect | J18: IBU Specific Connect | K18: PUNE | L18: DEA- D-4023, DEA-D-4024, DEA-D-4025 | M18: MIX | N18: Virtual | O18: NGS Service Line | P18: DEA-D-4032 | Q18: Suncorp Bank | U18: Career | V18: ELTP Connect (12-24m) | AS18: Internal Mobility / Rotation Opportunities;Recognition & Visibility of Growth;Career Progression & Next-Level Readiness; | AT18: Rotation/mobility interest is high but process and eligibility are unclear;na; | AU18: Highlight ELTP success stories + learning milestones in leadership forums/townhalls;Run structured mobility/rotation sessions with examples and process FAQs; | CR18: Positive | CS18: No specific Action, Issue addressed in meeting; | CU18: Low | CV18: Closed
A19: 18 | B19: 46082.144 | C19: 46082.16 | D19: AS660069@techmahindra.com | E19: Adya Sangha | F19: Janaki Kanda | G19: 660069 | H19: 46070 | I19: 1:1 | J19: Practice Specific Connect (Across IBU) | K19: Danapur | L19: NGS-D-2004 | M19: MIX | N19: Virtual | O19: DEA Service Line | P19: DEA-D-4016 | Q19: Location connect with DEA team. AI session by Natesh. | U19: Alignment | W19: New Joiner Connect (30 Days) | BK19: Project Allocation Clarity;Manager Connect Effectiveness; | BL19: Difficulty in understanding tools/processes;Associates undergoing project training; | BM19: Define timeline for project allocation (max 0 days);NA; | CR19: Negative | CS19: No specific Action, Issue addressed in meeting; | CT19: the associates had doubts related to the RTO guidelines and seat allocations | CU19: Moderate | CV19: Closed
A20: 19 | B20: 46123.875 | C20: 46123.882 | D20: ID232352@techmahindra.com | E20: Imaran Dua | F20: Imaran Dua | G20: 232352 | H20: 46120 | I20: 1:1 | J20: IBU Specific Connect | K20: Kolkata | L20: DEA-D-2006 | M20: MIX | N20: Mix (Virtual & In-person) | O20: DIG Vertical | P20: MFG-D-4003 | Q20: DIG-D-4005, DIG-D-4008, DIG-D-4009 | U20: Strive | Z20: Josh (Fun Engagements) | CI20: General wellbeing check-in;Discussion on team dynamics;Clarity on expectations; | CJ20: Minor process related queries;No major concerns raised; | CK20: No specific action required; | CR20: Neutral | CS20: Delivery; | CT20: NA | CU20: High | CV20: Closed | CX20: Discussed general SL level updates and priorities.
A21: 20 | B21: 46148.32 | C21: 46148.329 | D21: DR658623@techmahindra.com | E21: Devansh Rajan | F21: Devansh Rajan | G21: 658623 | H21: 46137 | I21: Large Connect | J21: Practice Specific Connect (Across IBU) | K21: Kavali | L21: NGS-D-2004 | M21: U | N21: Virtual | O21: Network Services Service Line | P21: DIG-D-1001 | Q21: OPTUS | U21: Alignment | W21: New Joiner Connect (60 Days) | BN21: Workload Management; | BO21: Skill gaps becoming visible during execution;The associates had questions around WFH and leaves.; | BP21: Mandate structured monthly feedback from manager;The associates had queries mainly related to WFH and leaves.; | CR21: Neutral | CS21: Delivery; | CU21: High | CV21: Closed
A22: 21 | B22: 46215.61 | C22: 46215.628 | D22: AC497399@techmahindra.com | E22: Advay Contractor | F22: Advay Contractor | G22: 497399 | H22: 46200 | I22: Location-Offshore | J22: IBU Specific Connect | K22: Mau | L22: DEA-D-40026 | M22: MIX | N22: In-person-Tech M | O22: DIG Vertical | P22: DEA-D-4001 | Q22: SAP MEA | U22: Career | V22: Top Talent Connect | BB22: Clarity on Org Changes & Priorities; | BC22: No hike/VP alignment with performance; | BD22: Run quarterly nominations; | CR22: Positive | CS22: HRBP; | CU22: Moderate | CV22: Closed
A23: 22 | B23: 46054.159 | C23: 46054.173 | D23: NS656711@techmahindra.com | E23: Nakul Setty | F23: Nakul Setty | G23: 656711 | H23: 46037 | I23: FGD | J23: Practice Specific Connect (Across IBU) | K23: Firozabad | L23: DEA-D-40026 | M23: MIX | N23: In-person-Tech M | O23: DEA Service Line | P23: IFS | Q23: SALESFORCE PRACTICE | U23: Empowerment | Y23: Women Associate Connect | BZ23: Empathy And Communication; | CA23: Inclusive team practices;Need flexible arrangements during caregiving; | CB23: Leadership acknowledgment;There werenot much queries; | CR23: Positive | CS23: No specific Action, Issue addressed in meeting; | CT23: NA | CU23: Moderate | CV23: Closed
A24: 23 | B24: 46211.187 | C24: 46211.204 | D24: YC889359@techmahindra.com | E24: Yashica Cherian | F24: Yashica Cherian | G24: 889359 | H24: 46211 | I24: 1:1 | J24: IBU Specific Connect | K24: Chennai | L24: DEA- D-4023, DEA-D-4024, DEA-D-4025 | M24: MIX | N24: In-person-Tech M | O24: DEA Service Line | P24: CIS D 4001,4004,4025,4026 | Q24: NGS-D-4037 | U24: Alignment | W24: Townhall | AA24: Business & Strategy Clarity; | AB24: Associates are unsure how unit goals translate into day-to-day delivery expectations;associates seek practical relevance; | AC24: Publish role-based learning paths (beginner/intermediate/advanced) with links; | CR24: Neutral | CS24: Delivery; | CT24: No Projects for New Joiners in Bench | CU24: Low | CV24: Closed | CW24: Discussed regarding MCares Dissemination, attrition and diversity. IBU Head was happy with progress made so far. | CY24: Practice level priorities and bench status reviewed.
A25: 24 | B25: 46192.685 | C25: 46192.694 | D25: YI696251@techmahindra.com | E25: Yashica Issac | F25: Yashica Issac | G25: 696251 | H25: 46173 | I25: Leadership Connect | J25: IBU Specific Connect | K25: Hyderabad | L25: DEA-D-40026 | M25: MIX | N25: Virtual | O25: DEA Service Line | P25: CIS D 4001,4004,4025,4026 | Q25: DIG-D-4005, DIG-D-4008, DIG-D-4009 | U25: Career | V25: ELTP Connect (Practice Level) | AJ25: Engagement & Motivation Across Stages;Career Clarity & Growth Continuity;Allocation & Deployment Transparency; | AK25: Inconsistent visibility on allocation timelines and decision-making creates confusion across all ELTP groups; | AL25: Work with work force management and delivery closely to ensure the ELTP associates are mapped to projects once their trainings are completed;Introduce ELTP engagement framework by stage: 0–6M → onboarding support, 6–M → performance alignment, –M → growth & retention; | CR25: Positive | CS25: No specific Action, Issue addressed in meeting; | CT25: NA | CU25: Low | CV25: In-progress
A26: 25 | B26: 46061.694 | C26: 46061.699 | D26: AN378535@techmahindra.com | E26: Aadi Naik | F26: Aadi Naik | G26: 378535 | H26: 46059 | I26: Large Connect | J26: Practice Specific Connect (Across IBU) | K26: Hyderbad | L26: NWS-D-1001 | M26: MIX | N26: In-person-Tech M | O26: DIG Vertical | P26: DEA-D-4001 | Q26: Practice | U26: Alignment | W26: New Joiner Connect (90 Days) | BQ26: Career Path Visibility; | BR26: seat allocation;Lack of awareness of internal opportunities; | BS26: Align role expectations vs aspiration through discussion;shared CS SPOC details; | CR26: Positive | CS26: Delivery; | CT26: aNA | CU26: High | CV26: Open
A27: 26 | B27: 46122.979 | C27: 46122.998 | D27: JM283700@techmahindra.com | E27: Janani Mohanty | F27: Janani Mohanty | G27: 283700 | H27: 46102 | I27: FGD | J27: IBU Specific Connect | K27: PUNE | L27: TMC-D-1001 | M27: P | N27: Virtual | O27: DEA Service Line | P27: DEA-D-4009 | Q27: Scotia | U27: Career | V27: Top Talent Connect | BB27: For Role Rotation (PM/PGM/architect);Recognition Equity & Visibility; | BC27: No hike/VP alignment with performance; | BD27: Not happy with no hike; | CR27: Positive | CS27: No specific Action, Issue addressed in meeting; | CT27: NA | CU27: High | CV27: In-progress
A28: 27 | B28: 46077.503 | C28: 46077.506 | D28: FC296694@techmahindra.com | E28: Farhan Chada | F28: Farhan Chada | G28: 296694 | H28: 46058 | I28: Floor Connect | J28: IBU Specific Connect | K28: Hyderabad | L28: DEA-D-40026 | M28: MIX | N28: Mix (Virtual & In-person) | O28: DEA Service Line | P28: DIG-D-4005 | Q28: Paragon | U28: Career | V28: ELTP Connect (6-12m) | AP28: Business Context & Org Awareness; | AQ28: slows improvement; | AR28: Run fortnightly utilization reviews with WFM + delivery owners to rebalance work; | CR28: Positive | CS28: Supervisor; | CT28: Queries were related to AI being implemented in day-to-day projects practically to which leader had addressed that specific agents are identified at DEA level to work with and implement changes. | CU28: High | CV28: Closed
A29: 28 | B29: 46167.386 | C29: 46167.404 | D29: JD386706@techmahindra.com | E29: Jeremiah Dave | F29: Jeremiah Dave | G29: 386706 | H29: 46152 | I29: Induction | J29: IBU Specific Connect | K29: PUNE | L29: DEA-D-2007 | M29: E | N29: Virtual | O29: NGS Service Line | P29: NWS-D-4001 | Q29: Bench connect for the IBUs | U29: Alignment | W29: New Joiner Connect (60 Days) | BN29: Team Integration;Queries related to BGV check; | BO29: NA; | BP29: NA;The associates had queries mainly related to WFH and leaves.; | CR29: Negative | CS29: No specific Action, Issue addressed in meeting; | CT29: NA | CU29: Moderate | CV29: Closed
A30: 29 | B30: 46154.216 | C30: 46154.222 | D30: AW831380@techmahindra.com | E30: Alka Wable | F30: Alka Wable | G30: 831380 | H30: 46142 | I30: Large Connect | J30: Practice Specific Connect (Across IBU) | K30: Rajpur Sonarpur | L30: TMC-D-1001 | M30: MIX | N30: In-person-Tech M | O30: DEA Service Line | P30: DIG-D-4001, DIG-D-4005, DIG-D-4007 | Q30: ZF Consultancy | U30: Empowerment | Y30: Women Associate Connect | BZ30: Career Support & Sponsorship;Empathy And Communication; | CA30: Upskilling for future roles;Female assocaites in Haleon office are quite happy with the setup; | CB30: Leadership acknowledgment;Reinforce speak-up channels; | CR30: Neutral | CS30: No specific Action, Issue addressed in meeting; | CT30: NA | CU30: High | CV30: Closed
A31: 30 | B31: 46203.344 | C31: 46203.354 | D31: DR781403@techmahindra.com | E31: Devika Rastogi | F31: Raksha Varughese | G31: 781403 | H31: 46193 | I31: Location-Offshore | J31: Location Specific Connect | K31: Kolkata | L31: TMC-D-1001 | M31: U | N31: Virtual | O31: DEA Service Line | P31: DIG-D-1001 | Q31: ServiceNow Practice | U31: Empowerment | Y31: Women Associate Connect | BZ31: Career Support & Sponsorship;Inclusive Team Practices;Work-Life Balance & Flexibility; | CA31: Need empathy and communication; | CB31: Reinforce speak-up channels; | CR31: Neutral | CS31: No specific Action, Issue addressed in meeting; | CT31: None | CU31: Moderate | CV31: Closed
A32: 31 | B32: 46116.204 | C32: 46116.209 | D32: UB278240@techmahindra.com | E32: Umang Bhatt | F32: Umang Bhatt | G32: 278240 | H32: 46097 | I32: Location-Offshore | J32: IBU Specific Connect | K32: Jaipur | L32: DEA-D-2005 | M32: MIX | N32: Virtual | O32: DEA Service Line | P32: DIG-D-4001, DIG-D-4005, DIG-D-4007 | Q32: Adani | U32: Empowerment | Y32: Band Specific FGD Connect | CC32: Review of ongoing concerns;Feedback on recent processes; | CD32: Minor process related queries; | CE32: No specific action required;Monitor and follow up in next cycle; | CR32: Neutral | CS32: No specific Action, Issue addressed in meeting; | CT32: NA | CU32: Moderate | CV32: Closed
A33: 32 | B33: 46141.176 | C33: 46141.191 | D33: TA410244@techmahindra.com | E33: Thomas Amble | F33: Thomas Amble | G33: 410244 | H33: 46132 | I33: Large Connect | J33: Practice Specific Connect (Across IBU) | K33: Bengaluru | L33: DEA- D-4023, DEA-D-4024, DEA-D-4025 | M33: E | N33: In-person-Tech M | O33: CIS Service Line | P33: SAP Retail | Q33: IFS SELL TO | S33: Distributed TMC specific Swag Kit | U33: Recognition | X33: Exclusive Award Ceremony | CR33: Positive | CS33: No specific Action, Issue addressed in meeting; | CT33: NA | CU33: Low | CV33: Closed
A34: 33 | B34: 46046.756 | C34: 46046.758 | D34: VB423939@techmahindra.com | E34: Veer Bir | F34: Veer Bir | G34: 423939 | H34: 46045 | I34: 1:1 | J34: Practice Specific Connect (Across IBU) | K34: Bathinda | L34: DEA-D-4021 | M34: MIX | N34: Virtual | O34: DEA Service Line | P34: MFG-N-4007 | Q34: SAP | U34: Empowerment | Y34: Skip Meeting | BW34: Timely Policy/process Updates;Manager Effectiveness & Delegation;Communication & Transparency; | BX34: Need timely policy/process updates;Need clarity on growth opportunities; | BY34: Set comms cadence;Standardize messaging; | CR34: Mixed | CS34: No specific Action, Issue addressed in meeting; | CT34: tracker | CU34: Low | CV34: Open | CW34: SALESFORCE PRACTICE
A35: 34 | B35: 46046.731 | C35: 46046.733 | D35: AS377304@techmahindra.com | E35: Arya Sunder | F35: Arya Sunder | G35: 377304 | H35: 46032 | I35: FGD | J35: Practice Specific Connect (Across IBU) | K35: Panvel | L35: IIGA | M35: U | N35: Mix (Virtual & In-person) | O35: DEA Service Line | P35: DEA-D-2004 | Q35: Oracle HCM – UKG & Workday | U35: Career | V35: ELTP Connect (<6m) | AM35: Review of ongoing concerns;Feedback on recent processes; | AN35: Minor process related queries; | AO35: Share update with relevant stakeholder;NA; | CR35: Positive | CS35: HRBP;Delivery; | CU35: Moderate | CV35: In-progress
A36: 35 | B36: 46057.948 | C36: 46057.967 | D36: XS830316@techmahindra.com | E36: Xavier Solanki | F36: Xavier Solanki | G36: 830316 | H36: 46044 | I36: 1:1 | J36: Practice Specific Connect (Across IBU) | K36: Bhubaneswar | L36: TMC-D-1001 | M36: MIX | N36: Mix (Virtual & In-person) | O36: DEA Service Line | P36: DIG-D-4005 | Q36: Mixed | U36: Alignment | W36: New Joiner Connect (90 Days) | BQ36: Internal Growth Opportunities; | BR36: seat allocation; | BS36: Share internal job/cross-skill opportunities;Align role expectations vs aspiration through discussion; | CR36: Positive | CS36: No specific Action, Issue addressed in meeting; | CT36: NA | CU36: Low | CV36: Closed
A37: 36 | B37: 46181.183 | C37: 46181.203 | D37: GC449709@techmahindra.com | E37: Girindra Chatterjee | F37: Girindra Chatterjee | G37: 449709 | H37: 46177 | I37: Floor Connect | J37: IBU Specific Connect | K37: Hyderabad | L37: DEA-D-2007 | M37: U | N37: Virtual | O37: DIG Vertical | P37: MFG-N-4007 | Q37: SAP Sell To | U37: Career | V37: ELTP Connect (12-24m) | AS37: Career Progression & Next-Level Readiness; | AT37: ELTPs want clarity on progression timelines and competencies for the next band/role;na; | AU37: Highlight ELTP success stories + learning milestones in leadership forums/townhalls; | CR37: Positive | CS37: HRBP; | CU37: Moderate | CV37: Closed
A38: 37 | B38: 46154.076 | C38: 46154.088 | D38: PR570050@techmahindra.com | E38: Pallavi Roy | F38: Pallavi Roy | G38: 570050 | H38: 46138 | I38: 1:1 | J38: IBU Specific Connect | K38: Meerut | L38: DEA- D-4023, DEA-D-4024, DEA-D-4025 | M38: MIX | N38: In-person-Tech M | O38: DEA Service Line | P38: DEA-D-4008 | Q38: OPTUS | U38: Alignment | W38: Townhall | AA38: Leadership Communication & Q&A Effectiveness; | AB38: Org/structural updates are heard but not fully understood (what changes for me?);Need clearer articulation of business direction and priorities for the quarter; | AC38: NA; | CR38: Neutral | CS38: No specific Action, Issue addressed in meeting; | CT38: Open house connect for offshore | CU38: Low | CV38: Closed
A39: 38 | B39: 46156.701 | C39: 46156.71 | D39: DR499407@techmahindra.com | E39: Darsh Rau | F39: Darsh Rau | G39: 499407 | H39: 46140 | I39: FGD | J39: IBU Specific Connect | K39: Bhubaneswar | L39: DEA-D-2007 | M39: MIX | N39: In-person-Tech M | O39: DEA Service Line | P39: NGS-D-4018 | Q39: OPTUS | U39: Alignment | W39: SL Induction | AD39: HR / WFM / Training Communication Effectiveness;Engagement with Leadership & Confidence Level; | AE39: Associates unclear how their role contributes to business;Associates lack clarity on practice goals and IBU priorities; | AF39: Checked the action plan for pending allocation of new joiners and highlighted to IBU head and it was closed;TLS SPOC had cleared all the queries w.r.t learning; | CR39: Neutral | CS39: No specific Action, Issue addressed in meeting; | CT39: NA | CU39: High | CV39: Closed
A40: 39 | B40: 46166.712 | C40: 46166.716 | D40: YH530764@techmahindra.com | E40: Yuvraj Handa | F40: Yuvraj Handa | G40: 530764 | H40: 46153 | I40: Location-Offshore | J40: Practice Specific Connect (Across IBU) | K40: Hyderbad | L40: DIG-D-4002, 4003, 4007,4009 | M40: MIX | N40: Virtual | O40: DEA Service Line | P40: DEA-D-4023 | Q40: GE | U40: Empowerment | Y40: Skip Meeting | BW40: Manager Effectiveness & Delegation;Communication & Transparency;Learning/cert Support Requests; | BX40: Need timely policy/process updates; | BY40: Team recognition cadence; | CR40: Mixed | CS40: WFM; | CU40: Low | CV40: Closed
A41: 40 | B41: 46068.515 | C41: 46068.53 | D41: LS789275@techmahindra.com | E41: Logan Sami | F41: Logan Sami | G41: 789275 | H41: 46064 | I41: Floor Connect | J41: Location Specific Connect | K41: Alwar | L41: all | M41: MIX | N41: Virtual | O41: DEA Service Line | P41: DEA-D-4015 | Q41: Keysight | R41: 20 Years Long service anniversary celebration of Dharmateja Chava - 243623 at HYD location | U41: Recognition | X41: LSA Connect | CR41: Positive | CS41: HRBP; | CU41: Moderate | CV41: Closed
A42: 41 | B42: 46118.237 | C42: 46118.251 | D42: SC219346@techmahindra.com | E42: Saanvi Chaudhari | F42: Saanvi Chaudhari | G42: 219346 | H42: 46115 | I42: Large Connect | J42: Practice Specific Connect (Across IBU) | K42: Hyderbad | L42: DEA- D-4023, DEA-D-4024, DEA-D-4025 | M42: MIX | N42: In-person-Client Location | O42: DEA Service Line | P42: DEA -D-4020 | Q42: IFS project [bench guidelines policy, WFO GUIDLINES ] | U42: Empowerment | Y42: Women Associate Connect | BZ42: Grievance/speak-up Clarity;Work-Life Balance & Flexibility; | CA42: Female assocaites in Haleon office are quite happy with the setup; | CB42: There werenot much queries;Leadership acknowledgment; | CR42: Positive | CS42: No specific Action, Issue addressed in meeting; | CT42: NA | CU42: Low | CV42: Closed
A43: 42 | B43: 46043.032 | C43: 46043.044 | D43: GK181644@techmahindra.com | E43: Girik Khalsa | F43: Girik Khalsa | G43: 181644 | H43: 46025 | I43: FGD | J43: IBU Specific Connect | K43: Hyderbad | L43: DEA-D-2004 | M43: MIX | N43: Mix (Virtual & In-person) | O43: DEA Service Line | P43: DEA-N-4011 | Q43: OPTUS | U43: Empowerment | Y43: Skip Meeting | BW43: Recognition & Motivation; | BX43: Need clarity on growth opportunities; | BY43: Team recognition cadence;Standardize messaging; | CR43: Positive | CS43: No specific Action, Issue addressed in meeting; | CU43: Moderate | CV43: Closed
A44: 43 | B44: 46064.153 | C44: 46064.173 | D44: VK466346@techmahindra.com | E44: Vasana Kala | F44: Vasana Kala | G44: 466346 | H44: 46044 | I44: Floor Connect | J44: IBU Specific Connect | K44: Allahabad | L44: DEA-D-2007 | M44: MIX | N44: Virtual | O44: DIG Vertical | P44: CIS D 4001,4004,4025,4026 | Q44: ELTP Connect | U44: Empowerment | Y44: Band Specific FGD Connect | CC44: Review of ongoing concerns;Clarity on expectations; | CD44: Associates are settling in well;No major concerns raised; | CE44: NA;Share update with relevant stakeholder; | CR44: Positive | CS44: No specific Action, Issue addressed in meeting; | CU44: Low | CV44: Closed
A45: 44 | B45: 46063.848 | C45: 46063.851 | D45: ML775981@techmahindra.com | E45: Madhavi Lanka | F45: Madhavi Lanka | G45: 775981 | H45: 46061 | I45: 1:1 | J45: IBU Specific Connect | K45: Bengaluru | L45: NWS-D-1001 | M45: E | N45: Virtual | O45: DEA Service Line | P45: DEA-D-4040 | Q45: Oracle HCM – UKG & Workday | U45: Alignment | W45: Townhall | AA45: AI/future Readiness Messaging Is High-level;Career Visibility & Skill Roadmap; | AB45: Associates seek clarity on role progression and career paths within the unit; | AC45: Add ‘Wall of Fame’ segment: delivery wins, customer shoutouts, milestone highlights; | CR45: Neutral | CS45: Supervisor; | CT45: NA | CU45: Moderate | CV45: Open
A46: 45 | B46: 46202.906 | C46: 46202.909 | D46: BS927564@techmahindra.com | E46: Bhavika Sampath | F46: Bhavika Sampath | G46: 927564 | H46: 46192 | I46: Large Connect | J46: IBU Specific Connect | K46: Hyderbad | L46: DEA-D-40026 | M46: MIX | N46: Virtual | O46: NGS Service Line | P46: NWS-D-4001 | Q46: DIG-D-4001, DIG-D-4005, DIG-D-4007 | U46: Alignment | W46: HR Connect (Project Wise) | AV46: Policy & Process Clarity;Strategic Connect; | AW46: Seat availability and office logistics impact productivity; | AX46: Coach managers on feedback, delegation, and communication; | CR46: Positive | CS46: Delivery; | CU46: Low | CV46: Open | CW46: SALESFORCE PRACTICE
A47: 46 | B47: 46160.94 | C47: 46160.954 | D47: MG479404@techmahindra.com | E47: Mohammed Gupta | F47: Teerth Bhardwaj | G47: 479404 | H47: 46151 | I47: Large Connect | J47: IBU Specific Connect | K47: Pune | L47: DEA-D-2007 | M47: MIX | N47: Virtual | O47: DEA Service Line | P47: NGS-D-4038 | Q47: WSS | U47: Career | V47: ELTP Connect (12-24m) | AS47: Recognition & Visibility of Growth;Career Progression & Next-Level Readiness;Internal Mobility / Rotation Opportunities; | AT47: na; | AU47: Highlight ELTP success stories + learning milestones in leadership forums/townhalls;Run structured mobility/rotation sessions with examples and process FAQs; | CR47: Positive | CS47: Delivery; | CT47: Improve Hybrid compliance, IBU heads need to validate the data and share action plan | CU47: Low | CV47: Closed
A48: 47 | B48: 46139.51 | C48: 46139.526 | D48: DB398768@techmahindra.com | E48: Dipta Bhandari | F48: Dipta Bhandari | G48: 398768 | H48: 46125 | I48: Large Connect | J48: IBU Specific Connect | K48: Pune | L48: DEA-D-2007 | M48: MIX | N48: Mix (Virtual & In-person) | O48: Engg Services Service Line | P48: DEA-D-4022 | Q48: USA TTLH | U48: Alignment | W48: New Joiner Connect (60 Days) | BN48: Team Integration;Role Confidence Level;Feedback Mechanism; | BO48: Skill gaps becoming visible during execution; | BP48: Include in team rituals (scrum, meetings, discussions); | CR48: Positive | CS48: No specific Action, Issue addressed in meeting; | CT48: NA | CU48: Low | CV48: Closed
A49: 48 | B49: 46042.95 | C49: 46042.962 | D49: YW638289@techmahindra.com | E49: Yadavi Wali | F49: Dakshesh Trivedi | G49: 638289 | H49: 46029 | I49: Large Connect | J49: Location Specific Connect | K49: Kolkata | L49: DAI-D-2005 | M49: MIX | N49: Virtual | O49: DEA Service Line | P49: DEA-D-4016 | Q49: Cadence with IBU Head. | U49: Alignment | W49: Townhall | AA49: AI/future Readiness Messaging Is High-level;Career Visibility & Skill Roadmap; | AB49: Associates seek clarity on role progression and career paths within the unit; | AC49: Capture workload hotspots and review with delivery leads for rebalancing; | CR49: Neutral | CS49: No specific Action, Issue addressed in meeting; | CT49: Queries with regards with access card were raised. | CU49: Low | CV49: Closed
A50: 49 | B50: 46048.42 | C50: 46048.435 | D50: EB862560@techmahindra.com | E50: Ekapad Bir | F50: Ekapad Bir | G50: 862560 | H50: 46035 | I50: Large Connect | J50: IBU Specific Connect | K50: Bengaluru | L50: DEA-D-2026 | M50: MIX | N50: In-person-Tech M | O50: DEA Service Line | P50: CIS-D-4007 | Q50: Paragon Project | U50: Alignment | W50: Townhall | AA50: Recognition Visibility;Work-Life & Sustainability Signals;Business & Strategy Clarity; | AB50: NA; | AC50: Add a ‘What changes for teams’ section with 3–5 concrete takeaways;Publish role-based learning paths (beginner/intermediate/advanced) with links; | CR50: Positive | CS50: Delivery; | CT50: NA | CU50: Low | CV50: Closed | CW50: SALESFORCE PRACTICE | CY50: Practice level priorities and bench status reviewed.
A51: 50 | B51: 46157.038 | C51: 46157.053 | D51: ND121322@techmahindra.com | E51: Netra Dar | F51: Netra Dar | G51: 121322 | H51: 46142 | I51: Large Connect | J51: IBU Specific Connect | K51: Bengaluru | L51: DIG-D-4002, 4003, 4007,4009 | M51: U | N51: Virtual | O51: DIG Vertical | P51: DIG-D-1001 | Q51: DEA BLR (Women Associates) | U51: Recognition | X51: NA | CR51: Positive | CS51: No specific Action, Issue addressed in meeting; | CT51: NA | CU51: High | CV51: Closed | CW51: IBU Head liked the concept of Cadence and appreciated the efforts we are putting into publishing this data. He also wanted to work on retention strategies and diversity going forward.
A52: 51 | B52: 46205.658 | C52: 46205.661 | D52: BB850827@techmahindra.com | E52: Balveer Bumb | F52: Balveer Bumb | G52: 850827 | H52: 46191 | I52: Large Connect | J52: IBU Specific Connect | K52: Bengaluru | L52: DEA-D-4026 | M52: E | N52: Virtual | O52: Comms Vertical | P52: DEA-D-4028 | Q52: Oracle HCM – UKG & Workday | U52: Alignment | W52: HR Connect (General) | AY52: On Hybrid/WFO Rules And Monthly Compliance Expectations;Queries On Performance Cycle Steps And Deadlines; | AZ52: Need simplified updates on policy changes and timelines; | BA52: Feedback to be shared with IBU head;NA; | CR52: Positive | CS52: No specific Action, Issue addressed in meeting; | CT52: NA | CU52: Moderate | CV52: Closed
A53: 52 | B53: 46110.315 | C53: 46110.323 | D53: AJ940064@techmahindra.com | E53: Advika Jayaraman | F53: William Lanka | G53: 940064 | H53: 46097 | I53: Large Connect | J53: IBU Specific Connect | K53: Hyderbad | L53: DEA-D-4026 | M53: MIX | N53: Virtual | O53: DEA Service Line | P53: DEA-D-4021 | Q53: SAP Sell To - Non PS | U53: Alignment | W53: HR Connect (Project Wise) | AV53: Timesheet Submission/approval Process Inconsistencies Create;Recognition & Engagement within Project;On Leave/comp-off Due To Client Calendar Mismatches; | AW53: associates want clear routes; | AX53: NA;Define issue escalation ladder and response SLAs; | CR53: Positive | CS53: CS; | CT53: Allocation related queries and opportunities | CU53: Low | CV53: Closed
A54: 53 | B54: 46106.037 | C54: 46106.039 | D54: TM249715@techmahindra.com | E54: Tanvi Mutti | F54: Tanvi Mutti | G54: 249715 | H54: 46092 | I54: Large Connect | J54: IBU Specific Connect | K54: Kolkata | L54: DIG-D-4002, 4003, 4007,4009 | M54: MIX | N54: Virtual | O54: DEA Service Line | P54: DIG-D-4003 | Q54: New Joiners Connect - 60 Days | U54: Empowerment | Y54: Skip Meeting | BW54: Communication & Transparency;Learning/cert Support Requests; | BX54: Need timely policy/process updates;Need clarity on growth opportunities; | BY54: Set comms cadence;Team recognition cadence; | CR54: Positive | CS54: No specific Action, Issue addressed in meeting; | CT54: NA | CU54: Moderate | CV54: In-progress
A55: 54 | B55: 46203.363 | C55: 46203.381 | D55: AS615060@techmahindra.com | E55: Aditya Shanker | F55: Aditya Shanker | G55: 615060 | H55: 46199 | I55: Location-Offshore | J55: IBU Specific Connect | K55: Pune | L55: DEA-D-2003 | M55: U | N55: Mix (Virtual & In-person) | O55: Engg Services Service Line | P55: DIG-D-4001, DIG-D-4005, DIG-D-4007 | Q55: MIX | U55: Alignment | W55: ML Returnee Connect | BT55: Discussion on team dynamics;Review of ongoing concerns;General wellbeing check-in; | BU55: Associates are settling in well; | BV55: NA; | CR55: Mixed | CS55: HRBP; | CU55: Moderate | CV55: Closed | CX55: Discussed general SL level updates and priorities.
A56: 55 | B56: 46147.172 | C56: 46147.176 | D56: EY168941@techmahindra.com | E56: Ethan Yogi | F56: Ethan Yogi | G56: 168941 | H56: 46132 | I56: 1:1 | J56: Practice Specific Connect (Across IBU) | K56: Bhubaneswar | L56: DEA-D-2005 | M56: P | N56: Virtual | O56: DEA Service Line | P56: DIG-D-4003 | Q56: Rating Calibration Call | U56: Alignment | W56: ML Returnee Connect | BT56: Review of ongoing concerns;Feedback on recent processes;General wellbeing check-in; | BU56: Positive feedback overall;NA; | BV56: No specific action required; | CR56: Positive | CS56: No specific Action, Issue addressed in meeting; | CT56: NA | CU56: Moderate | CV56: Open
A57: 56 | B57: 46072.703 | C57: 46072.72 | D57: KP677599@techmahindra.com | E57: Kevin Palla | F57: Kevin Palla | G57: 677599 | H57: 46052 | I57: FGD | J57: IBU Specific Connect | K57: Chennai | L57: DEA-D-2005 | M57: MIX | N57: Virtual | O57: NGS Service Line | P57: DEA-D-4011 | Q57: SAP Manufacturing | U57: Career | V57: ELTP Connect (12-24m) | AS57: Career Progression & Next-Level Readiness; | AT57: na; | AU57: Highlight ELTP success stories + learning milestones in leadership forums/townhalls;Run structured mobility/rotation sessions with examples and process FAQs; | CR57: Positive | CS57: No specific Action, Issue addressed in meeting; | CT57: Team will start having SAP Syniti related training shortly | CU57: Moderate | CV57: Open
A58: 57 | B58: 46194.574 | C58: 46194.582 | D58: KM575575@techmahindra.com | E58: Kala Mane | F58: Raksha Mittal | G58: 575575 | H58: 46193 | I58: Large Connect | J58: IBU Specific Connect | K58: Kolkata | L58: DEA-D-2005 | M58: MIX | N58: In-person-Tech M | O58: DIG Vertical | P58: NWS-D-4001 | Q58: MIX | U58: Strive | Z58: Josh (Fun Engagements) | CI58: Review of ongoing concerns;General wellbeing check-in; | CJ58: No major concerns raised;Minor process related queries; | CK58: Monitor and follow up in next cycle; | CR58: Positive | CS58: No specific Action, Issue addressed in meeting; | CT58: NA | CU58: High | CV58: Closed | CW58: DEA-D-4011, Suresh Boddu
A59: 58 | B59: 46145.442 | C59: 46145.46 | D59: CC427905@techmahindra.com | E59: Chandani Chawla | F59: Chandani Chawla | G59: 427905 | H59: 46140 | I59: FGD | J59: IBU Specific Connect | K59: Hyderbad | L59: TMC-D-1001 | M59: MIX | N59: Mix (Virtual & In-person) | O59: DEA Service Line | P59: DEA-D-2007 | Q59: Ford | U59: Alignment | W59: Townhall | AA59: Career Visibility & Skill Roadmap; | AB59: associates seek practical relevance;Associates seek clarity on role progression and career paths within the unit; | AC59: Share a 1-page business snapshot (targets, priorities, key wins) post townhall; | CR59: Positive | CS59: No specific Action, Issue addressed in meeting; | CU59: Moderate | CV59: Closed
A60: 59 | B60: 46205.172 | C60: 46205.18 | D60: AD177103@techmahindra.com | E60: Aishani D’Alia | F60: Aishani D’Alia | G60: 177103 | H60: 46191 | I60: Floor Connect | J60: IBU Specific Connect | K60: Bhubaneswar | L60: DEA-D-2005 | M60: P | N60: Virtual | O60: DIG Vertical | P60: DEA-D-4011 | Q60: SAP MEA | U60: Empowerment | Y60: Women Associate Connect | BZ60: Learning & Skill Building; | CA60: Need equitable recognition;Female assocaites in Haleon office are quite happy with the setup; | CB60: Leadership acknowledgment; | CR60: Positive | CS60: No specific Action, Issue addressed in meeting; | CU60: Low | CV60: Closed
A61: 60 | B61: 46196.189 | C61: 46196.205 | D61: AM875232@techmahindra.com | E61: Anita Manda | F61: Anita Manda | G61: 875232 | H61: 46178 | I61: FGD | J61: Practice Specific Connect (Across IBU) | K61: Hyderbad | L61: TMC-D-1001 | M61: U | N61: Virtual | O61: DEA Service Line | P61: DEA-D-4019 | Q61: SAP PS- Connect with P&I team | U61: Alignment | W61: Townhall | AA61: Leadership Communication & Q&A Effectiveness;Career Visibility & Skill Roadmap;Business & Strategy Clarity; | AB61: associates seek practical relevance; | AC61: Publish role-based learning paths (beginner/intermediate/advanced) with links; | CR61: Neutral | CS61: Delivery; | CT61: Had a walkthrough of the DEA line and provided an overview of the following: RTO (Return to Office) guidelines Timesheet process Training structure Medical insurance details | CU61: High | CV61: Closed
A62: 61 | B62: 46144.192 | C62: 46144.204 | D62: SL428930@techmahindra.com | E62: Samar Lalla | F62: Samar Lalla | G62: 428930 | H62: 46131 | I62: 1:1 | J62: IBU Specific Connect | K62: Pune | L62: DEA- D-4023, DEA-D-4024, DEA-D-4025 | M62: MIX | N62: Virtual | O62: DEA Service Line | P62: DIG-D-4001, DIG-D-4005, DIG-D-4007 | Q62: PEGA | U62: Alignment | W62: New Joiner Connect (30 Days) | BK62: Project Allocation Clarity; | BL62: Most of the associates are undergoing trainings as there are FCTP's;Difficulty in understanding tools/processes; | BM62: NA;Ensure weekly : connect with manager; | CR62: Positive | CS62: No specific Action, Issue addressed in meeting; | CU62: High | CV62: Closed
A63: 62 | B63: 46126.046 | C63: 46126.054 | D63: CC603110@techmahindra.com | E63: Charan Chanda | F63: Charan Chanda | G63: 603110 | H63: 46118 | I63: FGD | J63: IBU Specific Connect | K63: PUNE | L63: DIG-D-4002, 4003, 4007,4009 | M63: E | N63: In-person-Tech M | O63: DEA Service Line | P63: DEA-D-4006 | Q63: Systra | U63: Career | V63: ELTP Connect (Practice Level) | AJ63: Career Clarity & Growth Continuity;Engagement & Motivation Across Stages;Allocation & Deployment Transparency; | AK63: Variation in how learning is translating into actual delivery readiness across different ELTP stages (early-stage ready, mid-stage struggling, late-stage stagnation); | AL63: Work with work force management and delivery closely to ensure the ELTP associates are mapped to projects once their trainings are completed;Introduce ELTP engagement framework by stage: 0–6M → onboarding support, 6–M → performance alignment, –M → growth & retention; | CR63: Positive | CS63: HRBP; | CU63: High | CV63: Closed
A64: 63 | B64: 46149.568 | C64: 46149.58 | D64: CA205428@techmahindra.com | E64: Chaitanya Aggarwal | F64: Chaitanya Aggarwal | G64: 205428 | H64: 46145 | I64: Large Connect | J64: IBU Specific Connect | K64: PUNE | L64: TMC-D-1001 | M64: MIX | N64: Virtual | O64: Network Services Service Line | P64: DEA-D-4009 | Q64: IFS SELL TO | U64: Alignment | W64: SL Induction | AD64: Visibility on Allocation & Demand;Business & Practice Awareness;Engagement with Leadership & Confidence Level; | AE64: Associates lack clarity on practice goals and IBU priorities; | AF64: Create consistent onboarding framework across practice;Checked the action plan for pending allocation of new joiners and highlighted to IBU head and it was closed; | CR64: Negative | CS64: No specific Action, Issue addressed in meeting; | CT64: NA | CU64: High | CV64: Open
A65: 64 | B65: 46094.679 | C65: 46094.683 | D65: AE451317@techmahindra.com | E65: Adweta Edwin | F65: Adweta Edwin | G65: 451317 | H65: 46074 | I65: 1:1 | J65: IBU Specific Connect | K65: Pune | L65: DEA-D-40026 | M65: MIX | N65: Virtual | O65: DEA Service Line | P65: DEA-D-4022 | Q65: Salesforce Comms | U65: Alignment | W65: HR Connect (Project Wise) | AV65: Recognition & Engagement within Project; | AW65: Seat availability and office logistics impact productivity;Timesheet submission/approval process inconsistencies create compliance risk; | AX65: All the queries were resolved in the session; | CR65: Positive | CS65: Delivery; | CU65: Moderate | CV65: Closed | CX65: Discussed general SL level updates and priorities.
A66: 65 | B66: 46169.088 | C66: 46169.095 | D66: AC107161@techmahindra.com | E66: Aditya Choudhury | F66: Aditya Choudhury | G66: 107161 | H66: 46162 | I66: FGD | J66: IBU Specific Connect | K66: Bengaluru | L66: DEA-D-40026 | M66: MIX | N66: In-person-Tech M | O66: DEA Service Line | P66: CIS-D-4007 | Q66: Oracle HCM ¿ UKG & Workday | U66: Alignment | W66: New Joiner Connect (60 Days) | BN66: Team Integration;Queries related to BGV check;BGV queries; | BO66: NA;Skill gaps becoming visible during execution; | BP66: Explained the complete process to associates; | CR66: Mixed | CS66: No specific Action, Issue addressed in meeting; | CT66: NA | CU66: Moderate | CV66: Closed | CW66: SALESFORCE PRACTICE
A67: 66 | B67: 46047.532 | C67: 46047.551 | D67: BP359486@techmahindra.com | E67: Balendra Pingle | F67: Balendra Pingle | G67: 359486 | H67: 46028 | I67: Location-Offshore | J67: IBU Specific Connect | K67: Kolkata | L67: DEA-D-2003 | M67: E | N67: Virtual | O67: CIS Service Line | P67: SAP Retail | Q67: Practice | U67: Alignment | W67: ML Returnee Connect | BT67: Feedback on recent processes; | BU67: Positive feedback overall;Minor process related queries; | BV67: Continue regular check-ins; | CR67: Neutral | CS67: No specific Action, Issue addressed in meeting; | CT67: Queries related to compensation. | CU67: High | CV67: Closed
A68: 67 | B68: 46140.118 | C68: 46140.13 | D68: QD805448@techmahindra.com | E68: Qushi Datta | F68: Qushi Datta | G68: 805448 | H68: 46140 | I68: FGD | J68: Practice Specific Connect (Across IBU) | K68: Bhubaneswar | L68: DEA- D-4023, DEA-D-4024, DEA-D-4025 | M68: MIX | N68: In-person-Tech M | O68: DEA Service Line | P68: CIS D 4001,4004,4021,4025,4026 | Q68: Bench connect for the IBUs | U68: Strive | Z68: Wellness Session | CL68: Stress & Burnout Management; | CM68: Low awareness;Flexibility alignment; | CN68: Workshops;Wellbeing check-ins; | CR68: Positive | CS68: HRBP;Delivery; | CU68: High | CV68: In-progress
A69: 68 | B69: 46041.433 | C69: 46041.447 | D69: BP512151@techmahindra.com | E69: Balveer Parmar | F69: Balveer Parmar | G69: 512151 | H69: 46034 | I69: Location-Offshore | J69: Practice Specific Connect (Across IBU) | K69: Pune | L69: NGS-D-2004 | M69: MIX | N69: In-person-Tech M | O69: DEA Service Line | P69: DEA-D-4013 | Q69: DIG-D-4001, DIG-D-4005, DIG-D-4007 | U69: Alignment | W69: SL Induction | AD69: HR / WFM / Training Communication Effectiveness; | AE69: Associates lack clarity on practice goals and IBU priorities; | AF69: Checked the action plan for pending allocation of new joiners and highlighted to IBU head and it was closed; | CR69: Positive | CS69: No specific Action, Issue addressed in meeting; | CT69: NA | CU69: Moderate | CV69: Closed
A70: 69 | B70: 46072.141 | C70: 46072.161 | D70: HP159185@techmahindra.com | E70: Harshil Pandya | F70: Mohammed Khalsa | G70: 159185 | H70: 46063 | I70: Large Connect | J70: Location Specific Connect | K70: Kolkata | L70: DEA-D-2026 | M70: MIX | N70: Virtual | O70: DEA Service Line | P70: DEA-D-2004 | Q70: NS MT Intern connect with Ahmed Bilal | U70: Alignment | W70: Townhall | AA70: Recognition Visibility;Business & Strategy Clarity;Leadership Communication & Q&A Effectiveness; | AB70: AI/future readiness messaging is high-level;Associates seek clarity on role progression and career paths within the unit; | AC70: Share a 1-page business snapshot (targets, priorities, key wins) post townhall;Publish role-based learning paths (beginner/intermediate/advanced) with links; | CR70: Positive | CS70: No specific Action, Issue addressed in meeting; | CU70: Low | CV70: Closed
A71: 70 | B71: 46191.606 | C71: 46191.627 | D71: NB585517@techmahindra.com | E71: Nitara Bakshi | F71: Nitara Bakshi | G71: 585517 | H71: 46174 | I71: FGD | J71: IBU Specific Connect | K71: PUNE | L71: DEA-D-2026 | M71: MIX | N71: Virtual | O71: DEA Service Line | P71: DEA-D-4021 | Q71: Mixed | U71: Career | V71: ELTP Connect (6-12m) | AP71: Business Context & Org Awareness; | AQ71: slows improvement;Feedback is irregular or not tied to a rubric; | AR71: Run fortnightly utilization reviews with WFM + delivery owners to rebalance work; | CR71: Neutral | CS71: Delivery; | CT71: Need budget clarity | CU71: Low | CV71: In-progress
A72: 71 | B72: 46066.535 | C72: 46066.541 | D72: NK877493@techmahindra.com | E72: Nisha Kothari | F72: Nathaniel Chokshi | G72: 877493 | H72: 46051 | I72: Location-Mixed | J72: Practice Specific Connect (Across IBU) | K72: PUNE | L72: DEA-D-2026 | M72: MIX | N72: In-person-Tech M | O72: DEA Service Line | P72: DEA-D-4028 | Q72: Salesforce Practice | U72: Alignment | W72: New Joiner Connect (7 Days) | BH72: Tool & System Access;Initial Organization Understanding; | BI72: Delays in access to systems/tools required for work;New joiners feel overwhelmed or unclear post induction; | BJ72: Hybrid working policy was explained in detail;Implement Day-1 access checklist tracking (IT + Admin); | CR72: Positive | CS72: No specific Action, Issue addressed in meeting; | CT72: Had a walkthrough of the DEA line and provided an overview of the following: RTO (Return to Office) guidelines Timesheet process Training structure Medical insurance details | CU72: Moderate | CV72: Closed
A73: 72 | B73: 46103.62 | C73: 46103.626 | D73: UK445888@techmahindra.com | E73: Upma Kapadia | F73: Upma Kapadia | G73: 445888 | H73: 46085 | I73: Location-Offshore | J73: IBU Specific Connect | K73: Kolkata | L73: DEA-D-40026 | M73: MIX | N73: Virtual | O73: DIG Vertical | P73: IFS | Q73: Paragon | U73: Alignment | W73: New Joiner Connect (30 Days) | BK73: Learning Curve Support; | BL73: Delay or lack of clarity in project onboarding;Associates undergoing project training; | BM73: Define timeline for project allocation (max 0 days); | CR73: Mixed | CS73: Delivery; | CT73: Queries on timesheet/attendance compliance during bench | CU73: Moderate | CV73: Closed
A74: 73 | B74: 46070.224 | C74: 46070.236 | D74: IM491329@techmahindra.com | E74: Inaya Mody | F74: Udant Bajwa | G74: 491329 | H74: 46050 | I74: 1:1 | J74: IBU Specific Connect | K74: Pune | L74: DAI-D-2005 | M74: MIX | N74: Virtual | O74: DEA Service Line | P74: DEA-D-4026 | Q74: TMC-D-1001 | U74: Alignment | W74: New Joiner Connect (7 Days) | BH74: Tool & System Access; | BI74: Limited clarity on policies (leave, WFO, reporting);Delays in access to systems/tools required for work; | BJ74: Share org structure + “who does what” quick guide; | CR74: Positive | CS74: No specific Action, Issue addressed in meeting; | CT74: NA | CU74: Moderate | CV74: Closed
A75: 74 | B75: 46154.268 | C75: 46154.285 | D75: FM336828@techmahindra.com | E75: Falguni Mallick | F75: Falguni Mallick | G75: 336828 | H75: 46152 | I75: 1:1 | J75: Location Specific Connect | K75: Bhubaneswar | L75: IIGA | M75: MIX | N75: Virtual | O75: DEA Service Line | P75: All SAP IBU's | Q75: Suncorp Bank | U75: Alignment | W75: New Joiner Connect (90 Days) | BQ75: Internal Growth Opportunities;Long-Term Role Alignment; | BR75: seat allocation; | BS75: Improve team engagement (inclusion, recognition); | CR75: Positive | CS75: Delivery;HRBP; | CT75: Queries with regards with access card were raised. | CU75: Moderate | CV75: Open
A76: 75 | B76: 46191.56 | C76: 46191.577 | D76: IU134500@techmahindra.com | E76: Indali Upadhyay | F76: Indali Upadhyay | G76: 134500 | H76: 46181 | I76: Large Connect | J76: IBU Specific Connect | K76: Jorhat | L76: IIGA | M76: E | N76: Virtual | O76: DEA Service Line | P76: DEA-D-4031 | Q76: Monthly Cadence DEA-D-4011 | U76: Alignment | W76: ML Returnee Connect | BT76: Clarity on expectations;Feedback on recent processes; | BU76: Positive feedback overall; | BV76: NA;No specific action required; | CR76: Positive | CS76: WFM; | CT76: NA | CU76: High | CV76: Closed
A77: 76 | B77: 46094.24 | C77: 46094.252 | D77: JL614435@techmahindra.com | E77: Jack Lal | F77: Jack Lal | G77: 614435 | H77: 46077 | I77: Workshop/Session | J77: IBU Specific Connect | K77: PUNE | L77: DEA-D-2003 | M77: MIX | N77: Virtual | O77: DEA Service Line | P77: CIS D 4001,4004,4025,4026 | Q77: Cadence with IBU Head. | U77: Alignment | W77: New Joiner Connect (60 Days) | BN77: Workload Management;Feedback Mechanism;Role Confidence Level; | BO77: NA;BGV; | BP77: BGV; | CR77: Mixed | CS77: No specific Action, Issue addressed in meeting; | CT77: Bench guidelines are explained | CU77: Moderate | CV77: Closed
A78: 77 | B78: 46066.39 | C78: 46066.392 | D78: BC193972@techmahindra.com | E78: Balvan Chopra | F78: Balvan Chopra | G78: 193972 | H78: 46064 | I78: 1:1 | J78: Practice Specific Connect (Across IBU) | K78: Bengaluru | L78: DEA-D-4021 | M78: MIX | N78: In-person-Tech M | O78: DIG Vertical | P78: DEA-D-4030 | Q78: Haleon | U78: Alignment | W78: HR Connect (Project Wise) | AV78: Strategic Connect;Manager Support & Local Leadership Effectiveness;Infrastructure / Workplace Enablement; | AW78: Generic discussion about the account with the leads;associates want clear routes; | AX78: All the queries were resolved in the session;All the queries were resolved in the ODC COnnect; | CR78: Positive | CS78: No specific Action, Issue addressed in meeting; | CT78: NA | CU78: Moderate | CV78: Open
A79: 78 | B79: 46142.684 | C79: 46142.697 | D79: DS212168@techmahindra.com | E79: Dipta Sarin | F79: Lekha Gupta | G79: 212168 | H79: 46142 | I79: Workshop/Session | J79: IBU Specific Connect | K79: Kolkata | L79: NWS-D-1001 | M79: MIX | N79: In-person-Tech M | O79: CIS Service Line | P79: DEA-D-4040 | Q79: DIG USA Minus TTLH | U79: Alignment | W79: HR Connect (General) | AY79: Monthly Cadence IBU Head coverage on HC, Attrition, eltp and Bench;Connect for recognition; | AZ79: Need simplified updates on policy changes and timelines;Need guidance on leave, travel, and exception approvals; | BA79: Send monthly HR bulletin with key updates and links;It was a general discussion with the IBU Head on the pulse at ground level; | CR79: Positive | CS79: No specific Action, Issue addressed in meeting; | CT79: QUERIES ON Travel post allocation | CU79: Moderate | CV79: Closed
A80: 79 | B80: 46080.29 | C80: 46080.305 | D80: AV128223@techmahindra.com | E80: Aarav Venkatesh | F80: Aarav Venkatesh | G80: 128223 | H80: 46066 | I80: Workshop/Session | J80: IBU Specific Connect | K80: Bhubaneswar | L80: NGS-D-2004 | M80: MIX | N80: Virtual | O80: DEA Service Line | P80: DEA-D-3027 | Q80: Salesforce practice | U80: Alignment | W80: New Joiner Connect (60 Days) | BN80: BGV queries;Role Confidence Level; | BO80: Skill gaps becoming visible during execution;Not fully integrated with team collaboration channels; | BP80: NA;BGV; | CR80: Neutral | CS80: No specific Action, Issue addressed in meeting; | CT80: Team was contented with the fun connect as it was a nice short break from work and the whole account was able to connect virtually | CU80: Low | CV80: Open
A81: 80 | B81: 46202.734 | C81: 46202.74 | D81: JS778428@techmahindra.com | E81: Januja Sankar | F81: Januja Sankar | G81: 778428 | H81: 46184 | I81: Monthly Cadence | J81: Practice Specific Connect (Across IBU) | K81: Kolkata | L81: NGS-D-2004 | M81: MIX | N81: Virtual | O81: DEA Service Line | P81: IFS | Q81: Rating Calibration Call | U81: Alignment | W81: HR Connect (General) | AY81: On Hybrid/WFO Rules And Monthly Compliance Expectations;Guidance On Leave, Travel, And Exception Approvals; | AZ81: na;NA; | BA81: Connect for recognition;No Action; | CR81: Positive | CS81: No specific Action, Issue addressed in meeting; | CT81: Clarity on Performance cycle | CU81: High | CV81: Closed
A82: 81 | B82: 46046.57 | C82: 46046.584 | D82: DD606384@techmahindra.com | E82: Dipta Dash | F82: Dipta Dash | G82: 606384 | H82: 46043 | I82: FGD | J82: Practice Specific Connect (Across IBU) | K82: Hyderbad | L82: DEA- D-4023, DEA-D-4024, DEA-D-4025 | M82: U | N82: Virtual | O82: CIS Service Line | P82: DIG-D-4001 | Q82: DEA BLR (Women Associates) | U82: Alignment | W82: HR Connect (Project Wise) | AV82: On Leave/comp-off Due To Client Calendar Mismatches;Manager Support & Local Leadership Effectiveness;Policy & Process Clarity; | AW82: Issues with respect to applying leaves and communication regarding leaves to the managers; | AX82: HR and Delivery Head clarified on org level communication on appraisals;All were resolved in the ODC connect; | CR82: Neutral | CS82: Delivery; | CT82: NA | CU82: Moderate | CV82: Closed
A83: 82 | B83: 46165.168 | C83: 46165.169 | D83: YM838968@techmahindra.com | E83: Yashica More | F83: Yashica More | G83: 838968 | H83: 46157 | I83: Floor Connect | J83: Practice Specific Connect (Across IBU) | K83: Khammam | L83: DEA-D-2004 | M83: U | N83: Virtual | O83: DEA Service Line | P83: DEA -D-4006 | Q83: OPTUS | U83: Career | V83: ELTP Connect (6-12m) | AP83: Business Context & Org Awareness; | AQ83: slows improvement;Feedback is irregular or not tied to a rubric; | AR83: Run fortnightly utilization reviews with WFM + delivery owners to rebalance work; | CR83: Neutral | CS83: Delivery; | CT83: Not happy with the inconsistent hike, but happy with the project as he is learning new technologies like S4 HANA | CU83: High | CV83: Closed
A84: 83 | B84: 46107.244 | C84: 46107.249 | D84: JH291936@techmahindra.com | E84: Joshua Handa | F84: Joshua Handa | G84: 291936 | H84: 46103 | I84: FGD | J84: IBU Specific Connect | K84: Nadiad | L84: IIGA | M84: MIX | N84: Virtual | O84: DEA Service Line | P84: DIG-D-4001 | Q84: ELTP Connect | U84: Alignment | W84: New Joiner Connect (90 Days) | BQ84: Engagement & Belonging;Career Path Visibility; | BR84: Lack of awareness of internal opportunities;Connect with Practice head, associates were happy with the session and interaction opportunity with practice head.; | BS84: Align role expectations vs aspiration through discussion;Improve team engagement (inclusion, recognition); | CR84: Positive | CS84: WFM; | CT84: RTO management and Bench | CU84: Low | CV84: Closed
A85: 84 | B85: 46157.422 | C85: 46157.428 | D85: CR186686@techmahindra.com | E85: Charvi Ravi | F85: Charvi Ravi | G85: 186686 | H85: 46150 | I85: FGD | J85: IBU Specific Connect | K85: Chennai | L85: NWS-D-1001 | M85: MIX | N85: In-person-Tech M | O85: DEA Service Line | P85: DEA-D-4024 | Q85: DEA Ops | U85: Alignment | W85: New Joiner Connect (7 Days) | BH85: Induction Effectiveness;Buddy / Support System;Tool & System Access; | BI85: none;Limited clarity on policies (leave, WFO, reporting); | BJ85: Assign buddy with defined responsibilities for 2 weeks;Hybrid working policy was explained in detail; | CR85: Positive | CS85: Delivery;HRBP;WFM; | CU85: High | CV85: Closed | CW85: DEA-D-4011, Suresh Boddu
A86: 85 | B86: 46133.808 | C86: 46133.825 | D86: DM467663@techmahindra.com | E86: Daksha Mangat | F86: Daksha Mangat | G86: 467663 | H86: 46114 | I86: 1:1 | J86: IBU Specific Connect | K86: Chinsurah | L86: DEA-D-2007 | M86: U | N86: In-person-Tech M | O86: DEA Service Line | P86: DEA-D-4028 | Q86: IFS Project | U86: Alignment | W86: HR Connect (Project Wise) | AV86: Policy & Process Clarity;Workload & Work-Life Balance; | AW86: Recurring questions on WFO/WFH expectations and exception handling;Timesheet submission/approval process inconsistencies create compliance risk; | AX86: All the queries were resolved in the session; | CR86: Mixed | CS86: HRBP; | CT86: No specific queries | CU86: High | CV86: Closed
A87: 86 | B87: 46177.215 | C87: 46177.222 | D87: US898462@techmahindra.com | E87: Udyati Sathe | F87: Udyati Sathe | G87: 898462 | H87: 46165 | I87: FGD | J87: IBU Specific Connect | K87: Kakinada | L87: NGS-D-2004 | M87: MIX | N87: Virtual | O87: DIG Vertical | P87: MFG-D-4003 | Q87: D&AI BFSI IBG | U87: Alignment | W87: New Joiner Connect (7 Days) | BH87: Induction Effectiveness;Initial Organization Understanding;HR Process Clarity; | BI87: none;Delays in access to systems/tools required for work; | BJ87: Standardize induction deck + post-induction summary mail; | CR87: Mixed | CS87: Delivery; | CT87: All were resolved | CU87: Low | CV87: Closed | CW87: DEA-D-4011, Suresh Boddu
A88: 87 | B88: 46127.098 | C88: 46127.106 | D88: FM454161@techmahindra.com | E88: Frado Mander | F88: Frado Mander | G88: 454161 | H88: 46123 | I88: 1:1 | J88: IBU Specific Connect | K88: Bengaluru | L88: DEA- D-4023, DEA-D-4024, DEA-D-4025 | M88: MIX | N88: In-person-Tech M | O88: DEA Service Line | P88: CIS-D-4007 | Q88: DIG-D-4005, DIG-D-4008, DIG-D-4009 | U88: Alignment | W88: Townhall | AA88: Business & Strategy Clarity;Work-Life & Sustainability Signals; | AB88: Associates seek clarity on role progression and career paths within the unit;Org/structural updates are heard but not fully understood (what changes for me?); | AC88: Add a ‘What changes for teams’ section with 3–5 concrete takeaways;Run a follow-up FAQ mailer and route unanswered questions to SPOCs; | CR88: Positive | CS88: No specific Action, Issue addressed in meeting; | CT88: the associates had doubts related to the RTO guidelines and seat allocations | CU88: Moderate | CV88: Closed
A89: 88 | B89: 46127.879 | C89: 46127.895 | D89: GK195629@techmahindra.com | E89: Girik Keer | F89: Girik Keer | G89: 195629 | H89: 46127 | I89: Large Connect | J89: IBU Specific Connect | K89: Pune | L89: DAI-D-2005 | M89: MIX | N89: Virtual | O89: DEA Service Line | P89: NWS-D-4001 | Q89: New Joiner 30 Day Connect | U89: Alignment | W89: New Joiner Connect (90 Days) | BQ89: Engagement & Belonging; | BR89: Connect with Practice head, associates were happy with the session and interaction opportunity with practice head.;seat allocation; | BS89: Share internal job/cross-skill opportunities; | CR89: Positive | CS89: No specific Action, Issue addressed in meeting; | CT89: NA | CU89: High | CV89: Closed
A90: 89 | B90: 46156.597 | C90: 46156.613 | D90: RD781595@techmahindra.com | E90: Rushil Din | F90: Rushil Din | G90: 781595 | H90: 46145 | I90: Floor Connect | J90: IBU Specific Connect | K90: Ranchi | L90: NGS-D-2004 | M90: MIX | N90: Virtual | O90: DEA Service Line | P90: SAP Retail | Q90: DEA | U90: Alignment | W90: SL Induction | AD90: HR / WFM / Training Communication Effectiveness;Engagement with Leadership & Confidence Level;Business & Practice Awareness; | AE90: Associates lack clarity on practice goals and IBU priorities;NA; | AF90: TLS SPOC had cleared all the queries w.r.t learning;Checked the action plan for pending allocation of new joiners and highlighted to IBU head and it was closed; | CR90: Positive | CS90: Delivery; | CT90: No specific queries - Associate participation HC was very low. | CU90: Low | CV90: Closed
A91: 90 | B91: 46078.487 | C91: 46078.501 | D91: ES736408@techmahindra.com | E91: Elijah Shah | F91: Elijah Shah | G91: 736408 | H91: 46066 | I91: FGD | J91: IBU Specific Connect | K91: Hyderabad | L91: TMC-D-1001 | M91: MIX | N91: Virtual | O91: DEA Service Line | P91: CIS D 4001,4004,4025,4026 | Q91: Rating Calibration call with IBU Head | U91: Empowerment | Y91: Leadership Connect | CF91: NA;Action Closure Discipline; | CG91: Rating Calibration Call;NA; | CH91: Work with AI Agents; | CR91: Mixed | CS91: HRBP; | CU91: Moderate | CV91: Closed
A92: 91 | B92: 46109.442 | C92: 46109.458 | D92: LT847245@techmahindra.com | E92: Leena Talwar | F92: Leena Talwar | G92: 847245 | H92: 46096 | I92: FGD | J92: IBU Specific Connect | K92: Chennai | L92: DEA-D-40026 | M92: MIX | N92: Virtual | O92: MFG Vertical | P92: NGS,D-4013, NGS-D-4014 | Q92: DIG-D-4001, DIG-D-4005, DIG-D-4007 | U92: Alignment | W92: New Joiner Connect (60 Days) | BN92: Workload Management;BGV queries;Queries related to BGV check; | BO92: The associates had questions around WFH and leaves.;BGV related queries; | BP92: Explained the complete process to associates; | CR92: Positive | CS92: No specific Action, Issue addressed in meeting; | CT92: NA | CU92: Moderate | CV92: Closed
A93: 92 | B93: 46106.743 | C93: 46106.761 | D93: AC111901@techmahindra.com | E93: Abdul Chhabra | F93: Abdul Chhabra | G93: 111901 | H93: 46095 | I93: 1:1 | J93: Practice Specific Connect (Across IBU) | K93: Chennai | L93: DIG-D-4002, 4003, 4007,4009 | M93: MIX | N93: In-person-Tech M | O93: DEA Service Line | P93: NWS-D-4019 & NWS-D-4020 | Q93: DEA-D-4030 | R93: Celebrated Priyanka Das’s 20th LSA in the Hyderabad location. We organized a virtual session as well where everyone appreciated her, followed by a cake-cutting ceremony and presentation of a memento. Overall, the associate was very happy and expressed her gratitude to the BHR team. | U93: Recognition | X93: LSA Connect | CR93: Neutral | CS93: No specific Action, Issue addressed in meeting; | CT93: NA | CU93: Low | CV93: Closed
A94: 93 | B94: 46175.876 | C94: 46175.89 | D94: PV274987@techmahindra.com | E94: Patrick Vasa | F94: Patrick Vasa | G94: 274987 | H94: 46167 | I94: Floor Connect | J94: Location Specific Connect | K94: Bhubaneswar | L94: DEA-D-2026 | M94: MIX | N94: Virtual | O94: CIS Service Line | P94: All SAP IBU's | Q94: Haleon | U94: Career | V94: Top Talent FGD Connect | BE94: Feedback on recent processes;Review of ongoing concerns; | BF94: Positive feedback overall; | BG94: Continue regular check-ins;Monitor and follow up in next cycle; | CR94: Positive | CS94: HRBP;Delivery; | CT94: NA | CU94: Low | CV94: Closed
A95: 94 | B95: 46118.588 | C95: 46118.602 | D95: JS148159@techmahindra.com | E95: Jairaj Shan | F95: Jairaj Shan | G95: 148159 | H95: 46116 | I95: Location-Offshore | J95: Location Specific Connect | K95: Hyderbad | L95: DEA-D-4026 | M95: MIX | N95: Virtual | O95: DEA Service Line | P95: DEA-D-4006 | Q95: SAP Manufacturing | T95: IBU Level Connect | U95: Empowerment | Y95: Cadence Connect | CR95: Positive | CS95: Delivery; | CT95: NA | CU95: Moderate | CV95: In-progress
A96: 95 | B96: 46058.135 | C96: 46058.146 | D96: ES125071@techmahindra.com | E96: Edhitha Savant | F96: Edhitha Savant | G96: 125071 | H96: 46047 | I96: 1:1 | J96: Practice Specific Connect (Across IBU) | K96: Motihari | L96: DEA-D-4026 | M96: MIX | N96: Virtual | O96: CIS Service Line | P96: ENS-D-4001 | Q96: Keysight | U96: Career | V96: ELTP Connect (<6m) | AM96: Clarity on expectations; | AN96: NA;No major concerns raised; | AO96: NA;No specific action required; | CR96: Mixed | CS96: Delivery;HRBP; | CT96: NA | CU96: Moderate | CV96: Open
A97: 96 | B97: 46115.186 | C97: 46115.207 | D97: VS513507@techmahindra.com | E97: Vaishnavi Sengupta | F97: Yug Malhotra | G97: 513507 | H97: 46097 | I97: Large Connect | J97: Practice Specific Connect (Across IBU) | K97: Mathura | L97: DEA-D-4021 | M97: MIX | N97: Virtual | O97: DIG Vertical | P97: DIG-D-4005 | Q97: The connect was celebrate the success of a senior leader where even the SL head joined for the celebrations | U97: Alignment | W97: New Joiner Connect (90 Days) | BQ97: Engagement & Belonging;Career Path Visibility; | BR97: Connect with Practice head, associates were happy with the session and interaction opportunity with practice head.; | BS97: Improve team engagement (inclusion, recognition); | CR97: Positive | CS97: No specific Action, Issue addressed in meeting; | CU97: Moderate | CV97: In-progress
A98: 97 | B98: 46083.918 | C98: 46083.921 | D98: BK265271@techmahindra.com | E98: Bhavika Keer | F98: Bhavika Keer | G98: 265271 | H98: 46074 | I98: Floor Connect | J98: Practice Specific Connect (Across IBU) | K98: Thanjavur | L98: DEA-D-4026 | M98: MIX | N98: In-person-Tech M | O98: Network Services Service Line | P98: DEA-D-4018 | Q98: PureStorage | U98: Career | V98: Top Talent FGD Connect | BE98: Feedback on recent processes;General wellbeing check-in; | BF98: Minor process related queries;No major concerns raised; | BG98: Share update with relevant stakeholder; | CR98: Positive | CS98: HRBP; | CU98: Low | CV98: Closed
A99: 98 | B99: 46092.152 | C99: 46092.168 | D99: LD188121@techmahindra.com | E99: Lakshit Dora | F99: Lakshit Dora | G99: 188121 | H99: 46084 | I99: Location-Mixed | J99: IBU Specific Connect | K99: Hyderabad | L99: NWS-D-1001 | M99: U | N99: Virtual | O99: CIS Service Line | P99: NGS,D-4013, NGS-D-4014 | Q99: MFG SL | U99: Career | V99: ELTP Connect (Practice Level) | AJ99: Allocation & Deployment Transparency; | AK99: Variation in how learning is translating into actual delivery readiness across different ELTP stages (early-stage ready, mid-stage struggling, late-stage stagnation);Lack of continuous career communication leads to: confusion in early stage, direction gap in mid-stage, retention risk in later stage; | AL99: Introduce ELTP engagement framework by stage: 0–6M → onboarding support, 6–M → performance alignment, –M → growth & retention;Work with work force management and delivery closely to ensure the ELTP associates are mapped to projects once their trainings are completed; | CR99: Neutral | CS99: No specific Action, Issue addressed in meeting; | CU99: Moderate | CV99: In-progress
A100: 99 | B100: 46076.008 | C100: 46076.016 | D100: TB623125@techmahindra.com | E100: Tanish Bhatt | F100: Tanish Bhatt | G100: 623125 | H100: 46059 | I100: FGD | J100: IBU Specific Connect | K100: PUNE | L100: DEA-D-2007 | M100: MIX | N100: In-person-Tech M | O100: DEA Service Line | P100: NGS,D-4013, NGS-D-4014 | Q100: SAP | U100: Empowerment | Y100: Band Specific FGD Connect | CC100: Discussion on team dynamics;Clarity on expectations;Review of ongoing concerns; | CD100: Associates are settling in well;Positive feedback overall; | CE100: Monitor and follow up in next cycle;Continue regular check-ins; | CR100: Positive | CS100: Delivery; | CT100: NA | CU100: Moderate | CV100: In-progress
...

Sheet Calc
A1: KPI FORMULAS | G1: ENGAGEMENT TYPE | J1: SL x SEVERITY | Q1: COVERAGE ISSUES (self-populating from Data_Summary) | W1: COVERAGE BREAKDOWN | AA1: SESSION DISTRIBUTION BY COHORT | AD1: TOP ORGANIZATIONAL CONCERNS (chart feed) | AG1: ENGAGEMENT TYPE (sorted feed) | AJ1: COVERAGE STATEMENT FREQ
A2: KPI | B2: Value | G2: Type | H2: Count | J2: Service Line | K2: High | L2: Moderate | M2: Low | N2: Total | Q2: Coverage Issue | R2: BHR Count | S2: % of Sessions | T2: Top Engagement Type | W2: Engagement / Coverage Area | X2: Sessions Covered | AA2: Cohort | AB2: Sessions | AD2: Concern | AE2: Mentions | AG2: Engagement Type | AH2: Count | AJ2: Statement | AK2: Count
A3: Total Sessions | B3: =COUNTA(RawData[ID]) -> 300 | G3: Large Connect | H3: =COUNTIF(RawData[Engagement Type],G3) -> 96 | J3: DEA Service Line | K3: =COUNTIFS(RawData[Service Line],J3,RawData[Severity],"High") -> 43 | L3: =COUNTIFS(RawData[Service Line],J3,RawData[Severity],"Moderate") -> 79 | M3: =COUNTIFS(RawData[Service Line],J3,RawData[Severity],"Low") -> 78 | N3: =SUM(K3:M3) -> 200 | Q3: {=IFERROR(INDEX($AJ$2:$AJ$599,MATCH(1,($AK$2:$AK$599=R3)*(COUNTIF($Q2:$Q$3,$AJ$2:$AJ$599)=0)*($AJ$2:$AJ$599<>""),0)),"")} -> Feedback on recent processes | R3: =IFERROR(LARGE($AK$2:$AK$599,1),"") -> 24 | S3: =IF(Q3="","",IFERROR(R3/$B$3,0)) -> 0.08 | T3: {=IF(Q3="","",IFERROR(INDEX(SummaryData[Engagement Type],MATCH(TRIM(Q3),TRIM(SummaryData[Statement]),0)),""))} -> 1:1 | W3: HR Connect (General) | X3: =SUMPRODUCT((TRIM(RawData[Alignment])=TRIM(W3))*1) -> 14 | AA3: {=IFERROR(INDEX($AM$2:$AM$199,MATCH(1,($AN$2:$AN$199=AB3)*(COUNTIF($AA2:$AA$3,$AM$2:$AM$199)=0)*($AM$2:$AM$199<>""),0)),"")} -> HR Connect (Project Wise) | AB3: =IFERROR(LARGE($AN$2:$AN$199,1),"") -> 30 | AD3: =IF(Calc!Q3="","",Calc!Q3) -> Feedback on recent processes | AE3: =IF(Calc!Q3="","",Calc!R3) -> 24 | AG3: {=IFERROR(INDEX($G$3:$G$15,MATCH(1,(($H$3:$H$15)=AH3)*(COUNTIF($AG2:$AG$3,$G$3:$G$15)=0),0)),"")} -> Large Connect | AH3: =IFERROR(LARGE($H$3:$H$15,1),"") -> 96 | AJ3: =IF(Data_Summary!Y3<>"Coverage","",IF(Data_Summary!AA3="","",IF(COUNTIFS(Data_Summary!$Y$2:$Y3,"Coverage",Data_Summary!$AA$2:$AA3,Data_Summary!AA3)=1,Data_Summary!AA3,""))) | AK3: =IF(AJ3="","",COUNTIFS(Data_Summary!$Y$2:$Y$20001,"Coverage",Data_Summary!$AA$2:$AA$20001,AJ3))
A4: Open Concerns | B4: =COUNTIF(RawData[Status],"Open") -> 29 | G4: FGD | H4: =COUNTIF(RawData[Engagement Type],G4) -> 59 | J4: MFG Vertical | K4: =COUNTIFS(RawData[Service Line],J4,RawData[Severity],"High") -> 1 | L4: =COUNTIFS(RawData[Service Line],J4,RawData[Severity],"Moderate") -> 5 | M4: =COUNTIFS(RawData[Service Line],J4,RawData[Severity],"Low") -> 0 | N4: =SUM(K4:M4) -> 6 | Q4: {=IFERROR(INDEX($AJ$2:$AJ$599,MATCH(1,($AK$2:$AK$599=R4)*(COUNTIF($Q$3:$Q3,$AJ$2:$AJ$599)=0)*($AJ$2:$AJ$599<>""),0)),"")} -> Clarity on expectations | R4: =IFERROR(LARGE($AK$2:$AK$599,2),"") -> 19 | S4: =IF(Q4="","",IFERROR(R4/$B$3,0)) -> 0.063333333 | T4: {=IF(Q4="","",IFERROR(INDEX(SummaryData[Engagement Type],MATCH(TRIM(Q4),TRIM(SummaryData[Statement]),0)),""))} -> Large Connect | W4: HR Connect (Project-Wise) | X4: =SUMPRODUCT((TRIM(RawData[Alignment])=TRIM(W4))*1) -> 0 | AA4: {=IFERROR(INDEX($AM$2:$AM$199,MATCH(1,($AN$2:$AN$199=AB4)*(COUNTIF($AA$3:$AA3,$AM$2:$AM$199)=0)*($AM$2:$AM$199<>""),0)),"")} -> New Joiner Connect (60 Days) | AB4: =IFERROR(LARGE($AN$2:$AN$199,2),"") -> 22 | AD4: =IF(Calc!Q4="","",Calc!Q4) -> Clarity on expectations | AE4: =IF(Calc!Q4="","",Calc!R4) -> 19 | AG4: {=IFERROR(INDEX($G$3:$G$15,MATCH(1,(($H$3:$H$15)=AH4)*(COUNTIF($AG$3:$AG3,$G$3:$G$15)=0),0)),"")} -> FGD | AH4: =IFERROR(LARGE($H$3:$H$15,2),"") -> 59 | AJ4: =IF(Data_Summary!Y5<>"Coverage","",IF(Data_Summary!AA5="","",IF(COUNTIFS(Data_Summary!$Y$2:$Y5,"Coverage",Data_Summary!$AA$2:$AA5,Data_Summary!AA5)=1,Data_Summary!AA5,""))) | AK4: =IF(AJ4="","",COUNTIFS(Data_Summary!$Y$2:$Y$20001,"Coverage",Data_Summary!$AA$2:$AA$20001,AJ4))
A5: In Progress | B5: =COUNTIF(RawData[Status],"In-progress") -> 57 | G5: 1:1 | H5: =COUNTIF(RawData[Engagement Type],G5) -> 59 | J5: Network Services Service Line | K5: =COUNTIFS(RawData[Service Line],J5,RawData[Severity],"High") -> 2 | L5: =COUNTIFS(RawData[Service Line],J5,RawData[Severity],"Moderate") -> 3 | M5: =COUNTIFS(RawData[Service Line],J5,RawData[Severity],"Low") -> 4 | N5: =SUM(K5:M5) -> 9 | Q5: {=IFERROR(INDEX($AJ$2:$AJ$599,MATCH(1,($AK$2:$AK$599=R5)*(COUNTIF($Q$3:$Q4,$AJ$2:$AJ$599)=0)*($AJ$2:$AJ$599<>""),0)),"")} -> General wellbeing check-in | R5: =IFERROR(LARGE($AK$2:$AK$599,3),"") -> 16 | S5: =IF(Q5="","",IFERROR(R5/$B$3,0)) -> 0.053333333 | T5: {=IF(Q5="","",IFERROR(INDEX(SummaryData[Engagement Type],MATCH(TRIM(Q5),TRIM(SummaryData[Statement]),0)),""))} -> Location-Offshore | W5: New Joinee Connect (7 Days) | X5: =SUMPRODUCT((TRIM(RawData[Alignment])=TRIM(W5))*1) -> 0 | AA5: {=IFERROR(INDEX($AM$2:$AM$199,MATCH(1,($AN$2:$AN$199=AB5)*(COUNTIF($AA$3:$AA4,$AM$2:$AM$199)=0)*($AM$2:$AM$199<>""),0)),"")} -> New Joiner Connect (30 Days) | AB5: =IFERROR(LARGE($AN$2:$AN$199,3),"") -> 19 | AD5: =IF(Calc!Q5="","",Calc!Q5) -> General wellbeing check-in | AE5: =IF(Calc!Q5="","",Calc!R5) -> 16 | AG5: {=IFERROR(INDEX($G$3:$G$15,MATCH(1,(($H$3:$H$15)=AH5)*(COUNTIF($AG$3:$AG4,$G$3:$G$15)=0),0)),"")} -> 1:1 | AH5: =IFERROR(LARGE($H$3:$H$15,3),"") -> 59 | AJ5: =IF(Data_Summary!Y6<>"Coverage","",IF(Data_Summary!AA6="","",IF(COUNTIFS(Data_Summary!$Y$2:$Y6,"Coverage",Data_Summary!$AA$2:$AA6,Data_Summary!AA6)=1,Data_Summary!AA6,""))) | AK5: =IF(AJ5="","",COUNTIFS(Data_Summary!$Y$2:$Y$20001,"Coverage",Data_Summary!$AA$2:$AA$20001,AJ5))
A6: Closed Actions | B6: =COUNTIF(RawData[Status],"Closed") -> 214 | G6: Floor Connect | H6: =COUNTIF(RawData[Engagement Type],G6) -> 36 | Q6: {=IFERROR(INDEX($AJ$2:$AJ$599,MATCH(1,($AK$2:$AK$599=R6)*(COUNTIF($Q$3:$Q5,$AJ$2:$AJ$599)=0)*($AJ$2:$AJ$599<>""),0)),"")} -> Team Integration | R6: =IFERROR(LARGE($AK$2:$AK$599,4),"") -> 13 | S6: =IF(Q6="","",IFERROR(R6/$B$3,0)) -> 0.043333333 | T6: {=IF(Q6="","",IFERROR(INDEX(SummaryData[Engagement Type],MATCH(TRIM(Q6),TRIM(SummaryData[Statement]),0)),""))} -> Induction | W6: New Joiner Connect (30 Days) | X6: =SUMPRODUCT((TRIM(RawData[Alignment])=TRIM(W6))*1) -> 19 | AA6: {=IFERROR(INDEX($AM$2:$AM$199,MATCH(1,($AN$2:$AN$199=AB6)*(COUNTIF($AA$3:$AA5,$AM$2:$AM$199)=0)*($AM$2:$AM$199<>""),0)),"")} -> New Joiner Connect (90 Days) | AB6: =IFERROR(LARGE($AN$2:$AN$199,4),"") -> 16 | AD6: =IF(Calc!Q6="","",Calc!Q6) -> Team Integration | AE6: =IF(Calc!Q6="","",Calc!R6) -> 13 | AG6: {=IFERROR(INDEX($G$3:$G$15,MATCH(1,(($H$3:$H$15)=AH6)*(COUNTIF($AG$3:$AG5,$G$3:$G$15)=0),0)),"")} -> Floor Connect | AH6: =IFERROR(LARGE($H$3:$H$15,4),"") -> 36 | AJ6: =IF(Data_Summary!Y7<>"Coverage","",IF(Data_Summary!AA7="","",IF(COUNTIFS(Data_Summary!$Y$2:$Y7,"Coverage",Data_Summary!$AA$2:$AA7,Data_Summary!AA7)=1,Data_Summary!AA7,""))) -> Business & Strategy Clarity | AK6: =IF(AJ6="","",COUNTIFS(Data_Summary!$Y$2:$Y$20001,"Coverage",Data_Summary!$AA$2:$AA$20001,AJ6)) -> 11
A7: High Severity | B7: =COUNTIF(RawData[Severity],"High") -> 63 | G7: Location-Offshore | H7: =COUNTIF(RawData[Engagement Type],G7) -> 19 | Q7: {=IFERROR(INDEX($AJ$2:$AJ$599,MATCH(1,($AK$2:$AK$599=R7)*(COUNTIF($Q$3:$Q6,$AJ$2:$AJ$599)=0)*($AJ$2:$AJ$599<>""),0)),"")} -> Workload & Work-Life Balance | R7: =IFERROR(LARGE($AK$2:$AK$599,5),"") -> 12 | S7: =IF(Q7="","",IFERROR(R7/$B$3,0)) -> 0.04 | T7: {=IF(Q7="","",IFERROR(INDEX(SummaryData[Engagement Type],MATCH(TRIM(Q7),TRIM(SummaryData[Statement]),0)),""))} -> FGD | W7: New Joiner Connect (60 Days) | X7: =SUMPRODUCT((TRIM(RawData[Alignment])=TRIM(W7))*1) -> 22 | AA7: {=IFERROR(INDEX($AM$2:$AM$199,MATCH(1,($AN$2:$AN$199=AB7)*(COUNTIF($AA$3:$AA6,$AM$2:$AM$199)=0)*($AM$2:$AM$199<>""),0)),"")} -> New Joiner Connect (7 Days) | AB7: =IFERROR(LARGE($AN$2:$AN$199,5),"") -> 16 | AD7: =IF(Calc!Q7="","",Calc!Q7) -> Workload & Work-Life Balance | AE7: =IF(Calc!Q7="","",Calc!R7) -> 12 | AG7: {=IFERROR(INDEX($G$3:$G$15,MATCH(1,(($H$3:$H$15)=AH7)*(COUNTIF($AG$3:$AG6,$G$3:$G$15)=0),0)),"")} -> Location-Offshore | AH7: =IFERROR(LARGE($H$3:$H$15,5),"") -> 19 | AJ7: =IF(Data_Summary!Y8<>"Coverage","",IF(Data_Summary!AA8="","",IF(COUNTIFS(Data_Summary!$Y$2:$Y8,"Coverage",Data_Summary!$AA$2:$AA8,Data_Summary!AA8)=1,Data_Summary!AA8,""))) -> Career Visibility & Skill Roadmap | AK7: =IF(AJ7="","",COUNTIFS(Data_Summary!$Y$2:$Y$20001,"Coverage",Data_Summary!$AA$2:$AA$20001,AJ7)) -> 7
A8: Moderate Severity | B8: =COUNTIF(RawData[Severity],"Moderate") -> 126 | G8: Workshop/Session | H8: =COUNTIF(RawData[Engagement Type],G8) -> 4 | Q8: {=IFERROR(INDEX($AJ$2:$AJ$599,MATCH(1,($AK$2:$AK$599=R8)*(COUNTIF($Q$3:$Q7,$AJ$2:$AJ$599)=0)*($AJ$2:$AJ$599<>""),0)),"")} -> Discussion on team dynamics | R8: =IFERROR(LARGE($AK$2:$AK$599,6),"") -> 12 | S8: =IF(Q8="","",IFERROR(R8/$B$3,0)) -> 0.04 | T8: {=IF(Q8="","",IFERROR(INDEX(SummaryData[Engagement Type],MATCH(TRIM(Q8),TRIM(SummaryData[Statement]),0)),""))} -> 1:1 | W8: New Joiner Connect (90 Days) | X8: =SUMPRODUCT((TRIM(RawData[Alignment])=TRIM(W8))*1) -> 16 | AA8: {=IFERROR(INDEX($AM$2:$AM$199,MATCH(1,($AN$2:$AN$199=AB8)*(COUNTIF($AA$3:$AA7,$AM$2:$AM$199)=0)*($AM$2:$AM$199<>""),0)),"")} -> Cadence Connect | AB8: =IFERROR(LARGE($AN$2:$AN$199,6),"") -> 12 | AD8: =IF(Calc!Q8="","",Calc!Q8) -> Discussion on team dynamics | AE8: =IF(Calc!Q8="","",Calc!R8) -> 12 | AG8: {=IFERROR(INDEX($G$3:$G$15,MATCH(1,(($H$3:$H$15)=AH8)*(COUNTIF($AG$3:$AG7,$G$3:$G$15)=0),0)),"")} -> Location-Mixed | AH8: =IFERROR(LARGE($H$3:$H$15,6),"") -> 8 | AJ8: =IF(Data_Summary!Y9<>"Coverage","",IF(Data_Summary!AA9="","",IF(COUNTIFS(Data_Summary!$Y$2:$Y9,"Coverage",Data_Summary!$AA$2:$AA9,Data_Summary!AA9)=1,Data_Summary!AA9,""))) -> AI/future Readiness Messaging Is High-level | AK8: =IF(AJ8="","",COUNTIFS(Data_Summary!$Y$2:$Y$20001,"Coverage",Data_Summary!$AA$2:$AA$20001,AJ8)) -> 4
A9: Low Severity | B9: =COUNTIF(RawData[Severity],"Low") -> 111 | G9: Connect with Women Associates | H9: =COUNTIF(RawData[Engagement Type],G9) -> 0 | Q9: {=IFERROR(INDEX($AJ$2:$AJ$599,MATCH(1,($AK$2:$AK$599=R9)*(COUNTIF($Q$3:$Q8,$AJ$2:$AJ$599)=0)*($AJ$2:$AJ$599<>""),0)),"")} -> Business & Strategy Clarity | R9: =IFERROR(LARGE($AK$2:$AK$599,7),"") -> 11 | S9: =IF(Q9="","",IFERROR(R9/$B$3,0)) -> 0.036666667 | T9: {=IF(Q9="","",IFERROR(INDEX(SummaryData[Engagement Type],MATCH(TRIM(Q9),TRIM(SummaryData[Statement]),0)),""))} -> Large Connect | W9: SL Induction | X9: =SUMPRODUCT((TRIM(RawData[Alignment])=TRIM(W9))*1) -> 21 | AA9: {=IFERROR(INDEX($AM$2:$AM$199,MATCH(1,($AN$2:$AN$199=AB9)*(COUNTIF($AA$3:$AA8,$AM$2:$AM$199)=0)*($AM$2:$AM$199<>""),0)),"")} -> Skip Meeting | AB9: =IFERROR(LARGE($AN$2:$AN$199,7),"") -> 11 | AD9: =IF(Calc!Q9="","",Calc!Q9) -> Business & Strategy Clarity | AE9: =IF(Calc!Q9="","",Calc!R9) -> 11 | AG9: {=IFERROR(INDEX($G$3:$G$15,MATCH(1,(($H$3:$H$15)=AH9)*(COUNTIF($AG$3:$AG8,$G$3:$G$15)=0),0)),"")} -> Induction | AH9: =IFERROR(LARGE($H$3:$H$15,7),"") -> 5 | AJ9: =IF(Data_Summary!Y10<>"Coverage","",IF(Data_Summary!AA10="","",IF(COUNTIFS(Data_Summary!$Y$2:$Y10,"Coverage",Data_Summary!$AA$2:$AA10,Data_Summary!AA10)=1,Data_Summary!AA10,""))) | AK9: =IF(AJ9="","",COUNTIFS(Data_Summary!$Y$2:$Y$20001,"Coverage",Data_Summary!$AA$2:$AA$20001,AJ9))
A10: Positive Sentiment | B10: =COUNTIF(RawData[Overall Sentiment],"Positive") -> 193 | G10: Location-Mixed | H10: =COUNTIF(RawData[Engagement Type],G10) -> 8 | Q10: {=IFERROR(INDEX($AJ$2:$AJ$599,MATCH(1,($AK$2:$AK$599=R10)*(COUNTIF($Q$3:$Q9,$AJ$2:$AJ$599)=0)*($AJ$2:$AJ$599<>""),0)),"")} -> HR / WFM / Training Communication Effectiveness | R10: =IFERROR(LARGE($AK$2:$AK$599,8),"") -> 11 | S10: =IF(Q10="","",IFERROR(R10/$B$3,0)) -> 0.036666667 | T10: {=IF(Q10="","",IFERROR(INDEX(SummaryData[Engagement Type],MATCH(TRIM(Q10),TRIM(SummaryData[Statement]),0)),""))} -> 1:1 | W10: Townhall | X10: {=SUMPRODUCT((TRIM(RawData[Alignment])=TRIM(W10))*1)} -> 18 | AA10: {=IFERROR(INDEX($AM$2:$AM$199,MATCH(1,($AN$2:$AN$199=AB10)*(COUNTIF($AA$3:$AA9,$AM$2:$AM$199)=0)*($AM$2:$AM$199<>""),0)),"")} -> Josh (Fun Engagements) | AB10: =IFERROR(LARGE($AN$2:$AN$199,8),"") -> 9 | AD10: =IF(Calc!Q10="","",Calc!Q10) -> HR / WFM / Training Communication Effectiveness | AE10: =IF(Calc!Q10="","",Calc!R10) -> 11 | AG10: {=IFERROR(INDEX($G$3:$G$15,MATCH(1,(($H$3:$H$15)=AH10)*(COUNTIF($AG$3:$AG9,$G$3:$G$15)=0),0)),"")} -> Workshop/Session | AH10: =IFERROR(LARGE($H$3:$H$15,8),"") -> 4 | AJ10: =IF(Data_Summary!Y11<>"Coverage","",IF(Data_Summary!AA11="","",IF(COUNTIFS(Data_Summary!$Y$2:$Y11,"Coverage",Data_Summary!$AA$2:$AA11,Data_Summary!AA11)=1,Data_Summary!AA11,""))) | AK10: =IF(AJ10="","",COUNTIFS(Data_Summary!$Y$2:$Y$20001,"Coverage",Data_Summary!$AA$2:$AA$20001,AJ10))
A11: Mixed Sentiment | B11: =COUNTIF(RawData[Overall Sentiment],"Mixed") -> 26 | G11: Account Based | H11: =COUNTIF(RawData[Engagement Type],G11) -> 0 | Q11: {=IFERROR(INDEX($AJ$2:$AJ$599,MATCH(1,($AK$2:$AK$599=R11)*(COUNTIF($Q$3:$Q10,$AJ$2:$AJ$599)=0)*($AJ$2:$AJ$599<>""),0)),"")} -> Manager Support & Local Leadership Effectiveness | R11: =IFERROR(LARGE($AK$2:$AK$599,9),"") -> 10 | S11: =IF(Q11="","",IFERROR(R11/$B$3,0)) -> 0.033333333 | T11: {=IF(Q11="","",IFERROR(INDEX(SummaryData[Engagement Type],MATCH(TRIM(Q11),TRIM(SummaryData[Statement]),0)),""))} -> FGD | W11: Skip Meeting | X11: {=SUMPRODUCT((TRIM(RawData[Empowerment])=TRIM(W11))*1)} -> 11 | AA11: {=IFERROR(INDEX($AM$2:$AM$199,MATCH(1,($AN$2:$AN$199=AB11)*(COUNTIF($AA$3:$AA10,$AM$2:$AM$199)=0)*($AM$2:$AM$199<>""),0)),"")} -> ELTP Connect (12-24m) | AB11: =IFERROR(LARGE($AN$2:$AN$199,9),"") -> 8 | AD11: =IF(Calc!Q11="","",Calc!Q11) -> Manager Support & Local Leadership Effectiveness | AE11: =IF(Calc!Q11="","",Calc!R11) -> 10 | AG11: {=IFERROR(INDEX($G$3:$G$15,MATCH(1,(($H$3:$H$15)=AH11)*(COUNTIF($AG$3:$AG10,$G$3:$G$15)=0),0)),"")} -> New Joiner Induction | AH11: =IFERROR(LARGE($H$3:$H$15,9),"") -> 4 | AJ11: =IF(Data_Summary!Y12<>"Coverage","",IF(Data_Summary!AA12="","",IF(COUNTIFS(Data_Summary!$Y$2:$Y12,"Coverage",Data_Summary!$AA$2:$AA12,Data_Summary!AA12)=1,Data_Summary!AA12,""))) | AK11: =IF(AJ11="","",COUNTIFS(Data_Summary!$Y$2:$Y$20001,"Coverage",Data_Summary!$AA$2:$AA$20001,AJ11))
A12: Neutral Sentiment | B12: =COUNTIF(RawData[Overall Sentiment],"Neutral") -> 77 | G12: Induction | H12: =COUNTIF(RawData[Engagement Type],G12) -> 5 | Q12: {=IFERROR(INDEX($AJ$2:$AJ$599,MATCH(1,($AK$2:$AK$599=R12)*(COUNTIF($Q$3:$Q11,$AJ$2:$AJ$599)=0)*($AJ$2:$AJ$599<>""),0)),"")} -> Queries related to BGV check | R12: =IFERROR(LARGE($AK$2:$AK$599,10),"") -> 10 | S12: =IF(Q12="","",IFERROR(R12/$B$3,0)) -> 0.033333333 | T12: {=IF(Q12="","",IFERROR(INDEX(SummaryData[Engagement Type],MATCH(TRIM(Q12),TRIM(SummaryData[Statement]),0)),""))} -> Induction | W12: Business Wait Connect | X12: {=SUMPRODUCT((TRIM(RawData[Career])=TRIM(W12))*1)} -> 1 | AA12: {=IFERROR(INDEX($AM$2:$AM$199,MATCH(1,($AN$2:$AN$199=AB12)*(COUNTIF($AA$3:$AA11,$AM$2:$AM$199)=0)*($AM$2:$AM$199<>""),0)),"")} -> Top Talent FGD Connect | AB12: =IFERROR(LARGE($AN$2:$AN$199,10),"") -> 7 | AD12: =IF(Calc!Q12="","",Calc!Q12) -> Queries related to BGV check | AE12: =IF(Calc!Q12="","",Calc!R12) -> 10 | AG12: {=IFERROR(INDEX($G$3:$G$15,MATCH(1,(($H$3:$H$15)=AH12)*(COUNTIF($AG$3:$AG11,$G$3:$G$15)=0),0)),"")} -> Leadership Connect | AH12: =IFERROR(LARGE($H$3:$H$15,10),"") -> 4 | AJ12: =IF(Data_Summary!Y13<>"Coverage","",IF(Data_Summary!AA13="","",IF(COUNTIFS(Data_Summary!$Y$2:$Y13,"Coverage",Data_Summary!$AA$2:$AA13,Data_Summary!AA13)=1,Data_Summary!AA13,""))) -> Visibility on Allocation & Demand | AK12: =IF(AJ12="","",COUNTIFS(Data_Summary!$Y$2:$Y$20001,"Coverage",Data_Summary!$AA$2:$AA$20001,AJ12)) -> 7 | AM12: =IF(Data_Insight!X12="","",IF(COUNTIF(Data_Insight!$X$2:$X12,Data_Insight!X12)=1,Data_Insight!X12,"")) -> Top Talent FGD Connect | AN12: =IF(AM12="","",COUNTIF(Data_Insight!$X$2:$X$20001,AM12)) -> 7
A13: Action Closure % | B13: =IFERROR(COUNTIF(RawData[Status],"Closed")/COUNTA(RawData[ID])*100,0) -> 71.333333 | G13: New Joiner Induction | H13: =COUNTIF(RawData[Engagement Type],G13) -> 4 | Q13: {=IFERROR(INDEX($AJ$2:$AJ$599,MATCH(1,($AK$2:$AK$599=R13)*(COUNTIF($Q$3:$Q12,$AJ$2:$AJ$599)=0)*($AJ$2:$AJ$599<>""),0)),"")} -> Engagement with Leadership & Confidence Level | R13: =IFERROR(LARGE($AK$2:$AK$599,11),"") -> 10 | S13: =IF(Q13="","",IFERROR(R13/$B$3,0)) -> 0.033333333 | T13: {=IF(Q13="","",IFERROR(INDEX(SummaryData[Engagement Type],MATCH(TRIM(Q13),TRIM(SummaryData[Statement]),0)),""))} -> FGD | W13: Top Talent Connect (One to One) (Exclusives/Ascend/WLP/Mentor) | X13: {=SUMPRODUCT((TRIM(RawData[Career])=TRIM(W13))*1)} -> 0 | AA13: {=IFERROR(INDEX($AM$2:$AM$199,MATCH(1,($AN$2:$AN$199=AB13)*(COUNTIF($AA$3:$AA12,$AM$2:$AM$199)=0)*($AM$2:$AM$199<>""),0)),"")} -> Leadership Connect | AB13: =IFERROR(LARGE($AN$2:$AN$199,11),"") -> 7 | AG13: {=IFERROR(INDEX($G$3:$G$15,MATCH(1,(($H$3:$H$15)=AH13)*(COUNTIF($AG$3:$AG12,$G$3:$G$15)=0),0)),"")} -> Monthly Cadence | AH13: =IFERROR(LARGE($H$3:$H$15,11),"") -> 3 | AJ13: =IF(Data_Summary!Y14<>"Coverage","",IF(Data_Summary!AA14="","",IF(COUNTIFS(Data_Summary!$Y$2:$Y14,"Coverage",Data_Summary!$AA$2:$AA14,Data_Summary!AA14)=1,Data_Summary!AA14,""))) | AK13: =IF(AJ13="","",COUNTIFS(Data_Summary!$Y$2:$Y$20001,"Coverage",Data_Summary!$AA$2:$AA$20001,AJ13)) | AM13: =IF(Data_Insight!X13="","",IF(COUNTIF(Data_Insight!$X$2:$X13,Data_Insight!X13)=1,Data_Insight!X13,"")) -> Leadership Connect | AN13: =IF(AM13="","",COUNTIF(Data_Insight!$X$2:$X$20001,AM13)) -> 7
A14: Sentiment Score | B14: =IFERROR((COUNTIF(RawData[Overall Sentiment],"Positive")*100+COUNTIF(RawData[Overall Sentiment],"Neutral")*50+COUNTIF(RawData[Overall Sentiment],"Mixed")*25)/COUNTA(RawData[ID]),0) -> 79.333333 | G14: Leadership Connect | H14: =COUNTIF(RawData[Engagement Type],G14) -> 4 | Q14: {=IFERROR(INDEX($AJ$2:$AJ$599,MATCH(1,($AK$2:$AK$599=R14)*(COUNTIF($Q$3:$Q13,$AJ$2:$AJ$599)=0)*($AJ$2:$AJ$599<>""),0)),"")} -> Role Confidence Level | R14: =IFERROR(LARGE($AK$2:$AK$599,12),"") -> 9 | S14: =IF(Q14="","",IFERROR(R14/$B$3,0)) -> 0.03 | T14: {=IF(Q14="","",IFERROR(INDEX(SummaryData[Engagement Type],MATCH(TRIM(Q14),TRIM(SummaryData[Statement]),0)),""))} -> Large Connect | W14: Top Talent FGD Connect (Exclusives/Ascend/WLP/Mentor) | X14: {=SUMPRODUCT((TRIM(RawData[Career])=TRIM(W14))*1)} -> 0 | AA14: {=IFERROR(INDEX($AM$2:$AM$199,MATCH(1,($AN$2:$AN$199=AB14)*(COUNTIF($AA$3:$AA13,$AM$2:$AM$199)=0)*($AM$2:$AM$199<>""),0)),"")} -> Top Talent Connect | AB14: =IFERROR(LARGE($AN$2:$AN$199,12),"") -> 6 | AG14: {=IFERROR(INDEX($G$3:$G$15,MATCH(1,(($H$3:$H$15)=AH14)*(COUNTIF($AG$3:$AG13,$G$3:$G$15)=0),0)),"")} -> Connect with Women Associates | AH14: =IFERROR(LARGE($H$3:$H$15,12),"") -> 0 | AJ14: =IF(Data_Summary!Y15<>"Coverage","",IF(Data_Summary!AA15="","",IF(COUNTIFS(Data_Summary!$Y$2:$Y15,"Coverage",Data_Summary!$AA$2:$AA15,Data_Summary!AA15)=1,Data_Summary!AA15,""))) | AK14: =IF(AJ14="","",COUNTIFS(Data_Summary!$Y$2:$Y$20001,"Coverage",Data_Summary!$AA$2:$AA$20001,AJ14)) | AM14: =IF(Data_Insight!X14="","",IF(COUNTIF(Data_Insight!$X$2:$X14,Data_Insight!X14)=1,Data_Insight!X14,"")) -> New Joiner Connect (30 Days) | AN14: =IF(AM14="","",COUNTIF(Data_Insight!$X$2:$X$20001,AM14)) -> 19
A15: Total BHRs | B15: {=SUMPRODUCT((RawData[BHR Name]<>"")/COUNTIF(RawData[BHR Name],RawData[BHR Name]&""))} -> 299 | G15: Monthly Cadence | H15: =COUNTIF(RawData[Engagement Type],G15) -> 3 | Q15: {=IFERROR(INDEX($AJ$2:$AJ$599,MATCH(1,($AK$2:$AK$599=R15)*(COUNTIF($Q$3:$Q14,$AJ$2:$AJ$599)=0)*($AJ$2:$AJ$599<>""),0)),"")} -> Engagement & Belonging | R15: =IFERROR(LARGE($AK$2:$AK$599,13),"") -> 9 | S15: =IF(Q15="","",IFERROR(R15/$B$3,0)) -> 0.03 | T15: {=IF(Q15="","",IFERROR(INDEX(SummaryData[Engagement Type],MATCH(TRIM(Q15),TRIM(SummaryData[Statement]),0)),""))} -> FGD | W15: LSA Connect | X15: {=SUMPRODUCT((TRIM(RawData[Recognition])=TRIM(W15))*1)} -> 3 | AA15: {=IFERROR(INDEX($AM$2:$AM$199,MATCH(1,($AN$2:$AN$199=AB15)*(COUNTIF($AA$3:$AA14,$AM$2:$AM$199)=0)*($AM$2:$AM$199<>""),0)),"")} -> ELTP Connect (<6m) | AB15: =IFERROR(LARGE($AN$2:$AN$199,13),"") -> 6 | AG15: {=IFERROR(INDEX($G$3:$G$15,MATCH(1,(($H$3:$H$15)=AH15)*(COUNTIF($AG$3:$AG14,$G$3:$G$15)=0),0)),"")} -> Account Based | AH15: =IFERROR(LARGE($H$3:$H$15,13),"") -> 0 | AJ15: =IF(Data_Summary!Y16<>"Coverage","",IF(Data_Summary!AA16="","",IF(COUNTIFS(Data_Summary!$Y$2:$Y16,"Coverage",Data_Summary!$AA$2:$AA16,Data_Summary!AA16)=1,Data_Summary!AA16,""))) | AK15: =IF(AJ15="","",COUNTIFS(Data_Summary!$Y$2:$Y$20001,"Coverage",Data_Summary!$AA$2:$AA$20001,AJ15)) | AM15: =IF(Data_Insight!X15="","",IF(COUNTIF(Data_Insight!$X$2:$X15,Data_Insight!X15)=1,Data_Insight!X15,"")) | AN15: =IF(AM15="","",COUNTIF(Data_Insight!$X$2:$X$20001,AM15))
A16: Total SLs | B16: =IFERROR(SUMPRODUCT((RawData[Service Line]<>"")/COUNTIF(RawData[Service Line],RawData[Service Line]&"")),0) -> 10 | Q16: {=IFERROR(INDEX($AJ$2:$AJ$599,MATCH(1,($AK$2:$AK$599=R16)*(COUNTIF($Q$3:$Q15,$AJ$2:$AJ$599)=0)*($AJ$2:$AJ$599<>""),0)),"")} -> Business & Practice Awareness | R16: =IFERROR(LARGE($AK$2:$AK$599,14),"") -> 8 | S16: =IF(Q16="","",IFERROR(R16/$B$3,0)) -> 0.026666667 | T16: {=IF(Q16="","",IFERROR(INDEX(SummaryData[Engagement Type],MATCH(TRIM(Q16),TRIM(SummaryData[Statement]),0)),""))} -> Large Connect | W16: Exclusives Award Ceremony (Not part of Townhall) | X16: {=SUMPRODUCT((TRIM(RawData[Recognition])=TRIM(W16))*1)} -> 0 | AA16: {=IFERROR(INDEX($AM$2:$AM$199,MATCH(1,($AN$2:$AN$199=AB16)*(COUNTIF($AA$3:$AA15,$AM$2:$AM$199)=0)*($AM$2:$AM$199<>""),0)),"")} -> ELTP Connect (Practice Level) | AB16: =IFERROR(LARGE($AN$2:$AN$199,14),"") -> 5 | AJ16: =IF(Data_Summary!Y17<>"Coverage","",IF(Data_Summary!AA17="","",IF(COUNTIFS(Data_Summary!$Y$2:$Y17,"Coverage",Data_Summary!$AA$2:$AA17,Data_Summary!AA17)=1,Data_Summary!AA17,""))) | AK16: =IF(AJ16="","",COUNTIFS(Data_Summary!$Y$2:$Y$20001,"Coverage",Data_Summary!$AA$2:$AA$20001,AJ16)) | AM16: =IF(Data_Insight!X16="","",IF(COUNTIF(Data_Insight!$X$2:$X16,Data_Insight!X16)=1,Data_Insight!X16,"")) | AN16: =IF(AM16="","",COUNTIF(Data_Insight!$X$2:$X$20001,AM16))
A17: Most Active SL | B17: {=IFERROR(INDEX(RawData[Service Line],MATCH(MAX(COUNTIF(RawData[Service Line],RawData[Service Line])),COUNTIF(RawData[Service Line],RawData[Service Line]),0)),"N/A")} -> DEA Service Line | Q17: {=IFERROR(INDEX($AJ$2:$AJ$599,MATCH(1,($AK$2:$AK$599=R17)*(COUNTIF($Q$3:$Q16,$AJ$2:$AJ$599)=0)*($AJ$2:$AJ$599<>""),0)),"")} -> Project Allocation Clarity | R17: =IFERROR(LARGE($AK$2:$AK$599,15),"") -> 8 | S17: =IF(Q17="","",IFERROR(R17/$B$3,0)) -> 0.026666667 | T17: {=IF(Q17="","",IFERROR(INDEX(SummaryData[Engagement Type],MATCH(TRIM(Q17),TRIM(SummaryData[Statement]),0)),""))} -> 1:1 | W17: ELTP Connect - Practice Level | X17: {=SUMPRODUCT((TRIM(RawData[Empowerment])=TRIM(W17))*1)} -> 0 | AA17: {=IFERROR(INDEX($AM$2:$AM$199,MATCH(1,($AN$2:$AN$199=AB17)*(COUNTIF($AA$3:$AA16,$AM$2:$AM$199)=0)*($AM$2:$AM$199<>""),0)),"")} -> Exclusive Award Ceremony | AB17: =IFERROR(LARGE($AN$2:$AN$199,15),"") -> 5 | AJ17: =IF(Data_Summary!Y18<>"Coverage","",IF(Data_Summary!AA18="","",IF(COUNTIFS(Data_Summary!$Y$2:$Y18,"Coverage",Data_Summary!$AA$2:$AA18,Data_Summary!AA18)=1,Data_Summary!AA18,""))) -> General wellbeing check-in | AK17: =IF(AJ17="","",COUNTIFS(Data_Summary!$Y$2:$Y$20001,"Coverage",Data_Summary!$AA$2:$AA$20001,AJ17)) -> 16 | AM17: =IF(Data_Insight!X17="","",IF(COUNTIF(Data_Insight!$X$2:$X17,Data_Insight!X17)=1,Data_Insight!X17,"")) -> HR Connect (Project Wise) | AN17: =IF(AM17="","",COUNTIF(Data_Insight!$X$2:$X$20001,AM17)) -> 30
A18: IBU/Practice/Location | B18: {=IFERROR(INDEX(RawData[IBU/Practice/Location],MATCH(MAX(COUNTIF(RawData[IBU/Practice/Location],RawData[IBU/Practice/Location])),COUNTIF(RawData[IBU/Practice/Location],RawData[IBU/Practice/Location]),0)),"N/A")} -> IBU Specific Connect | Q18: {=IFERROR(INDEX($AJ$2:$AJ$599,MATCH(1,($AK$2:$AK$599=R18)*(COUNTIF($Q$3:$Q17,$AJ$2:$AJ$599)=0)*($AJ$2:$AJ$599<>""),0)),"")} -> Career Path Visibility | R18: =IFERROR(LARGE($AK$2:$AK$599,16),"") -> 8 | S18: =IF(Q18="","",IFERROR(R18/$B$3,0)) -> 0.026666667 | T18: {=IF(Q18="","",IFERROR(INDEX(SummaryData[Engagement Type],MATCH(TRIM(Q18),TRIM(SummaryData[Statement]),0)),""))} -> Large Connect | W18: ELTP Connect (<6m) | X18: {=SUMPRODUCT((TRIM(RawData[Empowerment])=TRIM(W18))*1)} -> 0 | AJ18: =IF(Data_Summary!Y19<>"Coverage","",IF(Data_Summary!AA19="","",IF(COUNTIFS(Data_Summary!$Y$2:$Y19,"Coverage",Data_Summary!$AA$2:$AA19,Data_Summary!AA19)=1,Data_Summary!AA19,""))) | AK18: =IF(AJ18="","",COUNTIFS(Data_Summary!$Y$2:$Y$20001,"Coverage",Data_Summary!$AA$2:$AA$20001,AJ18)) | AM18: =IF(Data_Insight!X18="","",IF(COUNTIF(Data_Insight!$X$2:$X18,Data_Insight!X18)=1,Data_Insight!X18,"")) -> ELTP Connect (12-24m) | AN18: =IF(AM18="","",COUNTIF(Data_Insight!$X$2:$X$20001,AM18)) -> 8
A19: Top CARES Lever | B19: {=IFERROR(INDEX(RawData[CARES Framework],MATCH(MAX(COUNTIF(RawData[CARES Framework],RawData[CARES Framework])),COUNTIF(RawData[CARES Framework],RawData[CARES Framework]),0)),"N/A")} -> Alignment | Q19: {=IFERROR(INDEX($AJ$2:$AJ$599,MATCH(1,($AK$2:$AK$599=R19)*(COUNTIF($Q$3:$Q18,$AJ$2:$AJ$599)=0)*($AJ$2:$AJ$599<>""),0)),"")} -> Policy & Process Clarity | R19: =IFERROR(LARGE($AK$2:$AK$599,17),"") -> 8 | S19: =IF(Q19="","",IFERROR(R19/$B$3,0)) -> 0.026666667 | T19: {=IF(Q19="","",IFERROR(INDEX(SummaryData[Engagement Type],MATCH(TRIM(Q19),TRIM(SummaryData[Statement]),0)),""))} -> Large Connect | W19: ELTP Connect (6- 12m) | X19: {=SUMPRODUCT((TRIM(RawData[Empowerment])=TRIM(W19))*1)} -> 0 | AJ19: =IF(Data_Summary!Y20<>"Coverage","",IF(Data_Summary!AA20="","",IF(COUNTIFS(Data_Summary!$Y$2:$Y20,"Coverage",Data_Summary!$AA$2:$AA20,Data_Summary!AA20)=1,Data_Summary!AA20,""))) | AK19: =IF(AJ19="","",COUNTIFS(Data_Summary!$Y$2:$Y$20001,"Coverage",Data_Summary!$AA$2:$AA$20001,AJ19)) | AM19: =IF(Data_Insight!X19="","",IF(COUNTIF(Data_Insight!$X$2:$X19,Data_Insight!X19)=1,Data_Insight!X19,"")) | AN19: =IF(AM19="","",COUNTIF(Data_Insight!$X$2:$X$20001,AM19))
A20: Open+InProgress | B20: =COUNTIF(RawData[Status],"Open")+COUNTIF(RawData[Status],"In-progress") -> 86 | Q20: {=IFERROR(INDEX($AJ$2:$AJ$599,MATCH(1,($AK$2:$AK$599=R20)*(COUNTIF($Q$3:$Q19,$AJ$2:$AJ$599)=0)*($AJ$2:$AJ$599<>""),0)),"")} -> Induction Effectiveness | R20: =IFERROR(LARGE($AK$2:$AK$599,18),"") -> 8 | S20: =IF(Q20="","",IFERROR(R20/$B$3,0)) -> 0.026666667 | T20: {=IF(Q20="","",IFERROR(INDEX(SummaryData[Engagement Type],MATCH(TRIM(Q20),TRIM(SummaryData[Statement]),0)),""))} -> FGD | W20: ELTP Connect (12-24m) | X20: {=SUMPRODUCT((TRIM(RawData[Empowerment])=TRIM(W20))*1)} -> 0 | AJ20: =IF(Data_Summary!Y21<>"Coverage","",IF(Data_Summary!AA21="","",IF(COUNTIFS(Data_Summary!$Y$2:$Y21,"Coverage",Data_Summary!$AA$2:$AA21,Data_Summary!AA21)=1,Data_Summary!AA21,""))) | AK20: =IF(AJ20="","",COUNTIFS(Data_Summary!$Y$2:$Y$20001,"Coverage",Data_Summary!$AA$2:$AA$20001,AJ20)) | AM20: =IF(Data_Insight!X20="","",IF(COUNTIF(Data_Insight!$X$2:$X20,Data_Insight!X20)=1,Data_Insight!X20,"")) -> Josh (Fun Engagements) | AN20: =IF(AM20="","",COUNTIF(Data_Insight!$X$2:$X$20001,AM20)) -> 9
Q21: {=IFERROR(INDEX($AJ$2:$AJ$599,MATCH(1,($AK$2:$AK$599=R21)*(COUNTIF($Q$3:$Q20,$AJ$2:$AJ$599)=0)*($AJ$2:$AJ$599<>""),0)),"")} -> Career Visibility & Skill Roadmap | R21: =IFERROR(LARGE($AK$2:$AK$599,19),"") -> 7 | S21: =IF(Q21="","",IFERROR(R21/$B$3,0)) -> 0.023333333 | T21: {=IF(Q21="","",IFERROR(INDEX(SummaryData[Engagement Type],MATCH(TRIM(Q21),TRIM(SummaryData[Statement]),0)),""))} -> Large Connect | W21: ML Returnee Connect | X21: {=SUMPRODUCT((TRIM(RawData[Empowerment])=TRIM(W21))*1)} -> 0 | AJ21: =IF(Data_Summary!Y22<>"Coverage","",IF(Data_Summary!AA22="","",IF(COUNTIFS(Data_Summary!$Y$2:$Y22,"Coverage",Data_Summary!$AA$2:$AA22,Data_Summary!AA22)=1,Data_Summary!AA22,""))) | AK21: =IF(AJ21="","",COUNTIFS(Data_Summary!$Y$2:$Y$20001,"Coverage",Data_Summary!$AA$2:$AA$20001,AJ21)) | AM21: =IF(Data_Insight!X21="","",IF(COUNTIF(Data_Insight!$X$2:$X21,Data_Insight!X21)=1,Data_Insight!X21,"")) -> New Joiner Connect (60 Days) | AN21: =IF(AM21="","",COUNTIF(Data_Insight!$X$2:$X$20001,AM21)) -> 22
A22: SENTIMENT | Q22: {=IFERROR(INDEX($AJ$2:$AJ$599,MATCH(1,($AK$2:$AK$599=R22)*(COUNTIF($Q$3:$Q21,$AJ$2:$AJ$599)=0)*($AJ$2:$AJ$599<>""),0)),"")} -> Visibility on Allocation & Demand | R22: =IFERROR(LARGE($AK$2:$AK$599,20),"") -> 7 | S22: =IF(Q22="","",IFERROR(R22/$B$3,0)) -> 0.023333333 | T22: {=IF(Q22="","",IFERROR(INDEX(SummaryData[Engagement Type],MATCH(TRIM(Q22),TRIM(SummaryData[Statement]),0)),""))} -> Large Connect | W22: Women Associate Connect | X22: {=SUMPRODUCT((TRIM(RawData[Empowerment])=TRIM(W22))*1)} -> 15 | AJ22: =IF(Data_Summary!Y23<>"Coverage","",IF(Data_Summary!AA23="","",IF(COUNTIFS(Data_Summary!$Y$2:$Y23,"Coverage",Data_Summary!$AA$2:$AA23,Data_Summary!AA23)=1,Data_Summary!AA23,""))) -> Connect for recognition | AK22: =IF(AJ22="","",COUNTIFS(Data_Summary!$Y$2:$Y$20001,"Coverage",Data_Summary!$AA$2:$AA$20001,AJ22)) -> 2 | AM22: =IF(Data_Insight!X22="","",IF(COUNTIF(Data_Insight!$X$2:$X22,Data_Insight!X22)=1,Data_Insight!X22,"")) -> Top Talent Connect | AN22: =IF(AM22="","",COUNTIF(Data_Insight!$X$2:$X$20001,AM22)) -> 6
A23: Label | B23: Count | Q23: {=IFERROR(INDEX($AJ$2:$AJ$599,MATCH(1,($AK$2:$AK$599=R23)*(COUNTIF($Q$3:$Q22,$AJ$2:$AJ$599)=0)*($AJ$2:$AJ$599<>""),0)),"")} -> Business Context & Org Awareness | R23: =IFERROR(LARGE($AK$2:$AK$599,21),"") -> 7 | S23: =IF(Q23="","",IFERROR(R23/$B$3,0)) -> 0.023333333 | T23: {=IF(Q23="","",IFERROR(INDEX(SummaryData[Engagement Type],MATCH(TRIM(Q23),TRIM(SummaryData[Statement]),0)),""))} -> FGD | W23: Top Talent FGD Connect (Ascend/WLP/Mentor) | X23: {=SUMPRODUCT((TRIM(RawData[Empowerment])=TRIM(W23))*1)} -> 0 | AJ23: =IF(Data_Summary!Y24<>"Coverage","",IF(Data_Summary!AA24="","",IF(COUNTIFS(Data_Summary!$Y$2:$Y24,"Coverage",Data_Summary!$AA$2:$AA24,Data_Summary!AA24)=1,Data_Summary!AA24,""))) -> Clarity On Role-based Learning Expectations | AK23: =IF(AJ23="","",COUNTIFS(Data_Summary!$Y$2:$Y$20001,"Coverage",Data_Summary!$AA$2:$AA$20001,AJ23)) -> 2 | AM23: =IF(Data_Insight!X23="","",IF(COUNTIF(Data_Insight!$X$2:$X23,Data_Insight!X23)=1,Data_Insight!X23,"")) | AN23: =IF(AM23="","",COUNTIF(Data_Insight!$X$2:$X$20001,AM23))
A24: Positive | B24: =COUNTIF(RawData[Overall Sentiment],A24) -> 193 | Q24: {=IFERROR(INDEX($AJ$2:$AJ$599,MATCH(1,($AK$2:$AK$599=R24)*(COUNTIF($Q$3:$Q23,$AJ$2:$AJ$599)=0)*($AJ$2:$AJ$599<>""),0)),"")} -> Work-Life Balance & Flexibility | R24: =IFERROR(LARGE($AK$2:$AK$599,22),"") -> 7 | S24: =IF(Q24="","",IFERROR(R24/$B$3,0)) -> 0.023333333 | T24: {=IF(Q24="","",IFERROR(INDEX(SummaryData[Engagement Type],MATCH(TRIM(Q24),TRIM(SummaryData[Statement]),0)),""))} -> FGD | W24: Leadership Connect | X24: {=SUMPRODUCT((TRIM(RawData[Empowerment])=TRIM(W24))*1)} -> 7 | AJ24: =IF(Data_Summary!Y25<>"Coverage","",IF(Data_Summary!AA25="","",IF(COUNTIFS(Data_Summary!$Y$2:$Y25,"Coverage",Data_Summary!$AA$2:$AA25,Data_Summary!AA25)=1,Data_Summary!AA25,""))) -> On Hybrid/WFO Rules And Monthly Compliance Expectations | AK24: =IF(AJ24="","",COUNTIFS(Data_Summary!$Y$2:$Y$20001,"Coverage",Data_Summary!$AA$2:$AA$20001,AJ24)) -> 5 | AM24: =IF(Data_Insight!X24="","",IF(COUNTIF(Data_Insight!$X$2:$X24,Data_Insight!X24)=1,Data_Insight!X24,"")) | AN24: =IF(AM24="","",COUNTIF(Data_Insight!$X$2:$X$20001,AM24))
A25: Neutral | B25: =COUNTIF(RawData[Overall Sentiment],A25) -> 77 | Q25: {=IFERROR(INDEX($AJ$2:$AJ$599,MATCH(1,($AK$2:$AK$599=R25)*(COUNTIF($Q$3:$Q24,$AJ$2:$AJ$599)=0)*($AJ$2:$AJ$599<>""),0)),"")} -> Role Expectation Clarity | R25: =IFERROR(LARGE($AK$2:$AK$599,23),"") -> 7 | S25: =IF(Q25="","",IFERROR(R25/$B$3,0)) -> 0.023333333 | T25: {=IF(Q25="","",IFERROR(INDEX(SummaryData[Engagement Type],MATCH(TRIM(Q25),TRIM(SummaryData[Statement]),0)),""))} -> FGD | W25: IBU Cadence Connect | X25: {=SUMPRODUCT((TRIM(RawData[Empowerment])=TRIM(W25))*1)} -> 0 | AJ25: =IF(Data_Summary!Y26<>"Coverage","",IF(Data_Summary!AA26="","",IF(COUNTIFS(Data_Summary!$Y$2:$Y26,"Coverage",Data_Summary!$AA$2:$AA26,Data_Summary!AA26)=1,Data_Summary!AA26,""))) | AK25: =IF(AJ25="","",COUNTIFS(Data_Summary!$Y$2:$Y$20001,"Coverage",Data_Summary!$AA$2:$AA$20001,AJ25)) | AM25: =IF(Data_Insight!X25="","",IF(COUNTIF(Data_Insight!$X$2:$X25,Data_Insight!X25)=1,Data_Insight!X25,"")) -> ELTP Connect (Practice Level) | AN25: =IF(AM25="","",COUNTIF(Data_Insight!$X$2:$X$20001,AM25)) -> 5
A26: Mixed | B26: =COUNTIF(RawData[Overall Sentiment],A26) -> 26 | Q26: {=IFERROR(INDEX($AJ$2:$AJ$599,MATCH(1,($AK$2:$AK$599=R26)*(COUNTIF($Q$3:$Q25,$AJ$2:$AJ$599)=0)*($AJ$2:$AJ$599<>""),0)),"")} -> Initial Engagement Level | R26: =IFERROR(LARGE($AK$2:$AK$599,24),"") -> 7 | S26: =IF(Q26="","",IFERROR(R26/$B$3,0)) -> 0.023333333 | T26: {=IF(Q26="","",IFERROR(INDEX(SummaryData[Engagement Type],MATCH(TRIM(Q26),TRIM(SummaryData[Statement]),0)),""))} -> FGD | W26: Josh (Fun Engagements) | X26: {=SUMPRODUCT((TRIM(RawData[Strive])=TRIM(W26))*1)} -> 9 | AJ26: =IF(Data_Summary!Y27<>"Coverage","",IF(Data_Summary!AA27="","",IF(COUNTIFS(Data_Summary!$Y$2:$Y27,"Coverage",Data_Summary!$AA$2:$AA27,Data_Summary!AA27)=1,Data_Summary!AA27,""))) | AK26: =IF(AJ26="","",COUNTIFS(Data_Summary!$Y$2:$Y$20001,"Coverage",Data_Summary!$AA$2:$AA$20001,AJ26)) | AM26: =IF(Data_Insight!X26="","",IF(COUNTIF(Data_Insight!$X$2:$X26,Data_Insight!X26)=1,Data_Insight!X26,"")) -> New Joiner Connect (90 Days) | AN26: =IF(AM26="","",COUNTIF(Data_Insight!$X$2:$X$20001,AM26)) -> 16
Q27: {=IFERROR(INDEX($AJ$2:$AJ$599,MATCH(1,($AK$2:$AK$599=R27)*(COUNTIF($Q$3:$Q26,$AJ$2:$AJ$599)=0)*($AJ$2:$AJ$599<>""),0)),"")} -> Career Progression & Next-Level Readiness | R27: =IFERROR(LARGE($AK$2:$AK$599,25),"") -> 7 | S27: =IF(Q27="","",IFERROR(R27/$B$3,0)) -> 0.023333333 | T27: {=IF(Q27="","",IFERROR(INDEX(SummaryData[Engagement Type],MATCH(TRIM(Q27),TRIM(SummaryData[Statement]),0)),""))} -> Large Connect | W27: Wellness Session | X27: {=SUMPRODUCT((TRIM(RawData[Strive])=TRIM(W27))*1)} -> 3 | AJ27: =IF(Data_Summary!Y28<>"Coverage","",IF(Data_Summary!AA28="","",IF(COUNTIFS(Data_Summary!$Y$2:$Y28,"Coverage",Data_Summary!$AA$2:$AA28,Data_Summary!AA28)=1,Data_Summary!AA28,""))) | AK27: =IF(AJ27="","",COUNTIFS(Data_Summary!$Y$2:$Y$20001,"Coverage",Data_Summary!$AA$2:$AA$20001,AJ27)) | AM27: =IF(Data_Insight!X27="","",IF(COUNTIF(Data_Insight!$X$2:$X27,Data_Insight!X27)=1,Data_Insight!X27,"")) | AN27: =IF(AM27="","",COUNTIF(Data_Insight!$X$2:$X$20001,AM27))
A28: SEVERITY | Q28: {=IFERROR(INDEX($AJ$2:$AJ$599,MATCH(1,($AK$2:$AK$599=R28)*(COUNTIF($Q$3:$Q27,$AJ$2:$AJ$599)=0)*($AJ$2:$AJ$599<>""),0)),"")} -> Manager Connect Effectiveness | R28: =IFERROR(LARGE($AK$2:$AK$599,26),"") -> 7 | S28: =IF(Q28="","",IFERROR(R28/$B$3,0)) -> 0.023333333 | T28: {=IF(Q28="","",IFERROR(INDEX(SummaryData[Engagement Type],MATCH(TRIM(Q28),TRIM(SummaryData[Statement]),0)),""))} -> 1:1 | W28: ISR Activity | X28: {=SUMPRODUCT((TRIM(RawData[Strive])=TRIM(W28))*1)} -> 3 | AJ28: =IF(Data_Summary!Y29<>"Coverage","",IF(Data_Summary!AA29="","",IF(COUNTIFS(Data_Summary!$Y$2:$Y29,"Coverage",Data_Summary!$AA$2:$AA29,Data_Summary!AA29)=1,Data_Summary!AA29,""))) -> Business Context & Org Awareness | AK28: =IF(AJ28="","",COUNTIFS(Data_Summary!$Y$2:$Y$20001,"Coverage",Data_Summary!$AA$2:$AA$20001,AJ28)) -> 7 | AM28: =IF(Data_Insight!X28="","",IF(COUNTIF(Data_Insight!$X$2:$X28,Data_Insight!X28)=1,Data_Insight!X28,"")) | AN28: =IF(AM28="","",COUNTIF(Data_Insight!$X$2:$X$20001,AM28))
A29: Label | B29: Count | Q29: {=IFERROR(INDEX($AJ$2:$AJ$599,MATCH(1,($AK$2:$AK$599=R29)*(COUNTIF($Q$3:$Q28,$AJ$2:$AJ$599)=0)*($AJ$2:$AJ$599<>""),0)),"")} -> Internal Growth Opportunities | R29: =IFERROR(LARGE($AK$2:$AK$599,27),"") -> 7 | S29: =IF(Q29="","",IFERROR(R29/$B$3,0)) -> 0.023333333 | T29: {=IF(Q29="","",IFERROR(INDEX(SummaryData[Engagement Type],MATCH(TRIM(Q29),TRIM(SummaryData[Statement]),0)),""))} -> 1:1 | AJ29: =IF(Data_Summary!Y30<>"Coverage","",IF(Data_Summary!AA30="","",IF(COUNTIFS(Data_Summary!$Y$2:$Y30,"Coverage",Data_Summary!$AA$2:$AA30,Data_Summary!AA30)=1,Data_Summary!AA30,""))) | AK29: =IF(AJ29="","",COUNTIFS(Data_Summary!$Y$2:$Y$20001,"Coverage",Data_Summary!$AA$2:$AA$20001,AJ29)) | AM29: =IF(Data_Insight!X29="","",IF(COUNTIF(Data_Insight!$X$2:$X29,Data_Insight!X29)=1,Data_Insight!X29,"")) | AN29: =IF(AM29="","",COUNTIF(Data_Insight!$X$2:$X$20001,AM29))
A30: High | B30: =ROUND(COUNTIF(RawData[Severity],A30)/COUNTA(RawData[Severity]),2) -> 0.21 | Q30: {=IFERROR(INDEX($AJ$2:$AJ$599,MATCH(1,($AK$2:$AK$599=R30)*(COUNTIF($Q$3:$Q29,$AJ$2:$AJ$599)=0)*($AJ$2:$AJ$599<>""),0)),"")} -> Leadership Communication & Q&A Effectiveness | R30: =IFERROR(LARGE($AK$2:$AK$599,28),"") -> 7 | S30: =IF(Q30="","",IFERROR(R30/$B$3,0)) -> 0.023333333 | T30: {=IF(Q30="","",IFERROR(INDEX(SummaryData[Engagement Type],MATCH(TRIM(Q30),TRIM(SummaryData[Statement]),0)),""))} -> 1:1 | AJ30: =IF(Data_Summary!Y31<>"Coverage","",IF(Data_Summary!AA31="","",IF(COUNTIFS(Data_Summary!$Y$2:$Y31,"Coverage",Data_Summary!$AA$2:$AA31,Data_Summary!AA31)=1,Data_Summary!AA31,""))) | AK30: =IF(AJ30="","",COUNTIFS(Data_Summary!$Y$2:$Y$20001,"Coverage",Data_Summary!$AA$2:$AA$20001,AJ30)) | AM30: =IF(Data_Insight!X30="","",IF(COUNTIF(Data_Insight!$X$2:$X30,Data_Insight!X30)=1,Data_Insight!X30,"")) | AN30: =IF(AM30="","",COUNTIF(Data_Insight!$X$2:$X$20001,AM30))
A31: Moderate | B31: =ROUND(COUNTIF(RawData[Severity],A31)/COUNTA(RawData[Severity]),2) -> 0.42 | Q31: {=IFERROR(INDEX($AJ$2:$AJ$599,MATCH(1,($AK$2:$AK$599=R31)*(COUNTIF($Q$3:$Q30,$AJ$2:$AJ$599)=0)*($AJ$2:$AJ$599<>""),0)),"")} -> Recognition & Engagement within Project | R31: =IFERROR(LARGE($AK$2:$AK$599,29),"") -> 7 | S31: =IF(Q31="","",IFERROR(R31/$B$3,0)) -> 0.023333333 | T31: {=IF(Q31="","",IFERROR(INDEX(SummaryData[Engagement Type],MATCH(TRIM(Q31),TRIM(SummaryData[Statement]),0)),""))} -> Large Connect | AJ31: =IF(Data_Summary!Y32<>"Coverage","",IF(Data_Summary!AA32="","",IF(COUNTIFS(Data_Summary!$Y$2:$Y32,"Coverage",Data_Summary!$AA$2:$AA32,Data_Summary!AA32)=1,Data_Summary!AA32,""))) -> Business & Practice Awareness | AK31: =IF(AJ31="","",COUNTIFS(Data_Summary!$Y$2:$Y$20001,"Coverage",Data_Summary!$AA$2:$AA$20001,AJ31)) -> 8 | AM31: =IF(Data_Insight!X31="","",IF(COUNTIF(Data_Insight!$X$2:$X31,Data_Insight!X31)=1,Data_Insight!X31,"")) | AN31: =IF(AM31="","",COUNTIF(Data_Insight!$X$2:$X$20001,AM31))
A32: Low | B32: =ROUND(COUNTIF(RawData[Severity],A32)/COUNTA(RawData[Severity]),2) -> 0.37 | Q32: {=IFERROR(INDEX($AJ$2:$AJ$599,MATCH(1,($AK$2:$AK$599=R32)*(COUNTIF($Q$3:$Q31,$AJ$2:$AJ$599)=0)*($AJ$2:$AJ$599<>""),0)),"")} -> BGV queries | R32: =IFERROR(LARGE($AK$2:$AK$599,30),"") -> 7 | S32: =IF(Q32="","",IFERROR(R32/$B$3,0)) -> 0.023333333 | T32: {=IF(Q32="","",IFERROR(INDEX(SummaryData[Engagement Type],MATCH(TRIM(Q32),TRIM(SummaryData[Statement]),0)),""))} -> FGD | AJ32: =IF(Data_Summary!Y33<>"Coverage","",IF(Data_Summary!AA33="","",IF(COUNTIFS(Data_Summary!$Y$2:$Y33,"Coverage",Data_Summary!$AA$2:$AA33,Data_Summary!AA33)=1,Data_Summary!AA33,""))) | AK32: =IF(AJ32="","",COUNTIFS(Data_Summary!$Y$2:$Y$20001,"Coverage",Data_Summary!$AA$2:$AA$20001,AJ32)) | AM32: =IF(Data_Insight!X32="","",IF(COUNTIF(Data_Insight!$X$2:$X32,Data_Insight!X32)=1,Data_Insight!X32,"")) | AN32: =IF(AM32="","",COUNTIF(Data_Insight!$X$2:$X$20001,AM32))
Q33: {=IFERROR(INDEX($AJ$2:$AJ$599,MATCH(1,($AK$2:$AK$599=R33)*(COUNTIF($Q$3:$Q32,$AJ$2:$AJ$599)=0)*($AJ$2:$AJ$599<>""),0)),"")} -> Tool & System Access | R33: =IFERROR(LARGE($AK$2:$AK$599,31),"") -> 7 | S33: =IF(Q33="","",IFERROR(R33/$B$3,0)) -> 0.023333333 | T33: {=IF(Q33="","",IFERROR(INDEX(SummaryData[Engagement Type],MATCH(TRIM(Q33),TRIM(SummaryData[Statement]),0)),""))} -> Location-Mixed | AJ33: =IF(Data_Summary!Y34<>"Coverage","",IF(Data_Summary!AA34="","",IF(COUNTIFS(Data_Summary!$Y$2:$Y34,"Coverage",Data_Summary!$AA$2:$AA34,Data_Summary!AA34)=1,Data_Summary!AA34,""))) | AK33: =IF(AJ33="","",COUNTIFS(Data_Summary!$Y$2:$Y$20001,"Coverage",Data_Summary!$AA$2:$AA$20001,AJ33)) | AM33: =IF(Data_Insight!X33="","",IF(COUNTIF(Data_Insight!$X$2:$X33,Data_Insight!X33)=1,Data_Insight!X33,"")) -> Exclusive Award Ceremony | AN33: =IF(AM33="","",COUNTIF(Data_Insight!$X$2:$X$20001,AM33)) -> 5
A34: STATUS | Q34: {=IFERROR(INDEX($AJ$2:$AJ$599,MATCH(1,($AK$2:$AK$599=R34)*(COUNTIF($Q$3:$Q33,$AJ$2:$AJ$599)=0)*($AJ$2:$AJ$599<>""),0)),"")} -> Internal Mobility / Rotation Opportunities | R34: =IFERROR(LARGE($AK$2:$AK$599,32),"") -> 6 | S34: =IF(Q34="","",IFERROR(R34/$B$3,0)) -> 0.02 | T34: {=IF(Q34="","",IFERROR(INDEX(SummaryData[Engagement Type],MATCH(TRIM(Q34),TRIM(SummaryData[Statement]),0)),""))} -> Large Connect | AJ34: =IF(Data_Summary!Y35<>"Coverage","",IF(Data_Summary!AA35="","",IF(COUNTIFS(Data_Summary!$Y$2:$Y35,"Coverage",Data_Summary!$AA$2:$AA35,Data_Summary!AA35)=1,Data_Summary!AA35,""))) | AK34: =IF(AJ34="","",COUNTIFS(Data_Summary!$Y$2:$Y$20001,"Coverage",Data_Summary!$AA$2:$AA$20001,AJ34)) | AM34: =IF(Data_Insight!X34="","",IF(COUNTIF(Data_Insight!$X$2:$X34,Data_Insight!X34)=1,Data_Insight!X34,"")) -> Skip Meeting | AN34: =IF(AM34="","",COUNTIF(Data_Insight!$X$2:$X$20001,AM34)) -> 11
A35: Label | B35: Count | Q35: {=IFERROR(INDEX($AJ$2:$AJ$599,MATCH(1,($AK$2:$AK$599=R35)*(COUNTIF($Q$3:$Q34,$AJ$2:$AJ$599)=0)*($AJ$2:$AJ$599<>""),0)),"")} -> Workload Management | R35: =IFERROR(LARGE($AK$2:$AK$599,33),"") -> 6 | S35: =IF(Q35="","",IFERROR(R35/$B$3,0)) -> 0.02 | T35: {=IF(Q35="","",IFERROR(INDEX(SummaryData[Engagement Type],MATCH(TRIM(Q35),TRIM(SummaryData[Statement]),0)),""))} -> Large Connect | AJ35: =IF(Data_Summary!Y36<>"Coverage","",IF(Data_Summary!AA36="","",IF(COUNTIFS(Data_Summary!$Y$2:$Y36,"Coverage",Data_Summary!$AA$2:$AA36,Data_Summary!AA36)=1,Data_Summary!AA36,""))) -> Clarity on expectations | AK35: =IF(AJ35="","",COUNTIFS(Data_Summary!$Y$2:$Y$20001,"Coverage",Data_Summary!$AA$2:$AA$20001,AJ35)) -> 19 | AM35: =IF(Data_Insight!X35="","",IF(COUNTIF(Data_Insight!$X$2:$X35,Data_Insight!X35)=1,Data_Insight!X35,"")) -> ELTP Connect (<6m) | AN35: =IF(AM35="","",COUNTIF(Data_Insight!$X$2:$X$20001,AM35)) -> 6
A36: Open | B36: =COUNTIF(RawData[Status],A36) -> 29 | Q36: {=IFERROR(INDEX($AJ$2:$AJ$599,MATCH(1,($AK$2:$AK$599=R36)*(COUNTIF($Q$3:$Q35,$AJ$2:$AJ$599)=0)*($AJ$2:$AJ$599<>""),0)),"")} -> Manager Effectiveness & Delegation | R36: =IFERROR(LARGE($AK$2:$AK$599,34),"") -> 6 | S36: =IF(Q36="","",IFERROR(R36/$B$3,0)) -> 0.02 | T36: {=IF(Q36="","",IFERROR(INDEX(SummaryData[Engagement Type],MATCH(TRIM(Q36),TRIM(SummaryData[Statement]),0)),""))} -> 1:1 | AJ36: =IF(Data_Summary!Y37<>"Coverage","",IF(Data_Summary!AA37="","",IF(COUNTIFS(Data_Summary!$Y$2:$Y37,"Coverage",Data_Summary!$AA$2:$AA37,Data_Summary!AA37)=1,Data_Summary!AA37,""))) | AK36: =IF(AJ36="","",COUNTIFS(Data_Summary!$Y$2:$Y$20001,"Coverage",Data_Summary!$AA$2:$AA$20001,AJ36)) | AM36: =IF(Data_Insight!X36="","",IF(COUNTIF(Data_Insight!$X$2:$X36,Data_Insight!X36)=1,Data_Insight!X36,"")) | AN36: =IF(AM36="","",COUNTIF(Data_Insight!$X$2:$X$20001,AM36))
A37: In-progress | B37: =COUNTIF(RawData[Status],A37) -> 57 | Q37: {=IFERROR(INDEX($AJ$2:$AJ$599,MATCH(1,($AK$2:$AK$599=R37)*(COUNTIF($Q$3:$Q36,$AJ$2:$AJ$599)=0)*($AJ$2:$AJ$599<>""),0)),"")} -> Recognition Visibility | R37: =IFERROR(LARGE($AK$2:$AK$599,35),"") -> 6 | S37: =IF(Q37="","",IFERROR(R37/$B$3,0)) -> 0.02 | T37: {=IF(Q37="","",IFERROR(INDEX(SummaryData[Engagement Type],MATCH(TRIM(Q37),TRIM(SummaryData[Statement]),0)),""))} -> Large Connect | AJ37: =IF(Data_Summary!Y38<>"Coverage","",IF(Data_Summary!AA38="","",IF(COUNTIFS(Data_Summary!$Y$2:$Y38,"Coverage",Data_Summary!$AA$2:$AA38,Data_Summary!AA38)=1,Data_Summary!AA38,""))) | AK37: =IF(AJ37="","",COUNTIFS(Data_Summary!$Y$2:$Y$20001,"Coverage",Data_Summary!$AA$2:$AA$20001,AJ37)) | AM37: =IF(Data_Insight!X37="","",IF(COUNTIF(Data_Insight!$X$2:$X37,Data_Insight!X37)=1,Data_Insight!X37,"")) | AN37: =IF(AM37="","",COUNTIF(Data_Insight!$X$2:$X$20001,AM37))
A38: Closed | B38: =COUNTIF(RawData[Status],A38) -> 214 | Q38: {=IFERROR(INDEX($AJ$2:$AJ$599,MATCH(1,($AK$2:$AK$599=R38)*(COUNTIF($Q$3:$Q37,$AJ$2:$AJ$599)=0)*($AJ$2:$AJ$599<>""),0)),"")} -> On Leave/comp-off Due To Client Calendar Mismatches | R38: =IFERROR(LARGE($AK$2:$AK$599,36),"") -> 6 | S38: =IF(Q38="","",IFERROR(R38/$B$3,0)) -> 0.02 | T38: {=IF(Q38="","",IFERROR(INDEX(SummaryData[Engagement Type],MATCH(TRIM(Q38),TRIM(SummaryData[Statement]),0)),""))} -> Large Connect | AJ38: =IF(Data_Summary!Y39<>"Coverage","",IF(Data_Summary!AA39="","",IF(COUNTIFS(Data_Summary!$Y$2:$Y39,"Coverage",Data_Summary!$AA$2:$AA39,Data_Summary!AA39)=1,Data_Summary!AA39,""))) | AK38: =IF(AJ38="","",COUNTIFS(Data_Summary!$Y$2:$Y$20001,"Coverage",Data_Summary!$AA$2:$AA$20001,AJ38)) | AM38: =IF(Data_Insight!X38="","",IF(COUNTIF(Data_Insight!$X$2:$X38,Data_Insight!X38)=1,Data_Insight!X38,"")) | AN38: =IF(AM38="","",COUNTIF(Data_Insight!$X$2:$X$20001,AM38))
Q39: {=IFERROR(INDEX($AJ$2:$AJ$599,MATCH(1,($AK$2:$AK$599=R39)*(COUNTIF($Q$3:$Q38,$AJ$2:$AJ$599)=0)*($AJ$2:$AJ$599<>""),0)),"")} -> Learning Curve Support | R39: =IFERROR(LARGE($AK$2:$AK$599,37),"") -> 6 | S39: =IF(Q39="","",IFERROR(R39/$B$3,0)) -> 0.02 | T39: {=IF(Q39="","",IFERROR(INDEX(SummaryData[Engagement Type],MATCH(TRIM(Q39),TRIM(SummaryData[Statement]),0)),""))} -> Location-Offshore | AJ39: =IF(Data_Summary!Y40<>"Coverage","",IF(Data_Summary!AA40="","",IF(COUNTIFS(Data_Summary!$Y$2:$Y40,"Coverage",Data_Summary!$AA$2:$AA40,Data_Summary!AA40)=1,Data_Summary!AA40,""))) | AK39: =IF(AJ39="","",COUNTIFS(Data_Summary!$Y$2:$Y$20001,"Coverage",Data_Summary!$AA$2:$AA$20001,AJ39)) | AM39: =IF(Data_Insight!X39="","",IF(COUNTIF(Data_Insight!$X$2:$X39,Data_Insight!X39)=1,Data_Insight!X39,"")) | AN39: =IF(AM39="","",COUNTIF(Data_Insight!$X$2:$X$20001,AM39))
A40: CARES | Q40: {=IFERROR(INDEX($AJ$2:$AJ$599,MATCH(1,($AK$2:$AK$599=R40)*(COUNTIF($Q$3:$Q39,$AJ$2:$AJ$599)=0)*($AJ$2:$AJ$599<>""),0)),"")} -> Long-Term Role Alignment | R40: =IFERROR(LARGE($AK$2:$AK$599,38),"") -> 6 | S40: =IF(Q40="","",IFERROR(R40/$B$3,0)) -> 0.02 | T40: {=IF(Q40="","",IFERROR(INDEX(SummaryData[Engagement Type],MATCH(TRIM(Q40),TRIM(SummaryData[Statement]),0)),""))} -> 1:1 | AJ40: =IF(Data_Summary!Y41<>"Coverage","",IF(Data_Summary!AA41="","",IF(COUNTIFS(Data_Summary!$Y$2:$Y41,"Coverage",Data_Summary!$AA$2:$AA41,Data_Summary!AA41)=1,Data_Summary!AA41,""))) -> Recognition & Visibility | AK40: =IF(AJ40="","",COUNTIFS(Data_Summary!$Y$2:$Y$20001,"Coverage",Data_Summary!$AA$2:$AA$20001,AJ40)) -> 3 | AM40: =IF(Data_Insight!X40="","",IF(COUNTIF(Data_Insight!$X$2:$X40,Data_Insight!X40)=1,Data_Insight!X40,"")) | AN40: =IF(AM40="","",COUNTIF(Data_Insight!$X$2:$X$20001,AM40))
A41: Label | B41: Count | Q41: {=IFERROR(INDEX($AJ$2:$AJ$599,MATCH(1,($AK$2:$AK$599=R41)*(COUNTIF($Q$3:$Q40,$AJ$2:$AJ$599)=0)*($AJ$2:$AJ$599<>""),0)),"")} -> Infrastructure / Workplace Enablement | R41: =IFERROR(LARGE($AK$2:$AK$599,39),"") -> 6 | S41: =IF(Q41="","",IFERROR(R41/$B$3,0)) -> 0.02 | T41: {=IF(Q41="","",IFERROR(INDEX(SummaryData[Engagement Type],MATCH(TRIM(Q41),TRIM(SummaryData[Statement]),0)),""))} -> 1:1 | AJ41: =IF(Data_Summary!Y42<>"Coverage","",IF(Data_Summary!AA42="","",IF(COUNTIFS(Data_Summary!$Y$2:$Y42,"Coverage",Data_Summary!$AA$2:$AA42,Data_Summary!AA42)=1,Data_Summary!AA42,""))) -> Grievance/speak-up Clarity | AK41: =IF(AJ41="","",COUNTIFS(Data_Summary!$Y$2:$Y$20001,"Coverage",Data_Summary!$AA$2:$AA$20001,AJ41)) -> 5 | AM41: =IF(Data_Insight!X41="","",IF(COUNTIF(Data_Insight!$X$2:$X41,Data_Insight!X41)=1,Data_Insight!X41,"")) -> LSA Connect | AN41: =IF(AM41="","",COUNTIF(Data_Insight!$X$2:$X$20001,AM41)) -> 3
A42: Alignment | B42: =COUNTIF(RawData[CARES Framework],A42) -> 173 | Q42: {=IFERROR(INDEX($AJ$2:$AJ$599,MATCH(1,($AK$2:$AK$599=R42)*(COUNTIF($Q$3:$Q41,$AJ$2:$AJ$599)=0)*($AJ$2:$AJ$599<>""),0)),"")} -> Buddy / Support System | R42: =IFERROR(LARGE($AK$2:$AK$599,40),"") -> 6 | S42: =IF(Q42="","",IFERROR(R42/$B$3,0)) -> 0.02 | T42: {=IF(Q42="","",IFERROR(INDEX(SummaryData[Engagement Type],MATCH(TRIM(Q42),TRIM(SummaryData[Statement]),0)),""))} -> FGD | AJ42: =IF(Data_Summary!Y43<>"Coverage","",IF(Data_Summary!AA43="","",IF(COUNTIFS(Data_Summary!$Y$2:$Y43,"Coverage",Data_Summary!$AA$2:$AA43,Data_Summary!AA43)=1,Data_Summary!AA43,""))) -> Empathy And Communication | AK42: =IF(AJ42="","",COUNTIFS(Data_Summary!$Y$2:$Y$20001,"Coverage",Data_Summary!$AA$2:$AA$20001,AJ42)) -> 4 | AM42: =IF(Data_Insight!X42="","",IF(COUNTIF(Data_Insight!$X$2:$X42,Data_Insight!X42)=1,Data_Insight!X42,"")) | AN42: =IF(AM42="","",COUNTIF(Data_Insight!$X$2:$X$20001,AM42))
A43: Career | B43: =COUNTIF(RawData[CARES Framework],A43) -> 40 | Q43: {=IFERROR(INDEX($AJ$2:$AJ$599,MATCH(1,($AK$2:$AK$599=R43)*(COUNTIF($Q$3:$Q42,$AJ$2:$AJ$599)=0)*($AJ$2:$AJ$599<>""),0)),"")} -> On Hybrid/WFO Rules And Monthly Compliance Expectations | R43: =IFERROR(LARGE($AK$2:$AK$599,41),"") -> 5 | S43: =IF(Q43="","",IFERROR(R43/$B$3,0)) -> 0.016666667 | T43: {=IF(Q43="","",IFERROR(INDEX(SummaryData[Engagement Type],MATCH(TRIM(Q43),TRIM(SummaryData[Statement]),0)),""))} -> FGD | AJ43: =IF(Data_Summary!Y44<>"Coverage","",IF(Data_Summary!AA44="","",IF(COUNTIFS(Data_Summary!$Y$2:$Y44,"Coverage",Data_Summary!$AA$2:$AA44,Data_Summary!AA44)=1,Data_Summary!AA44,""))) | AK43: =IF(AJ43="","",COUNTIFS(Data_Summary!$Y$2:$Y$20001,"Coverage",Data_Summary!$AA$2:$AA$20001,AJ43)) | AM43: =IF(Data_Insight!X43="","",IF(COUNTIF(Data_Insight!$X$2:$X43,Data_Insight!X43)=1,Data_Insight!X43,"")) | AN43: =IF(AM43="","",COUNTIF(Data_Insight!$X$2:$X$20001,AM43))
A44: Empowerment | B44: =COUNTIF(RawData[CARES Framework],A44) -> 58 | Q44: {=IFERROR(INDEX($AJ$2:$AJ$599,MATCH(1,($AK$2:$AK$599=R44)*(COUNTIF($Q$3:$Q43,$AJ$2:$AJ$599)=0)*($AJ$2:$AJ$599<>""),0)),"")} -> Grievance/speak-up Clarity | R44: =IFERROR(LARGE($AK$2:$AK$599,42),"") -> 5 | S44: =IF(Q44="","",IFERROR(R44/$B$3,0)) -> 0.016666667 | T44: {=IF(Q44="","",IFERROR(INDEX(SummaryData[Engagement Type],MATCH(TRIM(Q44),TRIM(SummaryData[Statement]),0)),""))} -> Large Connect | AJ44: =IF(Data_Summary!Y45<>"Coverage","",IF(Data_Summary!AA45="","",IF(COUNTIFS(Data_Summary!$Y$2:$Y45,"Coverage",Data_Summary!$AA$2:$AA45,Data_Summary!AA45)=1,Data_Summary!AA45,""))) | AK44: =IF(AJ44="","",COUNTIFS(Data_Summary!$Y$2:$Y$20001,"Coverage",Data_Summary!$AA$2:$AA$20001,AJ44)) | AM44: =IF(Data_Insight!X44="","",IF(COUNTIF(Data_Insight!$X$2:$X44,Data_Insight!X44)=1,Data_Insight!X44,"")) | AN44: =IF(AM44="","",COUNTIF(Data_Insight!$X$2:$X$20001,AM44))
A45: Recognition | B45: =COUNTIF(RawData[CARES Framework],A45) -> 14 | Q45: {=IFERROR(INDEX($AJ$2:$AJ$599,MATCH(1,($AK$2:$AK$599=R45)*(COUNTIF($Q$3:$Q44,$AJ$2:$AJ$599)=0)*($AJ$2:$AJ$599<>""),0)),"")} -> Career Support & Sponsorship | R45: =IFERROR(LARGE($AK$2:$AK$599,43),"") -> 5 | S45: =IF(Q45="","",IFERROR(R45/$B$3,0)) -> 0.016666667 | T45: {=IF(Q45="","",IFERROR(INDEX(SummaryData[Engagement Type],MATCH(TRIM(Q45),TRIM(SummaryData[Statement]),0)),""))} -> FGD | AJ45: =IF(Data_Summary!Y46<>"Coverage","",IF(Data_Summary!AA46="","",IF(COUNTIFS(Data_Summary!$Y$2:$Y46,"Coverage",Data_Summary!$AA$2:$AA46,Data_Summary!AA46)=1,Data_Summary!AA46,""))) | AK45: =IF(AJ45="","",COUNTIFS(Data_Summary!$Y$2:$Y$20001,"Coverage",Data_Summary!$AA$2:$AA$20001,AJ45)) | AM45: =IF(Data_Insight!X45="","",IF(COUNTIF(Data_Insight!$X$2:$X45,Data_Insight!X45)=1,Data_Insight!X45,"")) | AN45: =IF(AM45="","",COUNTIF(Data_Insight!$X$2:$X$20001,AM45))
A46: Strive | B46: =COUNTIF(RawData[CARES Framework],A46) -> 15 | Q46: {=IFERROR(INDEX($AJ$2:$AJ$599,MATCH(1,($AK$2:$AK$599=R46)*(COUNTIF($Q$3:$Q45,$AJ$2:$AJ$599)=0)*($AJ$2:$AJ$599<>""),0)),"")} -> Learning & Skill Building | R46: =IFERROR(LARGE($AK$2:$AK$599,44),"") -> 5 | S46: =IF(Q46="","",IFERROR(R46/$B$3,0)) -> 0.016666667 | T46: {=IF(Q46="","",IFERROR(INDEX(SummaryData[Engagement Type],MATCH(TRIM(Q46),TRIM(SummaryData[Statement]),0)),""))} -> Floor Connect | AJ46: =IF(Data_Summary!Y47<>"Coverage","",IF(Data_Summary!AA47="","",IF(COUNTIFS(Data_Summary!$Y$2:$Y47,"Coverage",Data_Summary!$AA$2:$AA47,Data_Summary!AA47)=1,Data_Summary!AA47,""))) | AK46: =IF(AJ46="","",COUNTIFS(Data_Summary!$Y$2:$Y$20001,"Coverage",Data_Summary!$AA$2:$AA$20001,AJ46)) | AM46: =IF(Data_Insight!X46="","",IF(COUNTIF(Data_Insight!$X$2:$X46,Data_Insight!X46)=1,Data_Insight!X46,"")) | AN46: =IF(AM46="","",COUNTIF(Data_Insight!$X$2:$X$20001,AM46))
Q47: {=IFERROR(INDEX($AJ$2:$AJ$599,MATCH(1,($AK$2:$AK$599=R47)*(COUNTIF($Q$3:$Q46,$AJ$2:$AJ$599)=0)*($AJ$2:$AJ$599<>""),0)),"")} -> Timesheet Submission/approval Process Inconsistencies Create | R47: =IFERROR(LARGE($AK$2:$AK$599,45),"") -> 5 | S47: =IF(Q47="","",IFERROR(R47/$B$3,0)) -> 0.016666667 | T47: {=IF(Q47="","",IFERROR(INDEX(SummaryData[Engagement Type],MATCH(TRIM(Q47),TRIM(SummaryData[Statement]),0)),""))} -> FGD | AJ47: =IF(Data_Summary!Y48<>"Coverage","",IF(Data_Summary!AA48="","",IF(COUNTIFS(Data_Summary!$Y$2:$Y48,"Coverage",Data_Summary!$AA$2:$AA48,Data_Summary!AA48)=1,Data_Summary!AA48,""))) -> Career Support & Sponsorship | AK47: =IF(AJ47="","",COUNTIFS(Data_Summary!$Y$2:$Y$20001,"Coverage",Data_Summary!$AA$2:$AA$20001,AJ47)) -> 5 | AM47: =IF(Data_Insight!X47="","",IF(COUNTIF(Data_Insight!$X$2:$X47,Data_Insight!X47)=1,Data_Insight!X47,"")) | AN47: =IF(AM47="","",COUNTIF(Data_Insight!$X$2:$X$20001,AM47))
A48: ENGAGEMENT MODE | Q48: {=IFERROR(INDEX($AJ$2:$AJ$599,MATCH(1,($AK$2:$AK$599=R48)*(COUNTIF($Q$3:$Q47,$AJ$2:$AJ$599)=0)*($AJ$2:$AJ$599<>""),0)),"")} -> Recognition & Visibility of Growth | R48: =IFERROR(LARGE($AK$2:$AK$599,46),"") -> 5 | S48: =IF(Q48="","",IFERROR(R48/$B$3,0)) -> 0.016666667 | T48: {=IF(Q48="","",IFERROR(INDEX(SummaryData[Engagement Type],MATCH(TRIM(Q48),TRIM(SummaryData[Statement]),0)),""))} -> Large Connect | AJ48: =IF(Data_Summary!Y49<>"Coverage","",IF(Data_Summary!AA49="","",IF(COUNTIFS(Data_Summary!$Y$2:$Y49,"Coverage",Data_Summary!$AA$2:$AA49,Data_Summary!AA49)=1,Data_Summary!AA49,""))) -> Work-Life Balance & Flexibility | AK48: =IF(AJ48="","",COUNTIFS(Data_Summary!$Y$2:$Y$20001,"Coverage",Data_Summary!$AA$2:$AA$20001,AJ48)) -> 7 | AM48: =IF(Data_Insight!X48="","",IF(COUNTIF(Data_Insight!$X$2:$X48,Data_Insight!X48)=1,Data_Insight!X48,"")) | AN48: =IF(AM48="","",COUNTIF(Data_Insight!$X$2:$X$20001,AM48))
A49: Mode | B49: Count | C49: Raw | Q49: {=IFERROR(INDEX($AJ$2:$AJ$599,MATCH(1,($AK$2:$AK$599=R49)*(COUNTIF($Q$3:$Q48,$AJ$2:$AJ$599)=0)*($AJ$2:$AJ$599<>""),0)),"")} -> Communication & Transparency | R49: =IFERROR(LARGE($AK$2:$AK$599,47),"") -> 5 | S49: =IF(Q49="","",IFERROR(R49/$B$3,0)) -> 0.016666667 | T49: {=IF(Q49="","",IFERROR(INDEX(SummaryData[Engagement Type],MATCH(TRIM(Q49),TRIM(SummaryData[Statement]),0)),""))} -> 1:1 | AJ49: =IF(Data_Summary!Y50<>"Coverage","",IF(Data_Summary!AA50="","",IF(COUNTIFS(Data_Summary!$Y$2:$Y50,"Coverage",Data_Summary!$AA$2:$AA50,Data_Summary!AA50)=1,Data_Summary!AA50,""))) | AK49: =IF(AJ49="","",COUNTIFS(Data_Summary!$Y$2:$Y$20001,"Coverage",Data_Summary!$AA$2:$AA$20001,AJ49)) | AM49: =IF(Data_Insight!X49="","",IF(COUNTIF(Data_Insight!$X$2:$X49,Data_Insight!X49)=1,Data_Insight!X49,"")) | AN49: =IF(AM49="","",COUNTIF(Data_Insight!$X$2:$X$20001,AM49))
A50: Virtual | B50: =COUNTIF(RawData[Engagement Mode],C50) -> 206 | C50: Virtual | Q50: {=IFERROR(INDEX($AJ$2:$AJ$599,MATCH(1,($AK$2:$AK$599=R50)*(COUNTIF($Q$3:$Q49,$AJ$2:$AJ$599)=0)*($AJ$2:$AJ$599<>""),0)),"")} -> Strategic Connect | R50: =IFERROR(LARGE($AK$2:$AK$599,48),"") -> 5 | S50: =IF(Q50="","",IFERROR(R50/$B$3,0)) -> 0.016666667 | T50: {=IF(Q50="","",IFERROR(INDEX(SummaryData[Engagement Type],MATCH(TRIM(Q50),TRIM(SummaryData[Statement]),0)),""))} -> Large Connect | AJ50: =IF(Data_Summary!Y51<>"Coverage","",IF(Data_Summary!AA51="","",IF(COUNTIFS(Data_Summary!$Y$2:$Y51,"Coverage",Data_Summary!$AA$2:$AA51,Data_Summary!AA51)=1,Data_Summary!AA51,""))) | AK50: =IF(AJ50="","",COUNTIFS(Data_Summary!$Y$2:$Y$20001,"Coverage",Data_Summary!$AA$2:$AA$20001,AJ50)) | AM50: =IF(Data_Insight!X50="","",IF(COUNTIF(Data_Insight!$X$2:$X50,Data_Insight!X50)=1,Data_Insight!X50,"")) | AN50: =IF(AM50="","",COUNTIF(Data_Insight!$X$2:$X$20001,AM50))
A51: In-person (Tech/Office) | B51: =COUNTIF(RawData[Engagement Mode],C51) -> 67 | C51: In-person-Tech M | Q51: {=IFERROR(INDEX($AJ$2:$AJ$599,MATCH(1,($AK$2:$AK$599=R51)*(COUNTIF($Q$3:$Q50,$AJ$2:$AJ$599)=0)*($AJ$2:$AJ$599<>""),0)),"")} -> Feedback Mechanism | R51: =IFERROR(LARGE($AK$2:$AK$599,49),"") -> 5 | S51: =IF(Q51="","",IFERROR(R51/$B$3,0)) -> 0.016666667 | T51: {=IF(Q51="","",IFERROR(INDEX(SummaryData[Engagement Type],MATCH(TRIM(Q51),TRIM(SummaryData[Statement]),0)),""))} -> Large Connect | AJ51: =IF(Data_Summary!Y52<>"Coverage","",IF(Data_Summary!AA52="","",IF(COUNTIFS(Data_Summary!$Y$2:$Y52,"Coverage",Data_Summary!$AA$2:$AA52,Data_Summary!AA52)=1,Data_Summary!AA52,""))) | AK51: =IF(AJ51="","",COUNTIFS(Data_Summary!$Y$2:$Y$20001,"Coverage",Data_Summary!$AA$2:$AA$20001,AJ51)) | AM51: =IF(Data_Insight!X51="","",IF(COUNTIF(Data_Insight!$X$2:$X51,Data_Insight!X51)=1,Data_Insight!X51,"")) -> NA | AN51: =IF(AM51="","",COUNTIF(Data_Insight!$X$2:$X$20001,AM51)) -> 3
A52: Virtual + In-person | B52: =COUNTIF(RawData[Engagement Mode],C52) -> 20 | C52: Mix (Virtual & In-person) | Q52: {=IFERROR(INDEX($AJ$2:$AJ$599,MATCH(1,($AK$2:$AK$599=R52)*(COUNTIF($Q$3:$Q51,$AJ$2:$AJ$599)=0)*($AJ$2:$AJ$599<>""),0)),"")} -> Work-Life & Sustainability Signals | R52: =IFERROR(LARGE($AK$2:$AK$599,50),"") -> 5 | S52: =IF(Q52="","",IFERROR(R52/$B$3,0)) -> 0.016666667 | T52: {=IF(Q52="","",IFERROR(INDEX(SummaryData[Engagement Type],MATCH(TRIM(Q52),TRIM(SummaryData[Statement]),0)),""))} -> Large Connect | AJ52: =IF(Data_Summary!Y53<>"Coverage","",IF(Data_Summary!AA53="","",IF(COUNTIFS(Data_Summary!$Y$2:$Y53,"Coverage",Data_Summary!$AA$2:$AA53,Data_Summary!AA53)=1,Data_Summary!AA53,""))) | AK52: =IF(AJ52="","",COUNTIFS(Data_Summary!$Y$2:$Y$20001,"Coverage",Data_Summary!$AA$2:$AA$20001,AJ52)) | AM52: =IF(Data_Insight!X52="","",IF(COUNTIF(Data_Insight!$X$2:$X52,Data_Insight!X52)=1,Data_Insight!X52,"")) | AN52: =IF(AM52="","",COUNTIF(Data_Insight!$X$2:$X$20001,AM52))
A53: In-person (Client) | B53: =COUNTIF(RawData[Engagement Mode],C53) -> 7 | C53: In-person-Client Location | Q53: {=IFERROR(INDEX($AJ$2:$AJ$599,MATCH(1,($AK$2:$AK$599=R53)*(COUNTIF($Q$3:$Q52,$AJ$2:$AJ$599)=0)*($AJ$2:$AJ$599<>""),0)),"")} -> Initial Organization Understanding | R53: =IFERROR(LARGE($AK$2:$AK$599,51),"") -> 5 | S53: =IF(Q53="","",IFERROR(R53/$B$3,0)) -> 0.016666667 | T53: {=IF(Q53="","",IFERROR(INDEX(SummaryData[Engagement Type],MATCH(TRIM(Q53),TRIM(SummaryData[Statement]),0)),""))} -> Location-Mixed | AJ53: =IF(Data_Summary!Y54<>"Coverage","",IF(Data_Summary!AA54="","",IF(COUNTIFS(Data_Summary!$Y$2:$Y54,"Coverage",Data_Summary!$AA$2:$AA54,Data_Summary!AA54)=1,Data_Summary!AA54,""))) -> Feedback on recent processes | AK53: =IF(AJ53="","",COUNTIFS(Data_Summary!$Y$2:$Y$20001,"Coverage",Data_Summary!$AA$2:$AA$20001,AJ53)) -> 24 | AM53: =IF(Data_Insight!X53="","",IF(COUNTIF(Data_Insight!$X$2:$X53,Data_Insight!X53)=1,Data_Insight!X53,"")) | AN53: =IF(AM53="","",COUNTIF(Data_Insight!$X$2:$X$20001,AM53))
Q54: {=IFERROR(INDEX($AJ$2:$AJ$599,MATCH(1,($AK$2:$AK$599=R54)*(COUNTIF($Q$3:$Q53,$AJ$2:$AJ$599)=0)*($AJ$2:$AJ$599<>""),0)),"")} -> HR Process Clarity | R54: =IFERROR(LARGE($AK$2:$AK$599,52),"") -> 5 | S54: =IF(Q54="","",IFERROR(R54/$B$3,0)) -> 0.016666667 | T54: {=IF(Q54="","",IFERROR(INDEX(SummaryData[Engagement Type],MATCH(TRIM(Q54),TRIM(SummaryData[Statement]),0)),""))} -> FGD | AJ54: =IF(Data_Summary!Y55<>"Coverage","",IF(Data_Summary!AA55="","",IF(COUNTIFS(Data_Summary!$Y$2:$Y55,"Coverage",Data_Summary!$AA$2:$AA55,Data_Summary!AA55)=1,Data_Summary!AA55,""))) | AK54: =IF(AJ54="","",COUNTIFS(Data_Summary!$Y$2:$Y$20001,"Coverage",Data_Summary!$AA$2:$AA$20001,AJ54)) | AM54: =IF(Data_Insight!X54="","",IF(COUNTIF(Data_Insight!$X$2:$X54,Data_Insight!X54)=1,Data_Insight!X54,"")) | AN54: =IF(AM54="","",COUNTIF(Data_Insight!$X$2:$X$20001,AM54))
Q55: {=IFERROR(INDEX($AJ$2:$AJ$599,MATCH(1,($AK$2:$AK$599=R55)*(COUNTIF($Q$3:$Q54,$AJ$2:$AJ$599)=0)*($AJ$2:$AJ$599<>""),0)),"")} -> AI/future Readiness Messaging Is High-level | R55: =IFERROR(LARGE($AK$2:$AK$599,53),"") -> 4 | S55: =IF(Q55="","",IFERROR(R55/$B$3,0)) -> 0.013333333 | T55: {=IF(Q55="","",IFERROR(INDEX(SummaryData[Engagement Type],MATCH(TRIM(Q55),TRIM(SummaryData[Statement]),0)),""))} -> Large Connect | AJ55: =IF(Data_Summary!Y56<>"Coverage","",IF(Data_Summary!AA56="","",IF(COUNTIFS(Data_Summary!$Y$2:$Y56,"Coverage",Data_Summary!$AA$2:$AA56,Data_Summary!AA56)=1,Data_Summary!AA56,""))) | AK55: =IF(AJ55="","",COUNTIFS(Data_Summary!$Y$2:$Y$20001,"Coverage",Data_Summary!$AA$2:$AA$20001,AJ55)) | AM55: =IF(Data_Insight!X55="","",IF(COUNTIF(Data_Insight!$X$2:$X55,Data_Insight!X55)=1,Data_Insight!X55,"")) | AN55: =IF(AM55="","",COUNTIF(Data_Insight!$X$2:$X$20001,AM55))
Q56: {=IFERROR(INDEX($AJ$2:$AJ$599,MATCH(1,($AK$2:$AK$599=R56)*(COUNTIF($Q$3:$Q55,$AJ$2:$AJ$599)=0)*($AJ$2:$AJ$599<>""),0)),"")} -> Empathy And Communication | R56: =IFERROR(LARGE($AK$2:$AK$599,54),"") -> 4 | S56: =IF(Q56="","",IFERROR(R56/$B$3,0)) -> 0.013333333 | T56: {=IF(Q56="","",IFERROR(INDEX(SummaryData[Engagement Type],MATCH(TRIM(Q56),TRIM(SummaryData[Statement]),0)),""))} -> Large Connect | AJ56: =IF(Data_Summary!Y57<>"Coverage","",IF(Data_Summary!AA57="","",IF(COUNTIFS(Data_Summary!$Y$2:$Y57,"Coverage",Data_Summary!$AA$2:$AA57,Data_Summary!AA57)=1,Data_Summary!AA57,""))) | AK56: =IF(AJ56="","",COUNTIFS(Data_Summary!$Y$2:$Y$20001,"Coverage",Data_Summary!$AA$2:$AA$20001,AJ56)) | AM56: =IF(Data_Insight!X56="","",IF(COUNTIF(Data_Insight!$X$2:$X56,Data_Insight!X56)=1,Data_Insight!X56,"")) | AN56: =IF(AM56="","",COUNTIF(Data_Insight!$X$2:$X$20001,AM56))
E57: =IFERROR(IF(D170=0,0,(D170-E170)/D170),0) -> 0 | Q57: {=IFERROR(INDEX($AJ$2:$AJ$599,MATCH(1,($AK$2:$AK$599=R57)*(COUNTIF($Q$3:$Q56,$AJ$2:$AJ$599)=0)*($AJ$2:$AJ$599<>""),0)),"")} -> Inclusive Team Practices | R57: =IFERROR(LARGE($AK$2:$AK$599,55),"") -> 4 | S57: =IF(Q57="","",IFERROR(R57/$B$3,0)) -> 0.013333333 | T57: {=IF(Q57="","",IFERROR(INDEX(SummaryData[Engagement Type],MATCH(TRIM(Q57),TRIM(SummaryData[Statement]),0)),""))} -> FGD | AJ57: =IF(Data_Summary!Y58<>"Coverage","",IF(Data_Summary!AA58="","",IF(COUNTIFS(Data_Summary!$Y$2:$Y58,"Coverage",Data_Summary!$AA$2:$AA58,Data_Summary!AA58)=1,Data_Summary!AA58,""))) | AK57: =IF(AJ57="","",COUNTIFS(Data_Summary!$Y$2:$Y$20001,"Coverage",Data_Summary!$AA$2:$AA$20001,AJ57)) | AM57: =IF(Data_Insight!X57="","",IF(COUNTIF(Data_Insight!$X$2:$X57,Data_Insight!X57)=1,Data_Insight!X57,"")) | AN57: =IF(AM57="","",COUNTIF(Data_Insight!$X$2:$X$20001,AM57))
Q58: {=IFERROR(INDEX($AJ$2:$AJ$599,MATCH(1,($AK$2:$AK$599=R58)*(COUNTIF($Q$3:$Q57,$AJ$2:$AJ$599)=0)*($AJ$2:$AJ$599<>""),0)),"")} -> Career Clarity & Growth Continuity | R58: =IFERROR(LARGE($AK$2:$AK$599,56),"") -> 4 | S58: =IF(Q58="","",IFERROR(R58/$B$3,0)) -> 0.013333333 | T58: {=IF(Q58="","",IFERROR(INDEX(SummaryData[Engagement Type],MATCH(TRIM(Q58),TRIM(SummaryData[Statement]),0)),""))} -> Leadership Connect | AJ58: =IF(Data_Summary!Y59<>"Coverage","",IF(Data_Summary!AA59="","",IF(COUNTIFS(Data_Summary!$Y$2:$Y59,"Coverage",Data_Summary!$AA$2:$AA59,Data_Summary!AA59)=1,Data_Summary!AA59,""))) -> AI Session | AK58: =IF(AJ58="","",COUNTIFS(Data_Summary!$Y$2:$Y$20001,"Coverage",Data_Summary!$AA$2:$AA$20001,AJ58)) -> 3 | AM58: =IF(Data_Insight!X58="","",IF(COUNTIF(Data_Insight!$X$2:$X58,Data_Insight!X58)=1,Data_Insight!X58,"")) | AN58: =IF(AM58="","",COUNTIF(Data_Insight!$X$2:$X$20001,AM58))
Q59: {=IFERROR(INDEX($AJ$2:$AJ$599,MATCH(1,($AK$2:$AK$599=R59)*(COUNTIF($Q$3:$Q58,$AJ$2:$AJ$599)=0)*($AJ$2:$AJ$599<>""),0)),"")} -> Allocation & Deployment Transparency | R59: =IFERROR(LARGE($AK$2:$AK$599,57),"") -> 4 | S59: =IF(Q59="","",IFERROR(R59/$B$3,0)) -> 0.013333333 | T59: {=IF(Q59="","",IFERROR(INDEX(SummaryData[Engagement Type],MATCH(TRIM(Q59),TRIM(SummaryData[Statement]),0)),""))} -> Leadership Connect | AJ59: =IF(Data_Summary!Y60<>"Coverage","",IF(Data_Summary!AA60="","",IF(COUNTIFS(Data_Summary!$Y$2:$Y60,"Coverage",Data_Summary!$AA$2:$AA60,Data_Summary!AA60)=1,Data_Summary!AA60,""))) -> Review Cadence | AK59: =IF(AJ59="","",COUNTIFS(Data_Summary!$Y$2:$Y$20001,"Coverage",Data_Summary!$AA$2:$AA$20001,AJ59)) -> 1 | AM59: =IF(Data_Insight!X59="","",IF(COUNTIF(Data_Insight!$X$2:$X59,Data_Insight!X59)=1,Data_Insight!X59,"")) | AN59: =IF(AM59="","",COUNTIF(Data_Insight!$X$2:$X$20001,AM59))
Q60: {=IFERROR(INDEX($AJ$2:$AJ$599,MATCH(1,($AK$2:$AK$599=R60)*(COUNTIF($Q$3:$Q59,$AJ$2:$AJ$599)=0)*($AJ$2:$AJ$599<>""),0)),"")} -> Timely Policy/process Updates | R60: =IFERROR(LARGE($AK$2:$AK$599,58),"") -> 4 | S60: =IF(Q60="","",IFERROR(R60/$B$3,0)) -> 0.013333333 | T60: {=IF(Q60="","",IFERROR(INDEX(SummaryData[Engagement Type],MATCH(TRIM(Q60),TRIM(SummaryData[Statement]),0)),""))} -> 1:1 | AJ60: =IF(Data_Summary!Y61<>"Coverage","",IF(Data_Summary!AA61="","",IF(COUNTIFS(Data_Summary!$Y$2:$Y61,"Coverage",Data_Summary!$AA$2:$AA61,Data_Summary!AA61)=1,Data_Summary!AA61,""))) | AK60: =IF(AJ60="","",COUNTIFS(Data_Summary!$Y$2:$Y$20001,"Coverage",Data_Summary!$AA$2:$AA$20001,AJ60)) | AM60: =IF(Data_Insight!X60="","",IF(COUNTIF(Data_Insight!$X$2:$X60,Data_Insight!X60)=1,Data_Insight!X60,"")) | AN60: =IF(AM60="","",COUNTIF(Data_Insight!$X$2:$X$20001,AM60))
Q61: {=IFERROR(INDEX($AJ$2:$AJ$599,MATCH(1,($AK$2:$AK$599=R61)*(COUNTIF($Q$3:$Q60,$AJ$2:$AJ$599)=0)*($AJ$2:$AJ$599<>""),0)),"")} -> Learning/cert Support Requests | R61: =IFERROR(LARGE($AK$2:$AK$599,59),"") -> 4 | S61: =IF(Q61="","",IFERROR(R61/$B$3,0)) -> 0.013333333 | T61: {=IF(Q61="","",IFERROR(INDEX(SummaryData[Engagement Type],MATCH(TRIM(Q61),TRIM(SummaryData[Statement]),0)),""))} -> Location-Offshore | AJ61: =IF(Data_Summary!Y62<>"Coverage","",IF(Data_Summary!AA62="","",IF(COUNTIFS(Data_Summary!$Y$2:$Y62,"Coverage",Data_Summary!$AA$2:$AA62,Data_Summary!AA62)=1,Data_Summary!AA62,""))) | AK61: =IF(AJ61="","",COUNTIFS(Data_Summary!$Y$2:$Y$20001,"Coverage",Data_Summary!$AA$2:$AA$20001,AJ61)) | AM61: =IF(Data_Insight!X61="","",IF(COUNTIF(Data_Insight!$X$2:$X61,Data_Insight!X61)=1,Data_Insight!X61,"")) | AN61: =IF(AM61="","",COUNTIF(Data_Insight!$X$2:$X$20001,AM61))
Q62: {=IFERROR(INDEX($AJ$2:$AJ$599,MATCH(1,($AK$2:$AK$599=R62)*(COUNTIF($Q$3:$Q61,$AJ$2:$AJ$599)=0)*($AJ$2:$AJ$599<>""),0)),"")} -> AI Workshop By Natesh | R62: =IFERROR(LARGE($AK$2:$AK$599,60),"") -> 4 | S62: =IF(Q62="","",IFERROR(R62/$B$3,0)) -> 0.013333333 | T62: {=IF(Q62="","",IFERROR(INDEX(SummaryData[Engagement Type],MATCH(TRIM(Q62),TRIM(SummaryData[Statement]),0)),""))} -> Location-Mixed | AJ62: =IF(Data_Summary!Y63<>"Coverage","",IF(Data_Summary!AA63="","",IF(COUNTIFS(Data_Summary!$Y$2:$Y63,"Coverage",Data_Summary!$AA$2:$AA63,Data_Summary!AA63)=1,Data_Summary!AA63,""))) | AK62: =IF(AJ62="","",COUNTIFS(Data_Summary!$Y$2:$Y$20001,"Coverage",Data_Summary!$AA$2:$AA$20001,AJ62)) | AM62: =IF(Data_Insight!X62="","",IF(COUNTIF(Data_Insight!$X$2:$X62,Data_Insight!X62)=1,Data_Insight!X62,"")) | AN62: =IF(AM62="","",COUNTIF(Data_Insight!$X$2:$X$20001,AM62))
AJ63: =IF(Data_Summary!Y64<>"Coverage","",IF(Data_Summary!AA64="","",IF(COUNTIFS(Data_Summary!$Y$2:$Y64,"Coverage",Data_Summary!$AA$2:$AA64,Data_Summary!AA64)=1,Data_Summary!AA64,""))) -> Role Expectation Clarity | AK63: =IF(AJ63="","",COUNTIFS(Data_Summary!$Y$2:$Y$20001,"Coverage",Data_Summary!$AA$2:$AA$20001,AJ63)) -> 7 | AM63: =IF(Data_Insight!X63="","",IF(COUNTIF(Data_Insight!$X$2:$X63,Data_Insight!X63)=1,Data_Insight!X63,"")) | AN63: =IF(AM63="","",COUNTIF(Data_Insight!$X$2:$X$20001,AM63))
AJ64: =IF(Data_Summary!Y65<>"Coverage","",IF(Data_Summary!AA65="","",IF(COUNTIFS(Data_Summary!$Y$2:$Y65,"Coverage",Data_Summary!$AA$2:$AA65,Data_Summary!AA65)=1,Data_Summary!AA65,""))) -> Initial Engagement Level | AK64: =IF(AJ64="","",COUNTIFS(Data_Summary!$Y$2:$Y$20001,"Coverage",Data_Summary!$AA$2:$AA$20001,AJ64)) -> 7 | AM64: =IF(Data_Insight!X64="","",IF(COUNTIF(Data_Insight!$X$2:$X64,Data_Insight!X64)=1,Data_Insight!X64,"")) | AN64: =IF(AM64="","",COUNTIF(Data_Insight!$X$2:$X$20001,AM64))
AJ65: =IF(Data_Summary!Y66<>"Coverage","",IF(Data_Summary!AA66="","",IF(COUNTIFS(Data_Summary!$Y$2:$Y66,"Coverage",Data_Summary!$AA$2:$AA66,Data_Summary!AA66)=1,Data_Summary!AA66,""))) | AK65: =IF(AJ65="","",COUNTIFS(Data_Summary!$Y$2:$Y$20001,"Coverage",Data_Summary!$AA$2:$AA$20001,AJ65)) | AM65: =IF(Data_Insight!X65="","",IF(COUNTIF(Data_Insight!$X$2:$X65,Data_Insight!X65)=1,Data_Insight!X65,"")) | AN65: =IF(AM65="","",COUNTIF(Data_Insight!$X$2:$X$20001,AM65))
AJ66: =IF(Data_Summary!Y67<>"Coverage","",IF(Data_Summary!AA67="","",IF(COUNTIFS(Data_Summary!$Y$2:$Y67,"Coverage",Data_Summary!$AA$2:$AA67,Data_Summary!AA67)=1,Data_Summary!AA67,""))) | AK66: =IF(AJ66="","",COUNTIFS(Data_Summary!$Y$2:$Y$20001,"Coverage",Data_Summary!$AA$2:$AA$20001,AJ66)) | AM66: =IF(Data_Insight!X66="","",IF(COUNTIF(Data_Insight!$X$2:$X66,Data_Insight!X66)=1,Data_Insight!X66,"")) | AN66: =IF(AM66="","",COUNTIF(Data_Insight!$X$2:$X$20001,AM66))
AJ67: =IF(Data_Summary!Y68<>"Coverage","",IF(Data_Summary!AA68="","",IF(COUNTIFS(Data_Summary!$Y$2:$Y68,"Coverage",Data_Summary!$AA$2:$AA68,Data_Summary!AA68)=1,Data_Summary!AA68,""))) | AK67: =IF(AJ67="","",COUNTIFS(Data_Summary!$Y$2:$Y$20001,"Coverage",Data_Summary!$AA$2:$AA$20001,AJ67)) | AM67: =IF(Data_Insight!X67="","",IF(COUNTIF(Data_Insight!$X$2:$X67,Data_Insight!X67)=1,Data_Insight!X67,"")) | AN67: =IF(AM67="","",COUNTIF(Data_Insight!$X$2:$X$20001,AM67))
AJ68: =IF(Data_Summary!Y69<>"Coverage","",IF(Data_Summary!AA69="","",IF(COUNTIFS(Data_Summary!$Y$2:$Y69,"Coverage",Data_Summary!$AA$2:$AA69,Data_Summary!AA69)=1,Data_Summary!AA69,""))) | AK68: =IF(AJ68="","",COUNTIFS(Data_Summary!$Y$2:$Y$20001,"Coverage",Data_Summary!$AA$2:$AA$20001,AJ68)) | AM68: =IF(Data_Insight!X68="","",IF(COUNTIF(Data_Insight!$X$2:$X68,Data_Insight!X68)=1,Data_Insight!X68,"")) -> Wellness Session | AN68: =IF(AM68="","",COUNTIF(Data_Insight!$X$2:$X$20001,AM68)) -> 3
AJ69: =IF(Data_Summary!Y70<>"Coverage","",IF(Data_Summary!AA70="","",IF(COUNTIFS(Data_Summary!$Y$2:$Y70,"Coverage",Data_Summary!$AA$2:$AA70,Data_Summary!AA70)=1,Data_Summary!AA70,""))) -> Learning & Skill Building | AK69: =IF(AJ69="","",COUNTIFS(Data_Summary!$Y$2:$Y$20001,"Coverage",Data_Summary!$AA$2:$AA$20001,AJ69)) -> 5 | AM69: =IF(Data_Insight!X69="","",IF(COUNTIF(Data_Insight!$X$2:$X69,Data_Insight!X69)=1,Data_Insight!X69,"")) | AN69: =IF(AM69="","",COUNTIF(Data_Insight!$X$2:$X$20001,AM69))
AJ70: =IF(Data_Summary!Y71<>"Coverage","",IF(Data_Summary!AA71="","",IF(COUNTIFS(Data_Summary!$Y$2:$Y71,"Coverage",Data_Summary!$AA$2:$AA71,Data_Summary!AA71)=1,Data_Summary!AA71,""))) | AK70: =IF(AJ70="","",COUNTIFS(Data_Summary!$Y$2:$Y$20001,"Coverage",Data_Summary!$AA$2:$AA$20001,AJ70)) | AM70: =IF(Data_Insight!X70="","",IF(COUNTIF(Data_Insight!$X$2:$X70,Data_Insight!X70)=1,Data_Insight!X70,"")) | AN70: =IF(AM70="","",COUNTIF(Data_Insight!$X$2:$X$20001,AM70))
AJ71: =IF(Data_Summary!Y72<>"Coverage","",IF(Data_Summary!AA72="","",IF(COUNTIFS(Data_Summary!$Y$2:$Y72,"Coverage",Data_Summary!$AA$2:$AA72,Data_Summary!AA72)=1,Data_Summary!AA72,""))) -> Inclusive Team Practices | AK71: =IF(AJ71="","",COUNTIFS(Data_Summary!$Y$2:$Y$20001,"Coverage",Data_Summary!$AA$2:$AA$20001,AJ71)) -> 4 | AM71: =IF(Data_Insight!X71="","",IF(COUNTIF(Data_Insight!$X$2:$X71,Data_Insight!X71)=1,Data_Insight!X71,"")) | AN71: =IF(AM71="","",COUNTIF(Data_Insight!$X$2:$X$20001,AM71))
AJ72: =IF(Data_Summary!Y73<>"Coverage","",IF(Data_Summary!AA73="","",IF(COUNTIFS(Data_Summary!$Y$2:$Y73,"Coverage",Data_Summary!$AA$2:$AA73,Data_Summary!AA73)=1,Data_Summary!AA73,""))) | AK72: =IF(AJ72="","",COUNTIFS(Data_Summary!$Y$2:$Y$20001,"Coverage",Data_Summary!$AA$2:$AA$20001,AJ72)) | AM72: =IF(Data_Insight!X72="","",IF(COUNTIF(Data_Insight!$X$2:$X72,Data_Insight!X72)=1,Data_Insight!X72,"")) -> New Joiner Connect (7 Days) | AN72: =IF(AM72="","",COUNTIF(Data_Insight!$X$2:$X$20001,AM72)) -> 16
AJ73: =IF(Data_Summary!Y74<>"Coverage","",IF(Data_Summary!AA74="","",IF(COUNTIFS(Data_Summary!$Y$2:$Y74,"Coverage",Data_Summary!$AA$2:$AA74,Data_Summary!AA74)=1,Data_Summary!AA74,""))) | AK73: =IF(AJ73="","",COUNTIFS(Data_Summary!$Y$2:$Y$20001,"Coverage",Data_Summary!$AA$2:$AA$20001,AJ73)) | AM73: =IF(Data_Insight!X73="","",IF(COUNTIF(Data_Insight!$X$2:$X73,Data_Insight!X73)=1,Data_Insight!X73,"")) | AN73: =IF(AM73="","",COUNTIF(Data_Insight!$X$2:$X$20001,AM73))
AJ74: =IF(Data_Summary!Y75<>"Coverage","",IF(Data_Summary!AA75="","",IF(COUNTIFS(Data_Summary!$Y$2:$Y75,"Coverage",Data_Summary!$AA$2:$AA75,Data_Summary!AA75)=1,Data_Summary!AA75,""))) | AK74: =IF(AJ74="","",COUNTIFS(Data_Summary!$Y$2:$Y$20001,"Coverage",Data_Summary!$AA$2:$AA$20001,AJ74)) | AM74: =IF(Data_Insight!X74="","",IF(COUNTIF(Data_Insight!$X$2:$X74,Data_Insight!X74)=1,Data_Insight!X74,"")) | AN74: =IF(AM74="","",COUNTIF(Data_Insight!$X$2:$X$20001,AM74))
... AJ199: =IF(Data_Summary!Y200<>"Coverage","",IF(Data_Summary!AA200="","",IF(COUNTIFS(Data_Summary!$Y$2:$Y200,"Coverage",Data_Summary!$AA$2:$AA200,Data_Summary!AA200)=1,Data_Summary!AA200,""))) | AK199: =IF(AJ199="","",COUNTIFS(Data_Summary!$Y$2:$Y$20001,"Coverage",Data_Summary!$AA$2:$AA$20001,AJ199)) | AM199: =IF(Data_Insight!X199="","",IF(COUNTIF(Data_Insight!$X$2:$X199,Data_Insight!X199)=1,Data_Insight!X199,"")) | AN199: =IF(AM199="","",COUNTIF(Data_Insight!$X$2:$X$20001,AM199))
AJ200: =IF(Data_Summary!Y201<>"Coverage","",IF(Data_Summary!AA201="","",IF(COUNTIFS(Data_Summary!$Y$2:$Y201,"Coverage",Data_Summary!$AA$2:$AA201,Data_Summary!AA201)=1,Data_Summary!AA201,""))) | AK200: =IF(AJ200="","",COUNTIFS(Data_Summary!$Y$2:$Y$20001,"Coverage",Data_Summary!$AA$2:$AA$20001,AJ200))
AJ201: =IF(Data_Summary!Y202<>"Coverage","",IF(Data_Summary!AA202="","",IF(COUNTIFS(Data_Summary!$Y$2:$Y202,"Coverage",Data_Summary!$AA$2:$AA202,Data_Summary!AA202)=1,Data_Summary!AA202,""))) | AK201: =IF(AJ201="","",COUNTIFS(Data_Summary!$Y$2:$Y$20001,"Coverage",Data_Summary!$AA$2:$AA$20001,AJ201))
AJ202: =IF(Data_Summary!Y203<>"Coverage","",IF(Data_Summary!AA203="","",IF(COUNTIFS(Data_Summary!$Y$2:$Y203,"Coverage",Data_Summary!$AA$2:$AA203,Data_Summary!AA203)=1,Data_Summary!AA203,""))) | AK202: =IF(AJ202="","",COUNTIFS(Data_Summary!$Y$2:$Y$20001,"Coverage",Data_Summary!$AA$2:$AA$20001,AJ202))
AJ203: =IF(Data_Summary!Y204<>"Coverage","",IF(Data_Summary!AA204="","",IF(COUNTIFS(Data_Summary!$Y$2:$Y204,"Coverage",Data_Summary!$AA$2:$AA204,Data_Summary!AA204)=1,Data_Summary!AA204,""))) -> Recognition & Motivation | AK203: =IF(AJ203="","",COUNTIFS(Data_Summary!$Y$2:$Y$20001,"Coverage",Data_Summary!$AA$2:$AA$20001,AJ203)) -> 3
AJ204: =IF(Data_Summary!Y205<>"Coverage","",IF(Data_Summary!AA205="","",IF(COUNTIFS(Data_Summary!$Y$2:$Y205,"Coverage",Data_Summary!$AA$2:$AA205,Data_Summary!AA205)=1,Data_Summary!AA205,""))) | AK204: =IF(AJ204="","",COUNTIFS(Data_Summary!$Y$2:$Y$20001,"Coverage",Data_Summary!$AA$2:$AA$20001,AJ204))
AJ205: =IF(Data_Summary!Y206<>"Coverage","",IF(Data_Summary!AA206="","",IF(COUNTIFS(Data_Summary!$Y$2:$Y206,"Coverage",Data_Summary!$AA$2:$AA206,Data_Summary!AA206)=1,Data_Summary!AA206,""))) | AK205: =IF(AJ205="","",COUNTIFS(Data_Summary!$Y$2:$Y$20001,"Coverage",Data_Summary!$AA$2:$AA$20001,AJ205))
AJ206: =IF(Data_Summary!Y207<>"Coverage","",IF(Data_Summary!AA207="","",IF(COUNTIFS(Data_Summary!$Y$2:$Y207,"Coverage",Data_Summary!$AA$2:$AA207,Data_Summary!AA207)=1,Data_Summary!AA207,""))) | AK206: =IF(AJ206="","",COUNTIFS(Data_Summary!$Y$2:$Y$20001,"Coverage",Data_Summary!$AA$2:$AA$20001,AJ206))
AJ207: =IF(Data_Summary!Y208<>"Coverage","",IF(Data_Summary!AA208="","",IF(COUNTIFS(Data_Summary!$Y$2:$Y208,"Coverage",Data_Summary!$AA$2:$AA208,Data_Summary!AA208)=1,Data_Summary!AA208,""))) | AK207: =IF(AJ207="","",COUNTIFS(Data_Summary!$Y$2:$Y$20001,"Coverage",Data_Summary!$AA$2:$AA$20001,AJ207))
AJ208: =IF(Data_Summary!Y209<>"Coverage","",IF(Data_Summary!AA209="","",IF(COUNTIFS(Data_Summary!$Y$2:$Y209,"Coverage",Data_Summary!$AA$2:$AA209,Data_Summary!AA209)=1,Data_Summary!AA209,""))) | AK208: =IF(AJ208="","",COUNTIFS(Data_Summary!$Y$2:$Y$20001,"Coverage",Data_Summary!$AA$2:$AA$20001,AJ208))
AJ209: =IF(Data_Summary!Y210<>"Coverage","",IF(Data_Summary!AA210="","",IF(COUNTIFS(Data_Summary!$Y$2:$Y210,"Coverage",Data_Summary!$AA$2:$AA210,Data_Summary!AA210)=1,Data_Summary!AA210,""))) | AK209: =IF(AJ209="","",COUNTIFS(Data_Summary!$Y$2:$Y$20001,"Coverage",Data_Summary!$AA$2:$AA$20001,AJ209))
AJ210: =IF(Data_Summary!Y211<>"Coverage","",IF(Data_Summary!AA211="","",IF(COUNTIFS(Data_Summary!$Y$2:$Y211,"Coverage",Data_Summary!$AA$2:$AA211,Data_Summary!AA211)=1,Data_Summary!AA211,""))) | AK210: =IF(AJ210="","",COUNTIFS(Data_Summary!$Y$2:$Y$20001,"Coverage",Data_Summary!$AA$2:$AA$20001,AJ210))
AJ211: =IF(Data_Summary!Y212<>"Coverage","",IF(Data_Summary!AA212="","",IF(COUNTIFS(Data_Summary!$Y$2:$Y212,"Coverage",Data_Summary!$AA$2:$AA212,Data_Summary!AA212)=1,Data_Summary!AA212,""))) | AK211: =IF(AJ211="","",COUNTIFS(Data_Summary!$Y$2:$Y$20001,"Coverage",Data_Summary!$AA$2:$AA$20001,AJ211))
... AJ249: =IF(Data_Summary!Y250<>"Coverage","",IF(Data_Summary!AA250="","",IF(COUNTIFS(Data_Summary!$Y$2:$Y250,"Coverage",Data_Summary!$AA$2:$AA250,Data_Summary!AA250)=1,Data_Summary!AA250,""))) -> On Leave/comp-off Due To Client Calendar Mismatches | AK249: =IF(AJ249="","",COUNTIFS(Data_Summary!$Y$2:$Y$20001,"Coverage",Data_Summary!$AA$2:$AA$20001,AJ249)) -> 6
J250: {=IFERROR(SMALL(IF(((Data_Insight!$W$2:$W$5001="Open")+(Data_Insight!$W$2:$W$5001="In-progress")),(IF((Data_Insight!$V$2:$V$5001="High")*(Data_Insight!$W$2:$W$5001="Open"),1,IF((Data_Insight!$V$2:$V$5001="High")*(Data_Insight!$W$2:$W$5001="In-progress"),2,IF((Data_Insight!$V$2:$V$5001="Moderate")*(Data_Insight!$W$2:$W$5001="Open"),3,IF((Data_Insight!$V$2:$V$5001="Moderate")*(Data_Insight!$W$2:$W$5001="In-progress"),4,IF((Data_Insight!$V$2:$V$5001="Low")*(Data_Insight!$W$2:$W$5001="Open"),5,IF((Data_Insight!$V$2:$V$5001="Low")*(Data_Insight!$W$2:$W$5001="In-progress"),6,9999)))))))*100000+ROW(Data_Insight!$V$2:$V$5001)),1),"")} -> 100026 | AJ250: =IF(Data_Summary!Y251<>"Coverage","",IF(Data_Summary!AA251="","",IF(COUNTIFS(Data_Summary!$Y$2:$Y251,"Coverage",Data_Summary!$AA$2:$AA251,Data_Summary!AA251)=1,Data_Summary!AA251,""))) | AK250: =IF(AJ250="","",COUNTIFS(Data_Summary!$Y$2:$Y$20001,"Coverage",Data_Summary!$AA$2:$AA$20001,AJ250))
J251: {=IFERROR(SMALL(IF(((Data_Insight!$W$2:$W$5001="Open")+(Data_Insight!$W$2:$W$5001="In-progress")),(IF((Data_Insight!$V$2:$V$5001="High")*(Data_Insight!$W$2:$W$5001="Open"),1,IF((Data_Insight!$V$2:$V$5001="High")*(Data_Insight!$W$2:$W$5001="In-progress"),2,IF((Data_Insight!$V$2:$V$5001="Moderate")*(Data_Insight!$W$2:$W$5001="Open"),3,IF((Data_Insight!$V$2:$V$5001="Moderate")*(Data_Insight!$W$2:$W$5001="In-progress"),4,IF((Data_Insight!$V$2:$V$5001="Low")*(Data_Insight!$W$2:$W$5001="Open"),5,IF((Data_Insight!$V$2:$V$5001="Low")*(Data_Insight!$W$2:$W$5001="In-progress"),6,9999)))))))*100000+ROW(Data_Insight!$V$2:$V$5001)),2),"")} -> 100064 | AJ251: =IF(Data_Summary!Y252<>"Coverage","",IF(Data_Summary!AA252="","",IF(COUNTIFS(Data_Summary!$Y$2:$Y252,"Coverage",Data_Summary!$AA$2:$AA252,Data_Summary!AA252)=1,Data_Summary!AA252,""))) | AK251: =IF(AJ251="","",COUNTIFS(Data_Summary!$Y$2:$Y$20001,"Coverage",Data_Summary!$AA$2:$AA$20001,AJ251))
J252: {=IFERROR(SMALL(IF(((Data_Insight!$W$2:$W$5001="Open")+(Data_Insight!$W$2:$W$5001="In-progress")),(IF((Data_Insight!$V$2:$V$5001="High")*(Data_Insight!$W$2:$W$5001="Open"),1,IF((Data_Insight!$V$2:$V$5001="High")*(Data_Insight!$W$2:$W$5001="In-progress"),2,IF((Data_Insight!$V$2:$V$5001="Moderate")*(Data_Insight!$W$2:$W$5001="Open"),3,IF((Data_Insight!$V$2:$V$5001="Moderate")*(Data_Insight!$W$2:$W$5001="In-progress"),4,IF((Data_Insight!$V$2:$V$5001="Low")*(Data_Insight!$W$2:$W$5001="Open"),5,IF((Data_Insight!$V$2:$V$5001="Low")*(Data_Insight!$W$2:$W$5001="In-progress"),6,9999)))))))*100000+ROW(Data_Insight!$V$2:$V$5001)),3),"")} -> 100167 | AJ252: =IF(Data_Summary!Y253<>"Coverage","",IF(Data_Summary!AA253="","",IF(COUNTIFS(Data_Summary!$Y$2:$Y253,"Coverage",Data_Summary!$AA$2:$AA253,Data_Summary!AA253)=1,Data_Summary!AA253,""))) | AK252: =IF(AJ252="","",COUNTIFS(Data_Summary!$Y$2:$Y$20001,"Coverage",Data_Summary!$AA$2:$AA$20001,AJ252))
J253: {=IFERROR(SMALL(IF(((Data_Insight!$W$2:$W$5001="Open")+(Data_Insight!$W$2:$W$5001="In-progress")),(IF((Data_Insight!$V$2:$V$5001="High")*(Data_Insight!$W$2:$W$5001="Open"),1,IF((Data_Insight!$V$2:$V$5001="High")*(Data_Insight!$W$2:$W$5001="In-progress"),2,IF((Data_Insight!$V$2:$V$5001="Moderate")*(Data_Insight!$W$2:$W$5001="Open"),3,IF((Data_Insight!$V$2:$V$5001="Moderate")*(Data_Insight!$W$2:$W$5001="In-progress"),4,IF((Data_Insight!$V$2:$V$5001="Low")*(Data_Insight!$W$2:$W$5001="Open"),5,IF((Data_Insight!$V$2:$V$5001="Low")*(Data_Insight!$W$2:$W$5001="In-progress"),6,9999)))))))*100000+ROW(Data_Insight!$V$2:$V$5001)),4),"")} -> 100254 | AJ253: =IF(Data_Summary!Y254<>"Coverage","",IF(Data_Summary!AA254="","",IF(COUNTIFS(Data_Summary!$Y$2:$Y254,"Coverage",Data_Summary!$AA$2:$AA254,Data_Summary!AA254)=1,Data_Summary!AA254,""))) | AK253: =IF(AJ253="","",COUNTIFS(Data_Summary!$Y$2:$Y$20001,"Coverage",Data_Summary!$AA$2:$AA$20001,AJ253))
J254: {=IFERROR(SMALL(IF(((Data_Insight!$W$2:$W$5001="Open")+(Data_Insight!$W$2:$W$5001="In-progress")),(IF((Data_Insight!$V$2:$V$5001="High")*(Data_Insight!$W$2:$W$5001="Open"),1,IF((Data_Insight!$V$2:$V$5001="High")*(Data_Insight!$W$2:$W$5001="In-progress"),2,IF((Data_Insight!$V$2:$V$5001="Moderate")*(Data_Insight!$W$2:$W$5001="Open"),3,IF((Data_Insight!$V$2:$V$5001="Moderate")*(Data_Insight!$W$2:$W$5001="In-progress"),4,IF((Data_Insight!$V$2:$V$5001="Low")*(Data_Insight!$W$2:$W$5001="Open"),5,IF((Data_Insight!$V$2:$V$5001="Low")*(Data_Insight!$W$2:$W$5001="In-progress"),6,9999)))))))*100000+ROW(Data_Insight!$V$2:$V$5001)),5),"")} -> 200005 | AJ254: =IF(Data_Summary!Y255<>"Coverage","",IF(Data_Summary!AA255="","",IF(COUNTIFS(Data_Summary!$Y$2:$Y255,"Coverage",Data_Summary!$AA$2:$AA255,Data_Summary!AA255)=1,Data_Summary!AA255,""))) | AK254: =IF(AJ254="","",COUNTIFS(Data_Summary!$Y$2:$Y$20001,"Coverage",Data_Summary!$AA$2:$AA$20001,AJ254))
J255: {=IFERROR(SMALL(IF(((Data_Insight!$W$2:$W$5001="Open")+(Data_Insight!$W$2:$W$5001="In-progress")),(IF((Data_Insight!$V$2:$V$5001="High")*(Data_Insight!$W$2:$W$5001="Open"),1,IF((Data_Insight!$V$2:$V$5001="High")*(Data_Insight!$W$2:$W$5001="In-progress"),2,IF((Data_Insight!$V$2:$V$5001="Moderate")*(Data_Insight!$W$2:$W$5001="Open"),3,IF((Data_Insight!$V$2:$V$5001="Moderate")*(Data_Insight!$W$2:$W$5001="In-progress"),4,IF((Data_Insight!$V$2:$V$5001="Low")*(Data_Insight!$W$2:$W$5001="Open"),5,IF((Data_Insight!$V$2:$V$5001="Low")*(Data_Insight!$W$2:$W$5001="In-progress"),6,9999)))))))*100000+ROW(Data_Insight!$V$2:$V$5001)),6),"")} -> 200027 | AJ255: =IF(Data_Summary!Y256<>"Coverage","",IF(Data_Summary!AA256="","",IF(COUNTIFS(Data_Summary!$Y$2:$Y256,"Coverage",Data_Summary!$AA$2:$AA256,Data_Summary!AA256)=1,Data_Summary!AA256,""))) | AK255: =IF(AJ255="","",COUNTIFS(Data_Summary!$Y$2:$Y$20001,"Coverage",Data_Summary!$AA$2:$AA$20001,AJ255))
J256: {=IFERROR(SMALL(IF(((Data_Insight!$W$2:$W$5001="Open")+(Data_Insight!$W$2:$W$5001="In-progress")),(IF((Data_Insight!$V$2:$V$5001="High")*(Data_Insight!$W$2:$W$5001="Open"),1,IF((Data_Insight!$V$2:$V$5001="High")*(Data_Insight!$W$2:$W$5001="In-progress"),2,IF((Data_Insight!$V$2:$V$5001="Moderate")*(Data_Insight!$W$2:$W$5001="Open"),3,IF((Data_Insight!$V$2:$V$5001="Moderate")*(Data_Insight!$W$2:$W$5001="In-progress"),4,IF((Data_Insight!$V$2:$V$5001="Low")*(Data_Insight!$W$2:$W$5001="Open"),5,IF((Data_Insight!$V$2:$V$5001="Low")*(Data_Insight!$W$2:$W$5001="In-progress"),6,9999)))))))*100000+ROW(Data_Insight!$V$2:$V$5001)),7),"")} -> 200068 | AJ256: =IF(Data_Summary!Y257<>"Coverage","",IF(Data_Summary!AA257="","",IF(COUNTIFS(Data_Summary!$Y$2:$Y257,"Coverage",Data_Summary!$AA$2:$AA257,Data_Summary!AA257)=1,Data_Summary!AA257,""))) | AK256: =IF(AJ256="","",COUNTIFS(Data_Summary!$Y$2:$Y$20001,"Coverage",Data_Summary!$AA$2:$AA$20001,AJ256))
J257: {=IFERROR(SMALL(IF(((Data_Insight!$W$2:$W$5001="Open")+(Data_Insight!$W$2:$W$5001="In-progress")),(IF((Data_Insight!$V$2:$V$5001="High")*(Data_Insight!$W$2:$W$5001="Open"),1,IF((Data_Insight!$V$2:$V$5001="High")*(Data_Insight!$W$2:$W$5001="In-progress"),2,IF((Data_Insight!$V$2:$V$5001="Moderate")*(Data_Insight!$W$2:$W$5001="Open"),3,IF((Data_Insight!$V$2:$V$5001="Moderate")*(Data_Insight!$W$2:$W$5001="In-progress"),4,IF((Data_Insight!$V$2:$V$5001="Low")*(Data_Insight!$W$2:$W$5001="Open"),5,IF((Data_Insight!$V$2:$V$5001="Low")*(Data_Insight!$W$2:$W$5001="In-progress"),6,9999)))))))*100000+ROW(Data_Insight!$V$2:$V$5001)),8),"")} -> 200113 | AJ257: =IF(Data_Summary!Y258<>"Coverage","",IF(Data_Summary!AA258="","",IF(COUNTIFS(Data_Summary!$Y$2:$Y258,"Coverage",Data_Summary!$AA$2:$AA258,Data_Summary!AA258)=1,Data_Summary!AA258,""))) | AK257: =IF(AJ257="","",COUNTIFS(Data_Summary!$Y$2:$Y$20001,"Coverage",Data_Summary!$AA$2:$AA$20001,AJ257))
J258: {=IFERROR(SMALL(IF(((Data_Insight!$W$2:$W$5001="Open")+(Data_Insight!$W$2:$W$5001="In-progress")),(IF((Data_Insight!$V$2:$V$5001="High")*(Data_Insight!$W$2:$W$5001="Open"),1,IF((Data_Insight!$V$2:$V$5001="High")*(Data_Insight!$W$2:$W$5001="In-progress"),2,IF((Data_Insight!$V$2:$V$5001="Moderate")*(Data_Insight!$W$2:$W$5001="Open"),3,IF((Data_Insight!$V$2:$V$5001="Moderate")*(Data_Insight!$W$2:$W$5001="In-progress"),4,IF((Data_Insight!$V$2:$V$5001="Low")*(Data_Insight!$W$2:$W$5001="Open"),5,IF((Data_Insight!$V$2:$V$5001="Low")*(Data_Insight!$W$2:$W$5001="In-progress"),6,9999)))))))*100000+ROW(Data_Insight!$V$2:$V$5001)),9),"")} -> 200151 | AJ258: =IF(Data_Summary!Y259<>"Coverage","",IF(Data_Summary!AA259="","",IF(COUNTIFS(Data_Summary!$Y$2:$Y259,"Coverage",Data_Summary!$AA$2:$AA259,Data_Summary!AA259)=1,Data_Summary!AA259,""))) | AK258: =IF(AJ258="","",COUNTIFS(Data_Summary!$Y$2:$Y$20001,"Coverage",Data_Summary!$AA$2:$AA$20001,AJ258))
J259: {=IFERROR(SMALL(IF(((Data_Insight!$W$2:$W$5001="Open")+(Data_Insight!$W$2:$W$5001="In-progress")),(IF((Data_Insight!$V$2:$V$5001="High")*(Data_Insight!$W$2:$W$5001="Open"),1,IF((Data_Insight!$V$2:$V$5001="High")*(Data_Insight!$W$2:$W$5001="In-progress"),2,IF((Data_Insight!$V$2:$V$5001="Moderate")*(Data_Insight!$W$2:$W$5001="Open"),3,IF((Data_Insight!$V$2:$V$5001="Moderate")*(Data_Insight!$W$2:$W$5001="In-progress"),4,IF((Data_Insight!$V$2:$V$5001="Low")*(Data_Insight!$W$2:$W$5001="Open"),5,IF((Data_Insight!$V$2:$V$5001="Low")*(Data_Insight!$W$2:$W$5001="In-progress"),6,9999)))))))*100000+ROW(Data_Insight!$V$2:$V$5001)),10),"")} -> 200156 | AJ259: =IF(Data_Summary!Y260<>"Coverage","",IF(Data_Summary!AA260="","",IF(COUNTIFS(Data_Summary!$Y$2:$Y260,"Coverage",Data_Summary!$AA$2:$AA260,Data_Summary!AA260)=1,Data_Summary!AA260,""))) | AK259: =IF(AJ259="","",COUNTIFS(Data_Summary!$Y$2:$Y$20001,"Coverage",Data_Summary!$AA$2:$AA$20001,AJ259))
AJ260: =IF(Data_Summary!Y261<>"Coverage","",IF(Data_Summary!AA261="","",IF(COUNTIFS(Data_Summary!$Y$2:$Y261,"Coverage",Data_Summary!$AA$2:$AA261,Data_Summary!AA261)=1,Data_Summary!AA261,""))) | AK260: =IF(AJ260="","",COUNTIFS(Data_Summary!$Y$2:$Y$20001,"Coverage",Data_Summary!$AA$2:$AA$20001,AJ260))
A261: ACTION ITEMS STATUS × SEVERITY | Data for Dashboard Chart | AJ261: =IF(Data_Summary!Y262<>"Coverage","",IF(Data_Summary!AA262="","",IF(COUNTIFS(Data_Summary!$Y$2:$Y262,"Coverage",Data_Summary!$AA$2:$AA262,Data_Summary!AA262)=1,Data_Summary!AA262,""))) | AK261: =IF(AJ261="","",COUNTIFS(Data_Summary!$Y$2:$Y$20001,"Coverage",Data_Summary!$AA$2:$AA$20001,AJ261))
...

Sheet Dashboard
C2: EMPLOYEE PULSE & ENGAGEMENT DASHBOARD | S2: May 2026 | IBU: All
C3: Monthly HRBP–Business Cadence | Action-Oriented People Review
C8: =Calc!B3 -> 300 | F8: =Calc!B4 -> 29 | I8: =Calc!B7 -> 63 | L8: =Calc!B5 -> 57 | O8: =Calc!B13 -> 71.333333 | R8: =Calc!B14 -> 79.333333 | U8: =Calc!B15 -> 299 | W8: =Calc!B16 -> 10
C9: TOTAL SESSIONS | F9: OPEN CONCERNS | I9: HIGH SEVERITY | L9: IN-PROGRESS | O9: ACTION CLOSURE % | R9: SENTIMENT SCORE | U9: ACTIVE BHRs | W9: SLs COVERED
F10: f
C12: MOST ACTIVE SERVICE LINE | I12: IBU/Practice/Location | O12: TOP CARES LEVER | U12: OPEN + IN-PROGRESS
C13: =Calc!B17 -> DEA Service Line | I13: =Calc!B18 -> IBU Specific Connect | O13: =Calc!B19 -> Alignment | U13: =Calc!B20 -> 86
C15: ENGAGEMENT OVERVIEW
C35: ENGAGEMENT MIX | Mode · Connect Type · Service-Line Risk
C56: SERVICE LINE RISK HEATMAP | Severity by SL
C70: 🍩 SESSION DISTRIBUTION | Share of sessions across engagement cohorts
C91: 🚨 TOP 10 PRIORITY ISSUES | Ranked: High→Moderate→Low × Open→In-Progress
C92: # | D92: ID | E92: BHR Name | G92: Service Line | I92: Engagement Cohort | L92: Severity | N92: Status | P92: Key Issue / Engagement Query
C93: =IFERROR(Calc!A271,"—") -> 1 | D93: =IFERROR(Calc!B271,"—") -> 25 | E93: =IFERROR(Calc!C271,"—") -> Aadi Naik | G93: =IFERROR(Calc!D271,"—") -> DIG Vertical | I93: =IFERROR(Calc!E271,"—") -> New Joiner Connect (90 Days) | L93: =IFERROR(Calc!F271,"—") -> High | N93: =IFERROR(Calc!G271,"—") -> Open | P93: =IFERROR(Calc!H271,"—") -> aNA
C94: =IFERROR(Calc!A272,"—") -> 2 | D94: =IFERROR(Calc!B272,"—") -> 63 | E94: =IFERROR(Calc!C272,"—") -> Chaitanya Aggarwal | G94: =IFERROR(Calc!D272,"—") -> Network Services Service Line | I94: =IFERROR(Calc!E272,"—") -> SL Induction | L94: =IFERROR(Calc!F272,"—") -> High | N94: =IFERROR(Calc!G272,"—") -> Open | P94: =IFERROR(Calc!H272,"—") -> NA
C95: =IFERROR(Calc!A273,"—") -> 3 | D95: =IFERROR(Calc!B273,"—") -> 166 | E95: =IFERROR(Calc!C273,"—") -> Harini Tripathi | G95: =IFERROR(Calc!D273,"—") -> DEA Service Line | I95: =IFERROR(Calc!E273,"—") -> Women Associate Connect | L95: =IFERROR(Calc!F273,"—") -> High | N95: =IFERROR(Calc!G273,"—") -> Open | P95: =IFERROR(Calc!H273,"—") -> NA
C96: =IFERROR(Calc!A274,"—") -> 4 | D96: =IFERROR(Calc!B274,"—") -> 253 | E96: =IFERROR(Calc!C274,"—") -> Anvi Bhalla | G96: =IFERROR(Calc!D274,"—") -> DEA Service Line | I96: =IFERROR(Calc!E274,"—") -> ML Returnee Connect | L96: =IFERROR(Calc!F274,"—") -> High | N96: =IFERROR(Calc!G274,"—") -> Open | P96: =IFERROR(Calc!H274,"—") -> NA
C97: =IFERROR(Calc!A275,"—") -> 5 | D97: =IFERROR(Calc!B275,"—") -> 4 | E97: =IFERROR(Calc!C275,"—") -> Abeer Dutta | G97: =IFERROR(Calc!D275,"—") -> DEA Service Line | I97: =IFERROR(Calc!E275,"—") -> ML Returnee Connect | L97: =IFERROR(Calc!F275,"—") -> High | N97: =IFERROR(Calc!G275,"—") -> In-progress | P97: =IFERROR(Calc!H275,"—") -> No response on IJP applied on Rapid
C98: =IFERROR(Calc!A276,"—") -> 6 | D98: =IFERROR(Calc!B276,"—") -> 26 | E98: =IFERROR(Calc!C276,"—") -> Janani Mohanty | G98: =IFERROR(Calc!D276,"—") -> DEA Service Line | I98: =IFERROR(Calc!E276,"—") -> Top Talent Connect | L98: =IFERROR(Calc!F276,"—") -> High | N98: =IFERROR(Calc!G276,"—") -> In-progress | P98: =IFERROR(Calc!H276,"—") -> NA
C99: =IFERROR(Calc!A277,"—") -> 7 | D99: =IFERROR(Calc!B277,"—") -> 67 | E99: =IFERROR(Calc!C277,"—") -> Qushi Datta | G99: =IFERROR(Calc!D277,"—") -> DEA Service Line | I99: =IFERROR(Calc!E277,"—") -> Wellness Session | L99: =IFERROR(Calc!F277,"—") -> High | N99: =IFERROR(Calc!G277,"—") -> In-progress | P99: =IFERROR(Calc!H277,"—") -> Workshops
C100: =IFERROR(Calc!A278,"—") -> 8 | D100: =IFERROR(Calc!B278,"—") -> 112 | E100: =IFERROR(Calc!C278,"—") -> Oliver Contractor | G100: =IFERROR(Calc!D278,"—") -> DEA Service Line | I100: =IFERROR(Calc!E278,"—") -> HR Connect (Project Wise) | L100: =IFERROR(Calc!F278,"—") -> High | N100: =IFERROR(Calc!G278,"—") -> In-progress | P100: =IFERROR(Calc!H278,"—") -> Leave encashment, Gratuity,Exit guidelines
C101: =IFERROR(Calc!A279,"—") -> 9 | D101: =IFERROR(Calc!B279,"—") -> 150 | E101: =IFERROR(Calc!C279,"—") -> Ekantika Krishna | G101: =IFERROR(Calc!D279,"—") -> DEA Service Line | I101: =IFERROR(Calc!E279,"—") -> HR Connect (General) | L101: =IFERROR(Calc!F279,"—") -> High | N101: =IFERROR(Calc!G279,"—") -> In-progress | P101: =IFERROR(Calc!H279,"—") -> NA
C102: =IFERROR(Calc!A280,"—") -> 10 | D102: =IFERROR(Calc!B280,"—") -> 155 | E102: =IFERROR(Calc!C280,"—") -> Bhavya Rattan | G102: =IFERROR(Calc!D280,"—") -> DEA Service Line | I102: =IFERROR(Calc!E280,"—") -> Cadence Connect | L102: =IFERROR(Calc!F280,"—") -> High | N102: =IFERROR(Calc!G280,"—") -> In-progress | P102: =IFERROR(Calc!H280,"—") -> the associates had queries related to timesheet which was cleared during the call
C105: 📊 ACTION ITEMS STATUS | Open · In-Progress · Closed × Severity Level
C107: Status | D107: 🔴 High | E107: 🟡 Moderate | F107: 🟢 Low | G107: Total
C108: =Calc!A264 -> Open | D108: =Calc!B264 -> 4 | E108: =Calc!C264 -> 17 | F108: =Calc!D264 -> 8 | G108: =Calc!E264 -> 29
C109: =Calc!A265 -> In-progress | D109: =Calc!B265 -> 15 | E109: =Calc!C265 -> 23 | F109: =Calc!D265 -> 19 | G109: =Calc!E265 -> 57
C110: =Calc!A266 -> Closed | D110: =Calc!B266 -> 44 | E110: =Calc!C266 -> 86 | F110: =Calc!D266 -> 84 | G110: =Calc!E266 -> 214
C121: 🔍 TOP 10 COVERAGE ISSUES | Organization-wide discussion themes ranked by BHR coverage
C122: # | D122: Coverage Area | L122: BHR Count | O122: % of Sessions | R122: Associated Engagement Type
C123: 1 | D123: =IFERROR(Calc!Q3,"") -> Feedback on recent processes | L123: =IFERROR(Calc!R3,"") -> 24 | O123: =IFERROR(Calc!S3,"") -> 0.08 | R123: =IFERROR(Calc!T3,"") -> 1:1
C124: 2 | D124: =IFERROR(Calc!Q4,"") -> Clarity on expectations | L124: =IFERROR(Calc!R4,"") -> 19 | O124: =IFERROR(Calc!S4,"") -> 0.063333333 | R124: =IFERROR(Calc!T4,"") -> Large Connect
C125: 3 | D125: =IFERROR(Calc!Q5,"") -> General wellbeing check-in | L125: =IFERROR(Calc!R5,"") -> 16 | O125: =IFERROR(Calc!S5,"") -> 0.053333333 | R125: =IFERROR(Calc!T5,"") -> Location-Offshore
C126: 4 | D126: =IFERROR(Calc!Q6,"") -> Team Integration | L126: =IFERROR(Calc!R6,"") -> 13 | O126: =IFERROR(Calc!S6,"") -> 0.043333333 | R126: =IFERROR(Calc!T6,"") -> Induction
C127: 5 | D127: =IFERROR(Calc!Q7,"") -> Workload & Work-Life Balance | L127: =IFERROR(Calc!R7,"") -> 12 | O127: =IFERROR(Calc!S7,"") -> 0.04 | R127: =IFERROR(Calc!T7,"") -> FGD
C128: 6 | D128: =IFERROR(Calc!Q8,"") -> Discussion on team dynamics | L128: =IFERROR(Calc!R8,"") -> 12 | O128: =IFERROR(Calc!S8,"") -> 0.04 | R128: =IFERROR(Calc!T8,"") -> 1:1
C129: 7 | D129: =IFERROR(Calc!Q9,"") -> Business & Strategy Clarity | L129: =IFERROR(Calc!R9,"") -> 11 | O129: =IFERROR(Calc!S9,"") -> 0.036666667 | R129: =IFERROR(Calc!T9,"") -> Large Connect
C130: 8 | D130: =IFERROR(Calc!Q10,"") -> HR / WFM / Training Communication Effectiveness | L130: =IFERROR(Calc!R10,"") -> 11 | O130: =IFERROR(Calc!S10,"") -> 0.036666667 | R130: =IFERROR(Calc!T10,"") -> 1:1
C131: 9 | D131: =IFERROR(Calc!Q11,"") -> Manager Support & Local Leadership Effectiveness | L131: =IFERROR(Calc!R11,"") -> 10 | O131: =IFERROR(Calc!S11,"") -> 0.033333333 | R131: =IFERROR(Calc!T11,"") -> FGD
C132: 10 | D132: =IFERROR(Calc!Q12,"") -> Queries related to BGV check | L132: =IFERROR(Calc!R12,"") -> 10 | O132: =IFERROR(Calc!S12,"") -> 0.033333333 | R132: =IFERROR(Calc!T12,"") -> Induction
C134: 🗣️ TOP ORGANIZATIONAL CONCERNS | What employees are talking about (top 10 recurring themes)
C146: ⚖️ CARES LEVER BREAKDOWN | Sessions by Framework Pillar × Severity + Action Owner
C148: CARES Lever | D148: Sessions | E148: High Sev | F148: Mod Sev | G148: Low Sev | H148: % of Total
C149: =Calc!A42 -> Alignment | D149: =Calc!B42 -> 173 | E149: =COUNTIFS(RawData[CARES Framework],C149,RawData[Severity],"High") -> 38 | F149: =COUNTIFS(RawData[CARES Framework],C149,RawData[Severity],"Moderate") -> 73 | G149: =COUNTIFS(RawData[CARES Framework],C149,RawData[Severity],"Low") -> 62 | H149: =IFERROR(D149/Calc!$B$3,0) -> 0.57666667
C150: =Calc!A43 -> Career | D150: =Calc!B43 -> 40 | E150: =COUNTIFS(RawData[CARES Framework],C150,RawData[Severity],"High") -> 7 | F150: =COUNTIFS(RawData[CARES Framework],C150,RawData[Severity],"Moderate") -> 17 | G150: =COUNTIFS(RawData[CARES Framework],C150,RawData[Severity],"Low") -> 16 | H150: =IFERROR(D150/Calc!$B$3,0) -> 0.13333333
C151: =Calc!A44 -> Empowerment | D151: =Calc!B44 -> 58 | E151: =COUNTIFS(RawData[CARES Framework],C151,RawData[Severity],"High") -> 10 | F151: =COUNTIFS(RawData[CARES Framework],C151,RawData[Severity],"Moderate") -> 25 | G151: =COUNTIFS(RawData[CARES Framework],C151,RawData[Severity],"Low") -> 23 | H151: =IFERROR(D151/Calc!$B$3,0) -> 0.19333333
C152: =Calc!A45 -> Recognition | D152: =Calc!B45 -> 14 | E152: =COUNTIFS(RawData[CARES Framework],C152,RawData[Severity],"High") -> 3 | F152: =COUNTIFS(RawData[CARES Framework],C152,RawData[Severity],"Moderate") -> 6 | G152: =COUNTIFS(RawData[CARES Framework],C152,RawData[Severity],"Low") -> 5 | H152: =IFERROR(D152/Calc!$B$3,0) -> 0.046666667
C153: =Calc!A46 -> Strive | D153: =Calc!B46 -> 15 | E153: =COUNTIFS(RawData[CARES Framework],C153,RawData[Severity],"High") -> 5 | F153: =COUNTIFS(RawData[CARES Framework],C153,RawData[Severity],"Moderate") -> 5 | G153: =COUNTIFS(RawData[CARES Framework],C153,RawData[Severity],"Low") -> 5 | H153: =IFERROR(D153/Calc!$B$3,0) -> 0.05
C155: 📍 ENGAGEMENT MODE & TYPE | How and through what formats engagement happens

Sheet Data_Summary
A1: ID | B1: Start time | C1: Completion time | D1: Email | E1: Name | F1: BHR Name | G1: BHR Employee ID | H1: Date of Connect | I1: Service Line | J1: IBU/Practice/Location | K1: Location Mentioned | L1: Practice Code | M1: Employee IBU Code | N1: Project Description | O1: Engagement Type | P1: Band | Q1: Engagement Mode | R1: CARES Framework | S1: Overall Sentiment | T1: Action Owner | U1: Engagement related Queries | V1: Severity | W1: Status | X1: Engagement Cohort | Y1: Record Type | Z1: Statement Order | AA1: Statement
A2: 1 | B2: 46150.506 | C2: 46150.523 | D2: AK216739@techmahindra.com | E2: Anvi Konda | F2: Liam Chaudry | G2: 216739 | H2: 46142 | I2: DEA Service Line | J2: IBU Specific Connect | K2: Gudivada | L2: DEA-D-2003 | M2: DEA-D-2004 | N2: Practice | O2: Large Connect | P2: MIX | Q2: Virtual | R2: Alignment | S2: Neutral | T2: No specific Action, Issue addressed in meeting; | U2: NA | V2: Moderate | W2: Closed | X2: ML Returnee Connect | Y2: Coverage | Z2: 1 | AA2: Review of ongoing concerns
A3: 1 | B3: 46150.506 | C3: 46150.523 | D3: AK216739@techmahindra.com | E3: Anvi Konda | F3: Liam Chaudry | G3: 216739 | H3: 46142 | I3: DEA Service Line | J3: IBU Specific Connect | K3: Gudivada | L3: DEA-D-2003 | M3: DEA-D-2004 | N3: Practice | O3: Large Connect | P3: MIX | Q3: Virtual | R3: Alignment | S3: Neutral | T3: No specific Action, Issue addressed in meeting; | U3: NA | V3: Moderate | W3: Closed | X3: ML Returnee Connect | Y3: Key Insight | Z3: 1 | AA3: No major concerns raised
A4: 1 | B4: 46150.506 | C4: 46150.523 | D4: AK216739@techmahindra.com | E4: Anvi Konda | F4: Liam Chaudry | G4: 216739 | H4: 46142 | I4: DEA Service Line | J4: IBU Specific Connect | K4: Gudivada | L4: DEA-D-2003 | M4: DEA-D-2004 | N4: Practice | O4: Large Connect | P4: MIX | Q4: Virtual | R4: Alignment | S4: Neutral | T4: No specific Action, Issue addressed in meeting; | U4: NA | V4: Moderate | W4: Closed | X4: ML Returnee Connect | Y4: Key Insight | Z4: 2 | AA4: Minor process related queries
A5: 1 | B5: 46150.506 | C5: 46150.523 | D5: AK216739@techmahindra.com | E5: Anvi Konda | F5: Liam Chaudry | G5: 216739 | H5: 46142 | I5: DEA Service Line | J5: IBU Specific Connect | K5: Gudivada | L5: DEA-D-2003 | M5: DEA-D-2004 | N5: Practice | O5: Large Connect | P5: MIX | Q5: Virtual | R5: Alignment | S5: Neutral | T5: No specific Action, Issue addressed in meeting; | U5: NA | V5: Moderate | W5: Closed | X5: ML Returnee Connect | Y5: Action Plan | Z5: 1 | AA5: NA
A6: 1 | B6: 46150.506 | C6: 46150.523 | D6: AK216739@techmahindra.com | E6: Anvi Konda | F6: Liam Chaudry | G6: 216739 | H6: 46142 | I6: DEA Service Line | J6: IBU Specific Connect | K6: Gudivada | L6: DEA-D-2003 | M6: DEA-D-2004 | N6: Practice | O6: Large Connect | P6: MIX | Q6: Virtual | R6: Alignment | S6: Neutral | T6: No specific Action, Issue addressed in meeting; | U6: NA | V6: Moderate | W6: Closed | X6: ML Returnee Connect | Y6: Action Plan | Z6: 2 | AA6: Continue regular check-ins
A7: 2 | B7: 46110.807 | C7: 46110.828 | D7: GK145561@techmahindra.com | E7: Girik Kamdar | F7: Girik Kamdar | G7: 145561 | H7: 46093 | I7: CIS Service Line | J7: Location Specific Connect | K7: Dibrugarh | L7: DEA-D-4021 | M7: DEA-D-4031 | N7: EY Project | O7: Large Connect | P7: U | Q7: Virtual | R7: Alignment | S7: Neutral | T7: No specific Action, Issue addressed in meeting; | V7: Moderate | W7: Open | X7: Townhall | Y7: Coverage | Z7: 1 | AA7: Business & Strategy Clarity
A8: 2 | B8: 46110.807 | C8: 46110.828 | D8: GK145561@techmahindra.com | E8: Girik Kamdar | F8: Girik Kamdar | G8: 145561 | H8: 46093 | I8: CIS Service Line | J8: Location Specific Connect | K8: Dibrugarh | L8: DEA-D-4021 | M8: DEA-D-4031 | N8: EY Project | O8: Large Connect | P8: U | Q8: Virtual | R8: Alignment | S8: Neutral | T8: No specific Action, Issue addressed in meeting; | V8: Moderate | W8: Open | X8: Townhall | Y8: Coverage | Z8: 2 | AA8: Career Visibility & Skill Roadmap
A9: 2 | B9: 46110.807 | C9: 46110.828 | D9: GK145561@techmahindra.com | E9: Girik Kamdar | F9: Girik Kamdar | G9: 145561 | H9: 46093 | I9: CIS Service Line | J9: Location Specific Connect | K9: Dibrugarh | L9: DEA-D-4021 | M9: DEA-D-4031 | N9: EY Project | O9: Large Connect | P9: U | Q9: Virtual | R9: Alignment | S9: Neutral | T9: No specific Action, Issue addressed in meeting; | V9: Moderate | W9: Open | X9: Townhall | Y9: Coverage | Z9: 3 | AA9: AI/future Readiness Messaging Is High-level
A10: 2 | B10: 46110.807 | C10: 46110.828 | D10: GK145561@techmahindra.com | E10: Girik Kamdar | F10: Girik Kamdar | G10: 145561 | H10: 46093 | I10: CIS Service Line | J10: Location Specific Connect | K10: Dibrugarh | L10: DEA-D-4021 | M10: DEA-D-4031 | N10: EY Project | O10: Large Connect | P10: U | Q10: Virtual | R10: Alignment | S10: Neutral | T10: No specific Action, Issue addressed in meeting; | V10: Moderate | W10: Open | X10: Townhall | Y10: Key Insight | Z10: 1 | AA10: Associates are unsure how unit goals translate into day-to-day delivery expectations
A11: 2 | B11: 46110.807 | C11: 46110.828 | D11: GK145561@techmahindra.com | E11: Girik Kamdar | F11: Girik Kamdar | G11: 145561 | H11: 46093 | I11: CIS Service Line | J11: Location Specific Connect | K11: Dibrugarh | L11: DEA-D-4021 | M11: DEA-D-4031 | N11: EY Project | O11: Large Connect | P11: U | Q11: Virtual | R11: Alignment | S11: Neutral | T11: No specific Action, Issue addressed in meeting; | V11: Moderate | W11: Open | X11: Townhall | Y11: Action Plan | Z11: 1 | AA11: Capture workload hotspots and review with delivery leads for rebalancing
A12: 2 | B12: 46110.807 | C12: 46110.828 | D12: GK145561@techmahindra.com | E12: Girik Kamdar | F12: Girik Kamdar | G12: 145561 | H12: 46093 | I12: CIS Service Line | J12: Location Specific Connect | K12: Dibrugarh | L12: DEA-D-4021 | M12: DEA-D-4031 | N12: EY Project | O12: Large Connect | P12: U | Q12: Virtual | R12: Alignment | S12: Neutral | T12: No specific Action, Issue addressed in meeting; | V12: Moderate | W12: Open | X12: Townhall | Y12: Action Plan | Z12: 2 | AA12: NA
A13: 3 | B13: 46143.679 | C13: 46143.697 | D13: OK356702@techmahindra.com | E13: Oni Kannan | F13: Oni Kannan | G13: 356702 | H13: 46131 | I13: DEA Service Line | J13: Location Specific Connect | K13: Hyderabad | L13: DEA-D-4026 | M13: CIS D 2001 | N13: Kimberly Clark | O13: Large Connect | P13: U | Q13: In-person-Tech M | R13: Alignment | S13: Positive | T13: No specific Action, Issue addressed in meeting; | U13: Team was contented with the fun connect as it was a nice short break from work and the whole account was able to connect virtually | V13: Moderate | W13: Closed | X13: SL Induction | Y13: Coverage | Z13: 1 | AA13: Visibility on Allocation & Demand
A14: 3 | B14: 46143.679 | C14: 46143.697 | D14: OK356702@techmahindra.com | E14: Oni Kannan | F14: Oni Kannan | G14: 356702 | H14: 46131 | I14: DEA Service Line | J14: Location Specific Connect | K14: Hyderabad | L14: DEA-D-4026 | M14: CIS D 2001 | N14: Kimberly Clark | O14: Large Connect | P14: U | Q14: In-person-Tech M | R14: Alignment | S14: Positive | T14: No specific Action, Issue addressed in meeting; | U14: Team was contented with the fun connect as it was a nice short break from work and the whole account was able to connect virtually | V14: Moderate | W14: Closed | X14: SL Induction | Y14: Key Insight | Z14: 1 | AA14: Associates lack clarity on practice goals and IBU priorities
A15: 3 | B15: 46143.679 | C15: 46143.697 | D15: OK356702@techmahindra.com | E15: Oni Kannan | F15: Oni Kannan | G15: 356702 | H15: 46131 | I15: DEA Service Line | J15: Location Specific Connect | K15: Hyderabad | L15: DEA-D-4026 | M15: CIS D 2001 | N15: Kimberly Clark | O15: Large Connect | P15: U | Q15: In-person-Tech M | R15: Alignment | S15: Positive | T15: No specific Action, Issue addressed in meeting; | U15: Team was contented with the fun connect as it was a nice short break from work and the whole account was able to connect virtually | V15: Moderate | W15: Closed | X15: SL Induction | Y15: Key Insight | Z15: 2 | AA15: HR/WFM/Training updates not actionable
A16: 3 | B16: 46143.679 | C16: 46143.697 | D16: OK356702@techmahindra.com | E16: Oni Kannan | F16: Oni Kannan | G16: 356702 | H16: 46131 | I16: DEA Service Line | J16: Location Specific Connect | K16: Hyderabad | L16: DEA-D-4026 | M16: CIS D 2001 | N16: Kimberly Clark | O16: Large Connect | P16: U | Q16: In-person-Tech M | R16: Alignment | S16: Positive | T16: No specific Action, Issue addressed in meeting; | U16: Team was contented with the fun connect as it was a nice short break from work and the whole account was able to connect virtually | V16: Moderate | W16: Closed | X16: SL Induction | Y16: Action Plan | Z16: 1 | AA16: TLS SPOC had cleared all the queries w.r.t learning
A17: 3 | B17: 46143.679 | C17: 46143.697 | D17: OK356702@techmahindra.com | E17: Oni Kannan | F17: Oni Kannan | G17: 356702 | H17: 46131 | I17: DEA Service Line | J17: Location Specific Connect | K17: Hyderabad | L17: DEA-D-4026 | M17: CIS D 2001 | N17: Kimberly Clark | O17: Large Connect | P17: U | Q17: In-person-Tech M | R17: Alignment | S17: Positive | T17: No specific Action, Issue addressed in meeting; | U17: Team was contented with the fun connect as it was a nice short break from work and the whole account was able to connect virtually | V17: Moderate | W17: Closed | X17: SL Induction | Y17: Action Plan | Z17: 2 | AA17: Provide FAQs, guides, refresher sessions
A18: 4 | B18: 46115.788 | C18: 46115.793 | D18: AD634277@techmahindra.com | E18: Abeer Dutta | F18: Abeer Dutta | G18: 634277 | H18: 46114 | I18: DEA Service Line | J18: IBU Specific Connect | K18: Mau | L18: NGS-D-2004 | M18: DEA-D-4022 | N18: Rating Calibration call with IBU Head | O18: Location-Offshore | P18: MIX | Q18: Virtual | R18: Alignment | S18: Positive | T18: WFM;Delivery; | U18: No response on IJP applied on Rapid | V18: High | W18: In-progress | X18: ML Returnee Connect | Y18: Coverage | Z18: 1 | AA18: General wellbeing check-in
A19: 4 | B19: 46115.788 | C19: 46115.793 | D19: AD634277@techmahindra.com | E19: Abeer Dutta | F19: Abeer Dutta | G19: 634277 | H19: 46114 | I19: DEA Service Line | J19: IBU Specific Connect | K19: Mau | L19: NGS-D-2004 | M19: DEA-D-4022 | N19: Rating Calibration call with IBU Head | O19: Location-Offshore | P19: MIX | Q19: Virtual | R19: Alignment | S19: Positive | T19: WFM;Delivery; | U19: No response on IJP applied on Rapid | V19: High | W19: In-progress | X19: ML Returnee Connect | Y19: Key Insight | Z19: 1 | AA19: Associates are settling in well
A20: 4 | B20: 46115.788 | C20: 46115.793 | D20: AD634277@techmahindra.com | E20: Abeer Dutta | F20: Abeer Dutta | G20: 634277 | H20: 46114 | I20: DEA Service Line | J20: IBU Specific Connect | K20: Mau | L20: NGS-D-2004 | M20: DEA-D-4022 | N20: Rating Calibration call with IBU Head | O20: Location-Offshore | P20: MIX | Q20: Virtual | R20: Alignment | S20: Positive | T20: WFM;Delivery; | U20: No response on IJP applied on Rapid | V20: High | W20: In-progress | X20: ML Returnee Connect | Y20: Key Insight | Z20: 2 | AA20: NA
A21: 4 | B21: 46115.788 | C21: 46115.793 | D21: AD634277@techmahindra.com | E21: Abeer Dutta | F21: Abeer Dutta | G21: 634277 | H21: 46114 | I21: DEA Service Line | J21: IBU Specific Connect | K21: Mau | L21: NGS-D-2004 | M21: DEA-D-4022 | N21: Rating Calibration call with IBU Head | O21: Location-Offshore | P21: MIX | Q21: Virtual | R21: Alignment | S21: Positive | T21: WFM;Delivery; | U21: No response on IJP applied on Rapid | V21: High | W21: In-progress | X21: ML Returnee Connect | Y21: Action Plan | Z21: 1 | AA21: Share update with relevant stakeholder
A22: 4 | B22: 46115.788 | C22: 46115.793 | D22: AD634277@techmahindra.com | E22: Abeer Dutta | F22: Abeer Dutta | G22: 634277 | H22: 46114 | I22: DEA Service Line | J22: IBU Specific Connect | K22: Mau | L22: NGS-D-2004 | M22: DEA-D-4022 | N22: Rating Calibration call with IBU Head | O22: Location-Offshore | P22: MIX | Q22: Virtual | R22: Alignment | S22: Positive | T22: WFM;Delivery; | U22: No response on IJP applied on Rapid | V22: High | W22: In-progress | X22: ML Returnee Connect | Y22: Action Plan | Z22: 2 | AA22: Continue regular check-ins
A23: 5 | B23: 46084.515 | C23: 46084.532 | D23: GC632323@techmahindra.com | E23: Gayathri Chaudry | F23: Gayathri Chaudry | G23: 632323 | H23: 46080 | I23: DEA Service Line | J23: IBU Specific Connect | K23: Bengaluru | L23: DEA-D-4026 | M23: NGS-D-4037 | N23: Keysight | O23: FGD | P23: MIX | Q23: Virtual | R23: Alignment | S23: Positive | T23: Delivery; | U23: NA | V23: Moderate | W23: Closed | X23: HR Connect (General) | Y23: Coverage | Z23: 1 | AA23: Connect for recognition
A24: 5 | B24: 46084.515 | C24: 46084.532 | D24: GC632323@techmahindra.com | E24: Gayathri Chaudry | F24: Gayathri Chaudry | G24: 632323 | H24: 46080 | I24: DEA Service Line | J24: IBU Specific Connect | K24: Bengaluru | L24: DEA-D-4026 | M24: NGS-D-4037 | N24: Keysight | O24: FGD | P24: MIX | Q24: Virtual | R24: Alignment | S24: Positive | T24: Delivery; | U24: NA | V24: Moderate | W24: Closed | X24: HR Connect (General) | Y24: Coverage | Z24: 2 | AA24: Clarity On Role-based Learning Expectations
... A52: 10 | B52: 46174.899 | C52: 46174.908 | D52: VC172132@techmahindra.com | E52: Viraj Chaudhuri | F52: Viraj Chaudhuri | G52: 172132 | H52: 46163 | I52: DEA Service Line | J52: IBU Specific Connect | K52: Hyderbad | L52: all | M52: DIG-D-4001, DIG-D-4005, DIG-D-4007 | N52: DEA BLR (Women Associates) | O52: FGD | P52: MIX | Q52: In-person-Tech M | R52: Empowerment | S52: Positive | T52: Delivery; | U52: RTO management and Bench | V52: Low | W52: In-progress | X52: Women Associate Connect | Y52: Action Plan | Z52: 2 | AA52: Reinforce speak-up channels
A53: 11 | B53: 46103.179 | C53: 46103.187 | D53: JG146228@techmahindra.com | E53: Janya Gaba | F53: Isha Kadakia | G53: 146228 | H53: 46099 | I53: DEA Service Line | J53: IBU Specific Connect | K53: PUNE | L53: DAI-D-2005 | M53: COM D 4018 | N53: SAP | O53: 1:1 | P53: MIX | Q53: Mix (Virtual & In-person) | R53: Career | S53: Neutral | T53: No specific Action, Issue addressed in meeting; | V53: Low | W53: In-progress | X53: Top Talent FGD Connect | Y53: Coverage | Z53: 1 | AA53: Review of ongoing concerns
A54: 11 | B54: 46103.179 | C54: 46103.187 | D54: JG146228@techmahindra.com | E54: Janya Gaba | F54: Isha Kadakia | G54: 146228 | H54: 46099 | I54: DEA Service Line | J54: IBU Specific Connect | K54: PUNE | L54: DAI-D-2005 | M54: COM D 4018 | N54: SAP | O54: 1:1 | P54: MIX | Q54: Mix (Virtual & In-person) | R54: Career | S54: Neutral | T54: No specific Action, Issue addressed in meeting; | V54: Low | W54: In-progress | X54: Top Talent FGD Connect | Y54: Coverage | Z54: 2 | AA54: Feedback on recent processes
A55: 11 | B55: 46103.179 | C55: 46103.187 | D55: JG146228@techmahindra.com | E55: Janya Gaba | F55: Isha Kadakia | G55: 146228 | H55: 46099 | I55: DEA Service Line | J55: IBU Specific Connect | K55: PUNE | L55: DAI-D-2005 | M55: COM D 4018 | N55: SAP | O55: 1:1 | P55: MIX | Q55: Mix (Virtual & In-person) | R55: Career | S55: Neutral | T55: No specific Action, Issue addressed in meeting; | V55: Low | W55: In-progress | X55: Top Talent FGD Connect | Y55: Coverage | Z55: 3 | AA55: Clarity on expectations
A56: 11 | B56: 46103.179 | C56: 46103.187 | D56: JG146228@techmahindra.com | E56: Janya Gaba | F56: Isha Kadakia | G56: 146228 | H56: 46099 | I56: DEA Service Line | J56: IBU Specific Connect | K56: PUNE | L56: DAI-D-2005 | M56: COM D 4018 | N56: SAP | O56: 1:1 | P56: MIX | Q56: Mix (Virtual & In-person) | R56: Career | S56: Neutral | T56: No specific Action, Issue addressed in meeting; | V56: Low | W56: In-progress | X56: Top Talent FGD Connect | Y56: Key Insight | Z56: 1 | AA56: NA
A57: 11 | B57: 46103.179 | C57: 46103.187 | D57: JG146228@techmahindra.com | E57: Janya Gaba | F57: Isha Kadakia | G57: 146228 | H57: 46099 | I57: DEA Service Line | J57: IBU Specific Connect | K57: PUNE | L57: DAI-D-2005 | M57: COM D 4018 | N57: SAP | O57: 1:1 | P57: MIX | Q57: Mix (Virtual & In-person) | R57: Career | S57: Neutral | T57: No specific Action, Issue addressed in meeting; | V57: Low | W57: In-progress | X57: Top Talent FGD Connect | Y57: Action Plan | Z57: 1 | AA57: Monitor and follow up in next cycle
A58: 11 | B58: 46103.179 | C58: 46103.187 | D58: JG146228@techmahindra.com | E58: Janya Gaba | F58: Isha Kadakia | G58: 146228 | H58: 46099 | I58: DEA Service Line | J58: IBU Specific Connect | K58: PUNE | L58: DAI-D-2005 | M58: COM D 4018 | N58: SAP | O58: 1:1 | P58: MIX | Q58: Mix (Virtual & In-person) | R58: Career | S58: Neutral | T58: No specific Action, Issue addressed in meeting; | V58: Low | W58: In-progress | X58: Top Talent FGD Connect | Y58: Action Plan | Z58: 2 | AA58: NA
A59: 12 | B59: 46156.119 | C59: 46156.126 | D59: OW270395@techmahindra.com | E59: Onveer Walla | F59: Onveer Walla | G59: 270395 | H59: 46151 | I59: CIS Service Line | J59: IBU Specific Connect | K59: Kolkata | L59: NGS-D-2004 | M59: DEA-D-4001 | N59: DIG-D-4005, DIG-D-4008, DIG-D-4009 | O59: Location-Offshore | P59: U | Q59: In-person-Tech M | R59: Empowerment | S59: Neutral | T59: Delivery;HRBP; | U59: NA | V59: Moderate | W59: Closed | X59: Leadership Connect | Y59: Coverage | Z59: 1 | AA59: AI Session
A60: 12 | B60: 46156.119 | C60: 46156.126 | D60: OW270395@techmahindra.com | E60: Onveer Walla | F60: Onveer Walla | G60: 270395 | H60: 46151 | I60: CIS Service Line | J60: IBU Specific Connect | K60: Kolkata | L60: NGS-D-2004 | M60: DEA-D-4001 | N60: DIG-D-4005, DIG-D-4008, DIG-D-4009 | O60: Location-Offshore | P60: U | Q60: In-person-Tech M | R60: Empowerment | S60: Neutral | T60: Delivery;HRBP; | U60: NA | V60: Moderate | W60: Closed | X60: Leadership Connect | Y60: Coverage | Z60: 2 | AA60: Review Cadence
A61: 12 | B61: 46156.119 | C61: 46156.126 | D61: OW270395@techmahindra.com | E61: Onveer Walla | F61: Onveer Walla | G61: 270395 | H61: 46151 | I61: CIS Service Line | J61: IBU Specific Connect | K61: Kolkata | L61: NGS-D-2004 | M61: DEA-D-4001 | N61: DIG-D-4005, DIG-D-4008, DIG-D-4009 | O61: Location-Offshore | P61: U | Q61: In-person-Tech M | R61: Empowerment | S61: Neutral | T61: Delivery;HRBP; | U61: NA | V61: Moderate | W61: Closed | X61: Leadership Connect | Y61: Key Insight | Z61: 1 | AA61: Need AI/skill readiness
A62: 12 | B62: 46156.119 | C62: 46156.126 | D62: OW270395@techmahindra.com | E62: Onveer Walla | F62: Onveer Walla | G62: 270395 | H62: 46151 | I62: CIS Service Line | J62: IBU Specific Connect | K62: Kolkata | L62: NGS-D-2004 | M62: DEA-D-4001 | N62: DIG-D-4005, DIG-D-4008, DIG-D-4009 | O62: Location-Offshore | P62: U | Q62: In-person-Tech M | R62: Empowerment | S62: Neutral | T62: Delivery;HRBP; | U62: NA | V62: Moderate | W62: Closed | X62: Leadership Connect | Y62: Action Plan | Z62: 1 | AA62: Publish budget guidelines
A63: 12 | B63: 46156.119 | C63: 46156.126 | D63: OW270395@techmahindra.com | E63: Onveer Walla | F63: Onveer Walla | G63: 270395 | H63: 46151 | I63: CIS Service Line | J63: IBU Specific Connect | K63: Kolkata | L63: NGS-D-2004 | M63: DEA-D-4001 | N63: DIG-D-4005, DIG-D-4008, DIG-D-4009 | O63: Location-Offshore | P63: U | Q63: In-person-Tech M | R63: Empowerment | S63: Neutral | T63: Delivery;HRBP; | U63: NA | V63: Moderate | W63: Closed | X63: Leadership Connect | Y63: Action Plan | Z63: 2 | AA63: Identify hotspots
A64: 13 | B64: 46166.878 | C64: 46166.892 | D64: TR519093@techmahindra.com | E64: Turvi Raghavan | F64: Turvi Raghavan | G64: 519093 | H64: 46149 | I64: DEA Service Line | J64: IBU Specific Connect | K64: Hyderbad | L64: DEA-D-2006 | M64: DEA-D-4040 | N64: New Joiner Connect - 60 days | O64: FGD | P64: MIX | Q64: In-person-Client Location | R64: Alignment | S64: Positive | T64: HRBP;Delivery; | U64: NA | V64: Low | W64: Closed | X64: New Joiner Connect (30 Days) | Y64: Coverage | Z64: 1 | AA64: Role Expectation Clarity
A65: 13 | B65: 46166.878 | C65: 46166.892 | D65: TR519093@techmahindra.com | E65: Turvi Raghavan | F65: Turvi Raghavan | G65: 519093 | H65: 46149 | I65: DEA Service Line | J65: IBU Specific Connect | K65: Hyderbad | L65: DEA-D-2006 | M65: DEA-D-4040 | N65: New Joiner Connect - 60 days | O65: FGD | P65: MIX | Q65: In-person-Client Location | R65: Alignment | S65: Positive | T65: HRBP;Delivery; | U65: NA | V65: Low | W65: Closed | X65: New Joiner Connect (30 Days) | Y65: Coverage | Z65: 2 | AA65: Initial Engagement Level
A66: 13 | B66: 46166.878 | C66: 46166.892 | D66: TR519093@techmahindra.com | E66: Turvi Raghavan | F66: Turvi Raghavan | G66: 519093 | H66: 46149 | I66: DEA Service Line | J66: IBU Specific Connect | K66: Hyderbad | L66: DEA-D-2006 | M66: DEA-D-4040 | N66: New Joiner Connect - 60 days | O66: FGD | P66: MIX | Q66: In-person-Client Location | R66: Alignment | S66: Positive | T66: HRBP;Delivery; | U66: NA | V66: Low | W66: Closed | X66: New Joiner Connect (30 Days) | Y66: Key Insight | Z66: 1 | AA66: Most of the associates are undergoing trainings as there are FCTP's
A67: 13 | B67: 46166.878 | C67: 46166.892 | D67: TR519093@techmahindra.com | E67: Turvi Raghavan | F67: Turvi Raghavan | G67: 519093 | H67: 46149 | I67: DEA Service Line | J67: IBU Specific Connect | K67: Hyderbad | L67: DEA-D-2006 | M67: DEA-D-4040 | N67: New Joiner Connect - 60 days | O67: FGD | P67: MIX | Q67: In-person-Client Location | R67: Alignment | S67: Positive | T67: HRBP;Delivery; | U67: NA | V67: Low | W67: Closed | X67: New Joiner Connect (30 Days) | Y67: Key Insight | Z67: 2 | AA67: Delay or lack of clarity in project onboarding
A68: 13 | B68: 46166.878 | C68: 46166.892 | D68: TR519093@techmahindra.com | E68: Turvi Raghavan | F68: Turvi Raghavan | G68: 519093 | H68: 46149 | I68: DEA Service Line | J68: IBU Specific Connect | K68: Hyderbad | L68: DEA-D-2006 | M68: DEA-D-4040 | N68: New Joiner Connect - 60 days | O68: FGD | P68: MIX | Q68: In-person-Client Location | R68: Alignment | S68: Positive | T68: HRBP;Delivery; | U68: NA | V68: Low | W68: Closed | X68: New Joiner Connect (30 Days) | Y68: Action Plan | Z68: 1 | AA68: Define timeline for project allocation (max 0 days)
A69: 13 | B69: 46166.878 | C69: 46166.892 | D69: TR519093@techmahindra.com | E69: Turvi Raghavan | F69: Turvi Raghavan | G69: 519093 | H69: 46149 | I69: DEA Service Line | J69: IBU Specific Connect | K69: Hyderbad | L69: DEA-D-2006 | M69: DEA-D-4040 | N69: New Joiner Connect - 60 days | O69: FGD | P69: MIX | Q69: In-person-Client Location | R69: Alignment | S69: Positive | T69: HRBP;Delivery; | U69: NA | V69: Low | W69: Closed | X69: New Joiner Connect (30 Days) | Y69: Action Plan | Z69: 2 | AA69: Ensure weekly : connect with manager
A70: 14 | B70: 46083.069 | C70: 46083.078 | D70: EB753425@techmahindra.com | E70: Ekta Bhalla | F70: Ekta Bhalla | G70: 753425 | H70: 46080 | I70: DEA Service Line | J70: IBU Specific Connect | K70: PUNE | L70: DEA-D-4026 | M70: DEA-D-4019 | N70: Scotia | O70: Floor Connect | P70: MIX | Q70: Virtual | R70: Empowerment | S70: Neutral | T70: Delivery; | V70: Low | W70: Closed | X70: Women Associate Connect | Y70: Coverage | Z70: 1 | AA70: Learning & Skill Building
A71: 14 | B71: 46083.069 | C71: 46083.078 | D71: EB753425@techmahindra.com | E71: Ekta Bhalla | F71: Ekta Bhalla | G71: 753425 | H71: 46080 | I71: DEA Service Line | J71: IBU Specific Connect | K71: PUNE | L71: DEA-D-4026 | M71: DEA-D-4019 | N71: Scotia | O71: Floor Connect | P71: MIX | Q71: Virtual | R71: Empowerment | S71: Neutral | T71: Delivery; | V71: Low | W71: Closed | X71: Women Associate Connect | Y71: Coverage | Z71: 2 | AA71: Grievance/speak-up Clarity
A72: 14 | B72: 46083.069 | C72: 46083.078 | D72: EB753425@techmahindra.com | E72: Ekta Bhalla | F72: Ekta Bhalla | G72: 753425 | H72: 46080 | I72: DEA Service Line | J72: IBU Specific Connect | K72: PUNE | L72: DEA-D-4026 | M72: DEA-D-4019 | N72: Scotia | O72: Floor Connect | P72: MIX | Q72: Virtual | R72: Empowerment | S72: Neutral | T72: Delivery; | V72: Low | W72: Closed | X72: Women Associate Connect | Y72: Coverage | Z72: 3 | AA72: Inclusive Team Practices
A73: 14 | B73: 46083.069 | C73: 46083.078 | D73: EB753425@techmahindra.com | E73: Ekta Bhalla | F73: Ekta Bhalla | G73: 753425 | H73: 46080 | I73: DEA Service Line | J73: IBU Specific Connect | K73: PUNE | L73: DEA-D-4026 | M73: DEA-D-4019 | N73: Scotia | O73: Floor Connect | P73: MIX | Q73: Virtual | R73: Empowerment | S73: Neutral | T73: Delivery; | V73: Low | W73: Closed | X73: Women Associate Connect | Y73: Key Insight | Z73: 1 | AA73: Inclusive team practices
A74: 14 | B74: 46083.069 | C74: 46083.078 | D74: EB753425@techmahindra.com | E74: Ekta Bhalla | F74: Ekta Bhalla | G74: 753425 | H74: 46080 | I74: DEA Service Line | J74: IBU Specific Connect | K74: PUNE | L74: DEA-D-4026 | M74: DEA-D-4019 | N74: Scotia | O74: Floor Connect | P74: MIX | Q74: Virtual | R74: Empowerment | S74: Neutral | T74: Delivery; | V74: Low | W74: Closed | X74: Women Associate Connect | Y74: Action Plan | Z74: 1 | AA74: Promote DEI initiatives
A75: 14 | B75: 46083.069 | C75: 46083.078 | D75: EB753425@techmahindra.com | E75: Ekta Bhalla | F75: Ekta Bhalla | G75: 753425 | H75: 46080 | I75: DEA Service Line | J75: IBU Specific Connect | K75: PUNE | L75: DEA-D-4026 | M75: DEA-D-4019 | N75: Scotia | O75: Floor Connect | P75: MIX | Q75: Virtual | R75: Empowerment | S75: Neutral | T75: Delivery; | V75: Low | W75: Closed | X75: Women Associate Connect | Y75: Action Plan | Z75: 2 | AA75: There werenot much queries
A76: 15 | B76: 46075.604 | C76: 46075.621 | D76: DR188914@techmahindra.com | E76: Diya Rattan | F76: Diya Rattan | G76: 188914 | H76: 46055 | I76: DEA Service Line | J76: IBU Specific Connect | K76: Hyderabad | L76: DEA-D-4021 | M76: DEA-D-2007 | N76: Oracle HCM – UKG & Workday | O76: 1:1 | P76: MIX | Q76: Virtual | R76: Alignment | S76: Neutral | T76: No specific Action, Issue addressed in meeting; | U76: Bench guidelines are explained | V76: Low | W76: Closed | X76: SL Induction | Y76: Coverage | Z76: 1 | AA76: HR / WFM / Training Communication Effectiveness
A77: 15 | B77: 46075.604 | C77: 46075.621 | D77: DR188914@techmahindra.com | E77: Diya Rattan | F77: Diya Rattan | G77: 188914 | H77: 46055 | I77: DEA Service Line | J77: IBU Specific Connect | K77: Hyderabad | L77: DEA-D-4021 | M77: DEA-D-2007 | N77: Oracle HCM – UKG & Workday | O77: 1:1 | P77: MIX | Q77: Virtual | R77: Alignment | S77: Neutral | T77: No specific Action, Issue addressed in meeting; | U77: Bench guidelines are explained | V77: Low | W77: Closed | X77: SL Induction | Y77: Coverage | Z77: 2 | AA77: Business & Practice Awareness
A78: 15 | B78: 46075.604 | C78: 46075.621 | D78: DR188914@techmahindra.com | E78: Diya Rattan | F78: Diya Rattan | G78: 188914 | H78: 46055 | I78: DEA Service Line | J78: IBU Specific Connect | K78: Hyderabad | L78: DEA-D-4021 | M78: DEA-D-2007 | N78: Oracle HCM – UKG & Workday | O78: 1:1 | P78: MIX | Q78: Virtual | R78: Alignment | S78: Neutral | T78: No specific Action, Issue addressed in meeting; | U78: Bench guidelines are explained | V78: Low | W78: Closed | X78: SL Induction | Y78: Key Insight | Z78: 1 | AA78: HR/WFM/Training updates not actionable
A79: 15 | B79: 46075.604 | C79: 46075.621 | D79: DR188914@techmahindra.com | E79: Diya Rattan | F79: Diya Rattan | G79: 188914 | H79: 46055 | I79: DEA Service Line | J79: IBU Specific Connect | K79: Hyderabad | L79: DEA-D-4021 | M79: DEA-D-2007 | N79: Oracle HCM – UKG & Workday | O79: 1:1 | P79: MIX | Q79: Virtual | R79: Alignment | S79: Neutral | T79: No specific Action, Issue addressed in meeting; | U79: Bench guidelines are explained | V79: Low | W79: Closed | X79: SL Induction | Y79: Key Insight | Z79: 2 | AA79: NA
A80: 15 | B80: 46075.604 | C80: 46075.621 | D80: DR188914@techmahindra.com | E80: Diya Rattan | F80: Diya Rattan | G80: 188914 | H80: 46055 | I80: DEA Service Line | J80: IBU Specific Connect | K80: Hyderabad | L80: DEA-D-4021 | M80: DEA-D-2007 | N80: Oracle HCM – UKG & Workday | O80: 1:1 | P80: MIX | Q80: Virtual | R80: Alignment | S80: Neutral | T80: No specific Action, Issue addressed in meeting; | U80: Bench guidelines are explained | V80: Low | W80: Closed | X80: SL Induction | Y80: Action Plan | Z80: 1 | AA80: Create consistent onboarding framework across practice
